Workbook
Name 会社保険率: 'テーブル定義-社会'!$B$95
Name 健康・介護保険料額: 'テーブル定義-社会'!$B$136
Name 雇用保険料額: 'テーブル定義-社会'!$B$502
Name 厚生年金料額: 'テーブル定義-社会'!$B$227
Name 事業所整理記号情報: 'テーブル定義-社会'!$B$442
Name 退職金計算項目: 'テーブル定義-社会'!$B$667
Name 退職金計算書設定: 'テーブル定義-社会'!$B$704
Name 退職金計算書設定詳細: 'テーブル定義-社会'!$B$729
Name 退職金項目: 'テーブル定義-社会'!$B$624
Name 退職金体系: 'テーブル定義-社会'!$B$592
Name 退職金明細書設定: 'テーブル定義-社会'!$B$766
Name 退職金明細書設定詳細: 'テーブル定義-社会'!$B$791
Name 届出基本: 'テーブル定義-社会'!$C$333

Sheet 表紙
A2: データベース定義書
B4: ユーザー | C4: 株式会社エフエム
B5: プロジェクト | C5: SociaX
B6: インスタンス | C6: テナント別
B7: システム | C7: 給与管理
B11: 作成日 | C11: 46008
B12: 作成者 | C12: ISI王
B13: 更新日 | C13: =改定履歴!J5 -> 46008
B14: 更新者 | C14: =改定履歴!K5 -> ISI王
D16: ©株式会社エフエム

Sheet 表定義の見直しについて
A1: =表紙!A2 -> データベース定義書 | C1: 表定義の見直しについて | I1: 版 | J1: 年月日 | K1: 作成/更新者
A2: =表紙!B4 -> ユーザー | B2: =表紙!C4 -> 株式会社エフエム | I2: 初 | J2: =表紙!C11 -> 46008 | K2: =表紙!C12 -> ISI王
A3: =表紙!B5 -> プロジェクト | B3: =表紙!C5 -> SociaX
A4: =表紙!B6 -> インスタンス | B4: =表紙!C6 -> テナント別
A5: =表紙!B7 -> システム | B5: =表紙!C7 -> 給与管理 | I5: 最終
A7: チケットNo. | C7: 改訂内容 | I7: 版 | J7: 改訂日付 | K7: 改訂者
A8: #220435 | C8: 社員管理の表は以下チケットを起点に見直しを行っています
C9: #218603 テーブル・カラム名 全面見直し
D10: 資料
E11: #218603 テーブル・カラム名 全面見直し - 資料.xlsx
E12: #218603 テーブル・カラム名 全面見直し - 資料.pptx
D14: テーブル名の見直し
E15: 主な修正点
F16: 表名自体の最適化
H17: 慣習性が高い語句を含め、データとして格納される内容を端的に表現できるようにします
F18: 日本語のローマ字表記を廃止
H19: 但し、旧Sociaで慣習性が高い以下のキーワードは日本語として残している
H20: 会社 kaisya
H21: 社員 syain
H22: など
F23: プレフィックスの廃止
D25: 列名の見直し
E26: 主な修正点
F27: 日本語のローマ字表記を廃止
H28: 但し、旧Sociaで慣習性が高い以下のキーワードは日本語として残している
H29: 社員連番 syainseq
H30: 会社コード kaisyacd
H31: など
D33: テーブル定義の見直し
E34: データの構成は一度精査し、非正規化への戻しも含めデータ構造のバランスを取りながらテーブル定義を再編します
D36: 本稼働が行われるまでは修正内容が確認できるようにします
H37: 可能な限り旧定義を残して、修正、削除などが行われたことがわかるようにしておく
A39: #220435 | B39: 共通 | D39: ナチュラルキーとサロゲートキーの分け方 | J39: 45616 | K39: CSM栗原
E40: ナチュラルキー
H41: キーそのものに業務的な意味が含まれており、意図的にユニークに定義されているもの。エンドユーザー側で定義される
H42: 例) 会社コード、組織コード、郵便番号、社員番号(本来は)
E43: サロゲートキー
H44: 業務的は意味を持つ値ではなく、システム上ユニークになるように連番が設定されるもの
H45: 例) 社員連番、性別ID(ないけど)、家族の連番(並び順は別)
E46: Sociaではエンドユーザーが定義するケースが多いナチュラルキーを優先して使用します
E47: 現定義でナチュラルキーとサロゲートキーが混在している場合、サロゲートキーを排除する可能性があります
E48: 但し、副表参照キーとしてあえてナチュラルキーとサロゲートキーを混在させるなど、許容するべきケースはありますので定義内に必ず説明を付与してください
A51: #220436 | B51: 共通 | D51: 有効/無効と表示/非表示の違い | J51: 45620 | K51: CSM栗原
E52: 有効/無効
H53: データに履歴がない(fromymd/toymdを持たない)場合に使用
H54: 列は 無効フラグ disabled false:有効 true:無効
E55: 表示/非表示
H56: データに履歴がある(fromymd/toymdを持っている)場合に使用
H57: 列は 非表示フラグ hidden false:表示 true:非表示
D62: 本稼働時には修正内容は破棄し正式版として綺麗な形で資料を残します

Sheet 論理データモデル
A1: =表紙!A2 -> データベース定義書 | C1: 論理データモデル | E1: 版 | F1: 年月日 | G1: 作成/更新者
A2: =表紙!B4 -> ユーザー | B2: =表紙!C4 -> 株式会社エフエム | E2: 初 | F2: =表紙!C11 -> 46008 | G2: =表紙!C12 -> ISI王
A3: =表紙!B5 -> プロジェクト | B3: =表紙!C5 -> SociaX
A4: =表紙!B6 -> インスタンス | B4: =表紙!C6 -> テナント別
A5: =表紙!B7 -> システム | B5: =表紙!C7 -> 給与管理 | E5: 最終 | F5: =表紙!C13 -> 46008 | G5: =表紙!C14 -> ISI王

Sheet 改定履歴
A1: =表紙!A2 -> データベース定義書 | C1: 改訂履歴 | I1: 版 | J1: 年月日 | K1: 作成/更新者
A2: =表紙!B4 -> ユーザー | B2: =表紙!C4 -> 株式会社エフエム | I2: 初 | J2: =表紙!C11 -> 46008 | K2: =表紙!C12 -> ISI王
A3: =表紙!B5 -> プロジェクト | B3: =表紙!C5 -> SociaX
A4: =表紙!B6 -> インスタンス | B4: =表紙!C6 -> テナント別
A5: =表紙!B7 -> システム | B5: =表紙!C7 -> 給与管理 | I5: 最終 | J5: =MAX($J$8:$J$925) -> 46008 | K5: =VLOOKUP(J5,$J$8:$K$925,2,FALSE) -> ISI王
A7: チケットNo. | B7: シート名 | C7: 改訂内容 | I7: 版 | J7: 改訂日付 | K7: 改訂者
A8: #220435 | B8: 全体 | C8: 初版 | F8: 作成開始。表紙とテーブル一覧の作成 | J8: 46008 | K8: ISI王

Sheet 退職金支給 (2)
A1: テーブル情報
B2: システム名 | C2: SOCIA | E2: 作成者 | I2: ITSP | M2: テーブル一覧へ
B3: サブシステム名 | C3: 給与 | E3: 作成日 | I3: 2025-11-28
B4: スキーマ名 | E4: RDBMS | I4: MySQL
B5: 論理テーブル名 | C5: 退職金支給 | E5: ENGINE | I5: InnoDB
B6: 物理テーブル名 | C6: retirement_pay_payment | E6: CHARSET | I6: utf8mb4
B7: 備考
A12: カラム情報 | L12: 外部キー情報
A13: No | B13: 論理名 | C13: 物理名 | D13: データ型 | E13: Size | F13: Not Null | G13: PK | H13: UK | I13: デフォルト | J13: 備考 | L13: 親テーブル | M13: 参照カラム
A14: 1 | B14: 社員連番 | C14: syainseq | D14: bigint | F14: not null | G14: 〇
A15: 2 | B15: 退職年月日 | C15: retirement_date | D15: date | F15: not null | G15: 〇
A16: 3 | B16: 社員コード | C16: syaincd | D16: varchar | E16: 20
A17: 4 | B17: 氏名 | C17: name | D17: varchar | E17: 255
A18: 5 | B18: 支給確定年月日 | C18: payment_confirm_date | D18: date | F18: not null
A19: 6 | B19: 支給年月日 | C19: payment_date | D19: date
A20: 7 | B20: 勤続期間開始年月日 | C20: tenure_period_fromymd | D20: date | F20: not null
A21: 8 | B21: 勤続期間終了年月日 | C21: tenure_period_toymd | D21: date | F21: not null
A22: 9 | B22: 勤続年数 | C22: tenure_year_count | D22: tinyint | F22: not null
A23: 10 | B23: 退職一時金区分 | C23: retirement_temporary_amount_type | D23: tinyint | F23: not null
A24: 11 | B24: 退職一時金額 | C24: retirement_temporary_amount | D24: bigint | F24: not null
A25: 12 | B25: 退職所得控除額 | C25: retirement_income_deduction_amount | D25: bigint | F25: not null
A26: 13 | B26: 源泉徴収税額 | C26: withholding_tax_amount | D26: bigint | F26: not null
A27: 14 | B27: 市町村民税額 | C27: municipalities_resident_tax | D27: bigint | F27: not null
A28: 15 | B28: 道府県民税額 | C28: prefecture_resident_tax | D28: bigint | F28: not null
A29: 16 | B29: 住民税清算額 | C29: resident_tax_settlement_amount | D29: bigint
A30: 17 | B30: 申告書提出区分 | C30: tax_return_filing_type | D30: tinyint | F30: not null
A31: 18 | B31: 障害退職区分 | C31: disability_retirement_type | D31: tinyint | F31: not null
A32: 19 | B32: 税計算区分 | C32: tax_equation_type | D32: tinyint | F32: not null
A33: 20 | B33: 源泉徴収税区分 | C33: withholding_tax_type | D33: tinyint | F33: not null
A34: 21 | B34: 源泉徴収摘要欄 | C34: withholding_summary_ran | D34: varchar | E34: 100
A35: 22 | B35: 差引支給額 | C35: deduct_payment_amount | D35: bigint | F35: not null
A36: 23 | B36: 特定役員 | C36: specific_officer | D36: tinyint | F36: not null
A37: 24 | B37: 作成者 | C37: created_by | D37: bigint | F37: not null
A38: 25 | B38: 作成日時 | C38: created_at | D38: datetime | E38: 6 | F38: not null
A39: 26 | B39: 更新者 | C39: updated_by | D39: bigint | F39: not null
A40: 27 | B40: 更新日時 | C40: updated_at | D40: datetime | E40: 6 | F40: not null

Sheet テーブル一覧ISI
A1: =表紙!A2 -> データベース定義書 | C1: テーブル一覧 | E1: 版 | F1: 年月日 | G1: 作成/更新者
A2: =表紙!B4 -> ユーザー | B2: =表紙!C4 -> 株式会社エフエム | E2: 初 | F2: =表紙!C11 -> 46008 | G2: =表紙!C12 -> ISI王
A3: =表紙!B5 -> プロジェクト | B3: =表紙!C5 -> SociaX
A4: =表紙!B6 -> インスタンス | B4: =表紙!C6 -> テナント別
A5: =表紙!B7 -> システム | B5: =表紙!C7 -> 給与管理 | E5: 最終 | F5: =表紙!C13 -> 46008 | G5: =表紙!C14 -> ISI王
A7: 社会
A8: No. | B8: 論理テーブル名 | C8: 物理テーブル名 | D8: 備考 | F8: 改訂日付 | G8: 改訂者
A9: 1 | B9: 健康・介護保険料額パターン | C9: health_care_insurance_amount_pattern | F9: 46054 | G9: ISI王
A10: =A9+1 -> 2 | B10: 健康・介護保険料額 | C10: health_care_insurance_amount | F10: 46008 | G10: ISI王
A11: =A10+1 -> 3 | B11: 厚生年金料額パターン | C11: kosei_pension_amount_pattern
A12: =A11+1 -> 4 | B12: 厚生年金料額 | C12: kosei_pension_amount
A13: =A12+1 -> 5 | B13: 届出基本 | C13: submission_basic | F13: 46019 | G13: ISI王
A14: =A13+1 -> 6 | B14: 健康・介護保険料額 | C14: health_care_insurance_amount | F14: 46008 | G14: ISI王
A15: =A14+1 -> 7 | B15: 事業所整理記号情報 | C15: office_arrangement_mark_info | F15: 46009 | G15: ISI王
A16: =A15+1 -> 8 | B16: 会社保険率 | C16: kaisya_insurance_rate | F16: 46009 | G16: ISI王
A17: =A16+1 -> 9 | B17: 厚生年金料額 | C17: kosei_pension_amount | F17: 46019 | G17: ISI王
A18: =A17+1 -> 10 | B18: 雇用保険料額 | C18: employment_insurance_amount | F18: 46019 | G18: ISI王
A19: =A18+1 -> 11 | B19: 労災保険料率 | C19: employment_insurance_amount | F19: 46040 | G19: ISI王
A20: =A19+1 -> 12 | B20: 退職金体系 | C20: retirement_taikei | F20: 46034 | G20: ISI王
A21: =A20+1 -> 13 | B21: 退職金項目 | C21: retirement_item | F21: 46034 | G21: ISI王
A22: =A21+1 -> 14 | B22: 退職金計算項目 | C22: retirement_calc_item | F22: 46040 | G22: ISI王
A23: =A22+1 -> 15 | B23: 退職金計算書 | C23: retirement_calc_statement | F23: 46040 | G23: ISI王
A24: =A23+1 -> 16 | B24: 退職金計算書詳細 | C24: retirement_calc_statement_detail | F24: 46040 | G24: ISI王
... A26: =A25+1 -> 18 | B26: 退職金明細書詳細 | C26: retirement_calc_detail_statement_detail | F26: 46040 | G26: ISI王
A27: =A26+1 -> 19
A28: =A27+1 -> 20

Sheet テーブル定義-社会
A1: =表紙!A2 -> データベース定義書 | D1: テーブル定義 | N1: 更新情報
A2: =表紙!B4 -> ユーザー | C2: =表紙!C4 -> 株式会社エフエム | N2: ="作成:"&TEXT(表紙!C11,"yyyy/mm/dd")&" "&表紙!C12 -> 作成:2025/12/17 ISI王
A3: =表紙!B5 -> プロジェクト | C3: =表紙!C5 -> SociaX
A4: =表紙!B6 -> インスタンス | C4: =表紙!C6 -> テナント別
A5: =表紙!B7 -> システム | C5: =表紙!C7 -> 給与管理 | N5: ="更新:"&TEXT(表紙!C13,"yyyy/mm/dd")&" "&表紙!C14 -> 更新:2025/12/17 ISI王
A7: No. | B7: 論理テーブル名 | C7: 物理テーブル名 | D7: 説明
A8: 14 | B8: 給与会社マスタ | C8: kyuyo_kaisya_master
B9: RDBMS | C9: MySQL
B10: ENGINE | C10: InnoDB
B11: CHARSET | C11: utf8mb4
B13: 作成日 / 作成者 | C13: 2026/01/18 王
B14: 更新日 / 更新者
A16: No, | B16: 論理名 | C16: 物理名 | D16: データ型 | E16: サイズ | F16: NOT NULL | G16: PK | H16: UK | I16: 索引123 | L16: デフォルト | M16: 関連/参照キー | N16: 列とコードの説明 / 備考
A17: 1 | B17: 会社コード | C17: kaisyacd | D17: varchar | E17: 10 | F17: not null | G17: 〇
A18: =A17+1 -> 2 | B18: 有効開始年月日 | C18: fromymd | D18: date | F18: not null | G18: 〇
A19: =A18+1 -> 3 | B19: 有効終了年月日 | C19: toymd | D19: date | F19: not null
A20: =A19+1 -> 4 | B20: 項目区分 | C20: item_type | D20: tinyint | F20: not null | N20: 1:全般 2:届出の管理 3:情報公開設定 4:計算区分 5:社会保険(共通) 6:健保料率パターン 7:厚年料率パターン 8:労災料率パターン 9:代表者パターン 10:連絡者パターン 11:金融機関パターン
A21: =A20+1 -> 5 | B21: 定年年齢 | C21: retirement_age | D21: smallint
A22: =A21+1 -> 6 | B22: 届出の利用 | C22: use_submission | D22: boolean | N22: true:利用する false:利用しない
A23: =A22+1 -> 7 | B23: 届出許可項目設定区分 | C23: submission_authorized Item_type | D23: tinyint | N23: 1:すべて許可 2:限定する
A24: =A23+1 -> 8 | B24: 届出許可項目設定格納値JSON | C24: submission_authorized Item_store_json | D24: json
A25: =A24+1 -> 9 | B25: 給与支給明細書・設定区分 | C25: kyuyo_pay_slip_use_type | D25: tinyint | N25: 1:既定値 2:届出内共通
A26: =A25+1 -> 10 | B26: 給与支給明細書・支給日前公開日数 | C26: kyuyo_pay_slip_before_pay_open_days | D26: smallint
A27: =A26+1 -> 11 | B27: 給与支給明細書・公開除外日 | C27: kyuyo_pay_slip_excluded_days | D27: json | N27: {["name":"月","value":0/1], ["name":"火","value":0/1], ["name":"水","value":0/1], ["name":"木","value":0/1], ["name":"金","value":0/1], ["name":"土","value":0/1], ["name":"日","value":0/1], ["name":"祝","value":0/1]}
A28: =A27+1 -> 12 | B28: 賞与支給明細書・設定区分 | C28: syoyo_pay_slip_use_type | D28: tinyint | N28: 1:既定値 2:届出内共通
A29: =A28+1 -> 13 | B29: 賞与支給明細書・支給日前公開日数 | C29: syoyo_pay_slip_before_pay_open_days | D29: smallint
A30: =A29+1 -> 14 | B30: 賞与支給明細書・公開除外日 | C30: syoyo_pay_slip_excluded_days | D30: json | N30: {["name":"月","value":0/1], ["name":"火","value":0/1], ["name":"水","value":0/1], ["name":"木","value":0/1], ["name":"金","value":0/1], ["name":"土","value":0/1], ["name":"日","value":0/1], ["name":"祝","value":0/1]}
A31: =A30+1 -> 15 | B31: 臨時給与支給明細書・設定区分 | C31: rinji_pay_slip_use_type | D31: tinyint | N31: 1:既定値 2:届出内共通
A32: =A31+1 -> 16 | B32: 臨時給与支給明細書・支給日前公開日数 | C32: rinji_pay_slip_before_pay_open_days | D32: smallint
A33: =A32+1 -> 17 | B33: 臨時給与支給明細書・公開除外日 | C33: rinji_pay_slip_excluded_days | D33: json | N33: {["name":"月","value":0/1], ["name":"火","value":0/1], ["name":"水","value":0/1], ["name":"木","value":0/1], ["name":"金","value":0/1], ["name":"土","value":0/1], ["name":"日","value":0/1], ["name":"祝","value":0/1]}
A34: =A33+1 -> 18 | B34: 退職金支給明細書・設定区分 | C34: retirement_pay_slip_use_type | D34: tinyint | N34: 1:既定値 2:届出内共通
A35: =A34+1 -> 19 | B35: 退職金支給明細書・支給前公開日数 | C35: retirement_pay_slip_before_pay_open_days | D35: smallint
A36: =A35+1 -> 20 | B36: 退職金支給明細書・公開除外日 | C36: retirement_pay_slip_excluded_days | D36: json | N36: {["name":"月","value":0/1], ["name":"火","value":0/1], ["name":"水","value":0/1], ["name":"木","value":0/1], ["name":"金","value":0/1], ["name":"土","value":0/1], ["name":"日","value":0/1], ["name":"祝","value":0/1]}
A37: =A36+1 -> 21 | B37: 退職金計算書・設定区分 | C37: retirement_calc_statement_use_type | D37: tinyint | N37: 1:既定値 2:届出内共通
A38: =A37+1 -> 22 | B38: 退職金計算書・支給前公開日数 | C38: retirement_calc_statement_before_pay_open_days | D38: smallint
A39: =A38+1 -> 23 | B39: 退職金計算書・公開除外日 | C39: retirement_calc_statement_excluded_days | D39: json | N39: {["name":"月","value":0/1], ["name":"火","value":0/1], ["name":"水","value":0/1], ["name":"木","value":0/1], ["name":"金","value":0/1], ["name":"土","value":0/1], ["name":"日","value":0/1], ["name":"祝","value":0/1]}
A40: =A39+1 -> 24 | B40: 退職給所得源泉徴収書・設定区分 | C40: retirement_withholding Statement_use_type | D40: tinyint | N40: 1:既定値 2:届出内共通
A41: =A40+1 -> 25 | B41: 退職給所得源泉徴収書・支給前公開日数 | C41: retirement_withholding Statement_before_pay_open_days | D41: smallint
A42: =A41+1 -> 26 | B42: 退職給所得源泉徴収書・公開除外日 | C42: retirement_withholding Statement_excluded_days | D42: json | N42: {["name":"月","value":0/1], ["name":"火","value":0/1], ["name":"水","value":0/1], ["name":"木","value":0/1], ["name":"金","value":0/1], ["name":"土","value":0/1], ["name":"日","value":0/1], ["name":"祝","value":0/1]}
A43: =A33+1 -> 18 | B43: 休職者計算区分 | C43: leave_employee_calc type | D43: tinyint | N43: 1:計算する 2:計算しない
A44: =A43+1 -> 19 | B44: 退職者計算区分 | C44: retirement_calc type | D44: tinyint | N44: 1:計算する 2:計算しない
A45: =A43+1 -> 19 | B45: 健康・介護保険料率パターン | C45: health_care_insurance_rate_pattern_id | M45: health_care_insurance_rate_pattern.pattern_id
A46: =A45+1 -> 20 | B46: 厚生年金料率パターン | C46: kosei_pension_rate_pattern_id | M46: kosei_pension_rate_pattern.pattern_id
A47: =A46+1 -> 21 | B47: 労災保険料率パターン | C47: rosai_insurance_rate_pattern_id | M47: rosai_insurance_rate_pattern.pattern_id
A48: =A47+1 -> 22 | B48: 代表者パターン | C48: _pattern_id | M48: _pattern_id
A49: =A48+1 -> 23 | B49: 連絡者パターン | C49: _pattern_id | M49: _pattern_id
A50: =A49+1 -> 24 | B50: 金融機関パターン | C50: _pattern_id | M50: _pattern_id
A51: =A50+1 -> 25 | B51: 並び順 | C51: sort_order | D51: bigint | F51: not null
A52: =A51+1 -> 26 | B52: 作成者 | C52: created_by | D52: bigint | F52: not null | M52: accounts.accountid | N52: 新規登録者のアカウントid
A53: =A52+1 -> 27 | B53: 作成日時 | C53: created_at | D53: datetime(6) | F53: not null | L53: 備考参照 | N53: 新規登録時にタイムスタンプを登録 CURRENT_TIMESTAMP
A54: =A53+1 -> 28 | B54: 更新者 | C54: updated_by | D54: bigint | F54: not null | M54: accounts.accountid | N54: 更新者のアカウントid
A55: =A54+1 -> 29 | B55: 更新日時 | C55: updated_at | D55: datetime(6) | F55: not null | L55: 備考参照 | N55: 更新時にタイムスタンプを登録 DEFAULT 0 ON UPDATE CURRENT_TIMESTAMP
A66: No. | B66: 論理テーブル名 | C66: 物理テーブル名 | D66: 説明
A67: 1 | B67: 健康・介護保険料率パターン | C67: health_care_insurance_rate_pattern
B68: RDBMS | C68: MySQL
B69: ENGINE | C69: InnoDB
B70: CHARSET | C70: utf8mb4
B72: 作成日 / 作成者 | C72: 2026/02/06 王
B73: 更新日 / 更新者
A75: No, | B75: 論理名 | C75: 物理名 | D75: データ型 | E75: サイズ | F75: NOT NULL | G75: PK | H75: UK | I75: 索引123 | L75: デフォルト | M75: 関連/参照キー | N75: 列とコードの説明 / 備考
A76: 1 | B76: 会社コード | C76: kaisyacd | D76: varchar | E76: 10 | F76: not null | G76: 〇
A77: =A76+1 -> 2 | B77: パターンID | C77: pattern_id | D77: bigint | F77: not null | G77: 〇
A78: =A77+1 -> 3 | B78: パターン名称 | C78: pattern_name | D78: varchar | E78: 255 | F78: not null | P78: テーブル情報 | AA78: テーブル情報
A79: =A78+1 -> 4 | B79: パターン略称 | C79: pattern_shortname | D79: varchar | E79: 255 | P79: システム名 | Q79: SOCIA | S79: 作成者 | W79: ITSP | AA79: システム名 | AB79: SOCIA | AD79: 作成者 | AH79: ITSP
A80: =A79+1 -> 5 | B80: 外国語名称１ | C80: alt1_name | D80: varchar | E80: 255 | P80: サブシステム名 | Q80: 給与 | S80: 作成日 | W80: 2025-11-28 | AA80: サブシステム名 | AB80: 給与 | AD80: 作成日 | AH80: 2025-11-28
A81: =A80+1 -> 6 | B81: 外国語名称２ | C81: alt2_name | D81: varchar | E81: 255 | P81: スキーマ名 | S81: RDBMS | W81: MySQL | AA81: スキーマ名 | AD81: RDBMS | AH81: MySQL
A82: =A81+1 -> 7 | B82: 外国語略称１ | C82: alt1_short_name | D82: varchar | E82: 255 | P82: 論理テーブル名 | Q82: 会社保険率 | S82: ENGINE | W82: InnoDB | AA82: 論理テーブル名 | AB82: 会社端数処理情報 | AD82: ENGINE | AH82: InnoDB
A83: =A82+1 -> 8 | B83: 外国語略称２ | C83: alt2_short_name | D83: varchar | E83: 255 | P83: 物理テーブル名 | Q83: kaisya_insurance_rate | S83: CHARSET | W83: utf8mb4 | AA83: 物理テーブル名 | AB83: kaisya_fraction_process_info | AD83: CHARSET | AH83: utf8mb4
A84: =A83+1 -> 9 | B84: 並び順 | C84: sort_order | D84: bigint | F84: not null | P84: 備考 | AA84: 備考
A85: =A84+1 -> 10 | B85: 非表示フラグ | C85: hidden | D85: boolean | F85: not null | L85: FALSE | N85: false:表示 true:非表示
A86: =A85+1 -> 11 | B86: 備考 | C86: notes | D86: text
A87: =A86+1 -> 12 | B87: 作成者 | C87: created_by | D87: bigint | F87: not null | M87: accounts.accountid | N87: 新規登録者のアカウントid
A88: =A87+1 -> 13 | B88: 作成日時 | C88: created_at | D88: datetime(6) | F88: not null | L88: 備考参照 | N88: 新規登録時にタイムスタンプを登録 CURRENT_TIMESTAMP | P88: カラム情報 | AA88: カラム情報
A89: =A88+1 -> 14 | B89: 更新者 | C89: updated_by | D89: bigint | F89: not null | M89: accounts.accountid | N89: 更新者のアカウントid | P89: No | Q89: 論理名 | R89: 物理名 | S89: データ型 | T89: Size | U89: Not Null | V89: PK | W89: UK | X89: デフォルト | Y89: 備考 | AA89: No | AB89: 論理名 | AC89: 物理名 | AD89: データ型 | AE89: Size | AF89: Not Null | AG89: PK | AH89: UK | AI89: デフォルト | AJ89: 備考
A90: =A89+1 -> 15 | B90: 更新日時 | C90: updated_at | D90: datetime(6) | F90: not null | L90: 備考参照 | N90: 更新時にタイムスタンプを登録 DEFAULT 0 ON UPDATE CURRENT_TIMESTAMP | P90: 1 | Q90: 会社コード | R90: kaisyacd | S90: varchar | T90: 20 | U90: not null | V90: 〇 | AA90: 1 | AB90: 会社コード | AC90: kaisyacd | AD90: varchar | AE90: 20 | AF90: not null | AG90: 〇
P91: 2 | Q91: 届出コード | R91: submission_code | S91: varchar | T91: 20 | U91: not null | V91: 〇 | AA91: 2 | AB91: 届出コード | AC91: submission_code | AD91: varchar | AE91: 20 | AF91: not null | AG91: 〇
P92: 3 | Q92: 有効開始年月日 | R92: fromymd | S92: date | U92: not null | V92: 〇 | AA92: 3 | AB92: 有効開始年月日 | AC92: fromymd | AD92: date | AF92: not null | AG92: 〇
P93: 4 | Q93: 有効終了年月日 | R93: toymd | S93: date | U93: not null | AA93: 4 | AB93: 有効終了年月日 | AC93: toymd | AD93: date | AF93: not null
A94: No. | B94: 論理テーブル名 | C94: 物理テーブル名 | D94: 説明 | AA94: 5 | AB94: 給与健康被保険者 | AC94: kyuyo_health_insured_person | AD94: tinyint | AJ94: コードマスタ.SQS0073
A95: 3 | B95: 健康・介護保険料率 | C95: health_care_insurance_rate | AA95: 6 | AB95: 給与健康事業主 | AC95: kyuyo_health_business_owner | AD95: tinyint | AJ95: コードマスタ.SQS0073
B96: RDBMS | C96: MySQL | P96: 5 | Q96: 給与健康率被保険者(基本) | R96: kyuyo_health_rate_insured_person_basic | S96: decimal | T96: 6,3 | U96: not null | AA96: 7 | AB96: 給与介護被保険者 | AC96: kyuyo_care_insured_person | AD96: tinyint | AJ96: コードマスタ.SQS0073
B97: ENGINE | C97: InnoDB | P97: 7 | Q97: 給与健康率事業主(基本) | R97: kyuyo_health_rate_business_owner_basic | S97: decimal | T97: 6,3 | U97: not null | AA97: 8 | AB97: 給与介護事業主 | AC97: kyuyo_care_business_owner | AD97: tinyint | AJ97: コードマスタ.SQS0073
B98: CHARSET | C98: utf8mb4 | P98: 6 | Q98: 給与健康率被保険者(特定) | R98: kyuyo_health_rate_insured_person_specific | S98: decimal | T98: 6,3 | U98: not null | AA98: 9 | AB98: 給与厚生年金被保険者 | AC98: kyuyo_kosei_pension_insured_person | AD98: tinyint | AJ98: コードマスタ.SQS0073
P99: 8 | Q99: 給与健康率事業主(特定) | R99: kyuyo_health_rate_business_owner_specific | S99: decimal | T99: 6,3 | U99: not null | AA99: 10 | AB99: 給与厚生年金事業主 | AC99: kyuyo_kosei_pension_business_owner | AD99: tinyint | AJ99: コードマスタ.SQS0073
B100: 作成日 / 作成者 | C100: 2026/02/06 王 | AA100: 11 | AB100: 給与厚生年金基金被保険者 | AC100: kyuyo_kosei_pension_fund_insured_person | AD100: tinyint | AJ100: コードマスタ.SQS0073
B101: 更新日 / 更新者 | AA101: 12 | AB101: 給与厚生年金基金事業主 | AC101: kyuyo_kosei_pension_fund_business_owner | AD101: tinyint | AJ101: コードマスタ.SQS0073
AA102: 13 | AB102: 賞与健康被保険者 | AC102: syoyo_health_insured_person | AD102: tinyint | AJ102: コードマスタ.SQS0073
A103: No, | B103: 論理名 | C103: 物理名 | D103: データ型 | E103: サイズ | F103: NOT NULL | G103: PK | H103: UK | I103: 索引123 | L103: デフォルト | M103: 関連/参照キー | N103: 列とコードの説明 / 備考 | AA103: 14 | AB103: 賞与健康事業主 | AC103: syoyo_health_business_owner | AD103: tinyint | AJ103: コードマスタ.SQS0073
A104: 1 | B104: 会社コード | C104: kaisyacd | D104: varchar | E104: 10 | F104: not null | G104: 〇 | O104: サイズ変更 | P104: 9 | Q104: 賞与健康率被保険者(基本) | R104: syoyo_health_rate_insured_person_basic | S104: decimal | T104: 6,3 | U104: not null | AA104: 15 | AB104: 賞与介護被保険者 | AC104: syoyo_care_insured_person | AD104: tinyint | AJ104: コードマスタ.SQS0073
A105: =A104+1 -> 2 | B105: パターンID | C105: pattern_id | D105: bigint | F105: not null | G105: 〇 | P105: 11 | Q105: 賞与健康率事業主(基本) | R105: syoyo_health_rate_business_owner_basic | S105: decimal | T105: 6,3 | U105: not null | AA105: 16 | AB105: 賞与介護事業主 | AC105: syoyo_care_business_owner | AD105: tinyint | AJ105: コードマスタ.SQS0073
A106: =A105+1 -> 3 | B106: 有効開始年月日 | C106: fromymd | D106: tinyint | F106: not null | G106: 〇 | P106: 10 | Q106: 賞与健康率被保険者(特定) | R106: syoyo_health_rate_insured_person_specific | S106: decimal | T106: 6,3 | U106: not null | AA106: 17 | AB106: 賞与厚生年金被保険者 | AC106: syoyo_kosei_pension_insured_person | AD106: tinyint | AJ106: コードマスタ.SQS0073
A107: =A106+1 -> 4 | B107: 有効終了年月日 | C107: toymd | D107: smallint | F107: not null | P107: 12 | Q107: 賞与健康率事業主(特定) | R107: syoyo_health_rate_business_owner_specific | S107: decimal | T107: 6,3 | U107: not null | AA107: 18 | AB107: 賞与厚生年金事業主 | AC107: syoyo_kosei_pension_business_owner | AD107: tinyint | AJ107: コードマスタ.SQS0073
A108: =A107+1 -> 5 | B108: 健康保険被保険者料率 | C108: health_insured_person_rate | D108: decimal | E108: 6,3 | F108: not null | O108: ←追加 | AA108: 19 | AB108: 賞与厚生年金基金被保険者 | AC108: syoyo_kosei_pension_fund_insured_person | AD108: tinyint | AJ108: コードマスタ.SQS0073
A109: =A108+1 -> 6 | B109: 健康保険事業主料率 | C109: health_business_owner_rate | D109: decimal | E109: 6,3 | F109: not null | O109: ←追加 | AA109: 20 | AB109: 賞与厚生年金基金事業主 | AC109: syoyo_kosei_pension_fund_business_owner | AD109: tinyint | AJ109: コードマスタ.SQS0073
A110: =A109+1 -> 7 | B110: 健康保険被保険者(基本)料率 | C110: health_insured_person_basic_rate | D110: decimal | E110: 6,3 | F110: not null | AA110: 21 | AB110: 給与健康被保険者(基本) | AC110: kyuyo_health_insured_person_basic | AD110: tinyint | AJ110: コードマスタ.SQS0073
A111: =A110+1 -> 8 | B111: 健康保険事業主(基本)料率 | C111: health_business_owner_basic_rate | D111: decimal | E111: 6,3 | F111: not null | AA111: 22 | AB111: 給与健康被保険者(特定) | AC111: kyuyo_health_insured_person_specific | AD111: tinyint | AJ111: コードマスタ.SQS0073
A112: =A111+1 -> 9 | B112: 健康保険被保険者(特定)料率 | C112: health_insured_person_specific_rate | D112: decimal | E112: 6,3 | F112: not null | AA112: 23 | AB112: 給与健康事業主(基本) | AC112: kyuyo_health_business_owner_basic | AD112: tinyint | AJ112: コードマスタ.SQS0073
A113: =A112+1 -> 10 | B113: 健康保険事業主(特定)料率 | C113: health_business_owner_specific_rate | D113: decimal | E113: 6,3 | F113: not null | AA113: 24 | AB113: 給与健康事業主(特定) | AC113: kyuyo_health_business_owner_specific | AD113: tinyint | AJ113: コードマスタ.SQS0073
A114: =A113+1 -> 11 | B114: 介護保険被保険者料率 | C114: care_insured_person_rate | D114: decimal | E114: 6,3 | F114: not null | O114: ←追加 | AA114: 25 | AB114: 賞与健康被保険者(基本) | AC114: syoyo_health_insured_person_basic | AD114: tinyint | AJ114: コードマスタ.SQS0073
A115: =A114+1 -> 12 | B115: 介護保険事業主料率 | C115: care_business_owner_rate | D115: decimal | E115: 6,3 | F115: not null | O115: ←追加 | AA115: 26 | AB115: 賞与健康被保険者(特定) | AC115: syoyo_health_insured_person_specific | AD115: tinyint | AJ115: コードマスタ.SQS0073
...

Sheet テーブル一覧
B1: テーブル一覧
B2: システム | C2: 論理テーブル名 | D2: 物理テーブル名 | I2: 論理名 | J2: 備考
D3: 用途 | E3: Sociaプロダクト | F3: データ種類 | G3: テーブル名 | H3: フルテーブル名
B4: 給与システム | C4: =HYPERLINK("#'"&I4&"'!A1",I4) -> v社員二以上事業所勤務情報 | G4: v_syain_multi_office_kinmu_info | H4: v_syain_multi_office_kinmu_info | I4: v社員二以上事業所勤務情報
B5: 給与システム | C5: =HYPERLINK("#'"&I5&"'!A1",I5) -> v社員介護保険 | G5: v_syain_care_insurance | H5: v_syain_care_insurance | I5: v社員介護保険
B6: 給与システム | C6: =HYPERLINK("#'"&I6&"'!A1",I6) -> v社員住民税納付先住所 | G6: v_syain_family_resident_tax_address | H6: v_syain_family_resident_tax_address | I6: v社員住民税納付先住所
B7: 給与システム | C7: =HYPERLINK("#'"&I7&"'!A1",I7) -> v社員体系 | G7: v_syain_taikei | H7: v_syain_taikei | I7: v社員体系
B8: 給与システム | C8: =HYPERLINK("#'"&I8&"'!A1",I8) -> v社員保険資格取得 | G8: v_syain_insurance_qualification_get | H8: v_syain_insurance_qualification_get | I8: v社員保険資格取得
B9: 給与システム | C9: =HYPERLINK("#'"&I9&"'!A1",I9) -> v社員保険資格喪失 | G9: v_syain_insurance_qualification_loss | H9: v_syain_insurance_qualification_loss | I9: v社員保険資格喪失
B10: 給与システム | C10: =HYPERLINK("#'"&I10&"'!A1",I10) -> v社員健康保険 | G10: v_syain_health_insurance | H10: v_syain_health_insurance | I10: v社員健康保険
B11: 給与システム | C11: =HYPERLINK("#'"&I11&"'!A1",I11) -> v社員厚生年金 | G11: v_syain_kosei_pension | H11: v_syain_kosei_pension | I11: v社員厚生年金
B12: 給与システム | C12: =HYPERLINK("#'"&I12&"'!A1",I12) -> v社員基本 | G12: v_syain_basic | H12: v_syain_basic | I12: v社員基本
B13: 給与システム | C13: =HYPERLINK("#'"&I13&"'!A1",I13) -> v社員家族 | G13: v_syain_family | H13: v_syain_family | I13: v社員家族
B14: 給与システム | C14: =HYPERLINK("#'"&I14&"'!A1",I14) -> v社員届出異動履歴 | G14: v_syain_submission_transfer_history | H14: v_syain_submission_transfer_history | I14: v社員届出異動履歴
B15: 給与システム | C15: =HYPERLINK("#'"&I15&"'!A1",I15) -> v社員社会保険関連個人情報 | G15: v_syain_syaho_personal_info | H15: v_syain_syaho_personal_info | I15: v社員社会保険関連個人情報
... B138: 給与システム | C138: =HYPERLINK("#'"&I138&"'!A1",I138) -> 項目 | G138: item | H138: item | I138: 項目

Sheet v社員二以上事業所勤務情報
A1: テーブル情報
B2: システム名 | C2: SOCIA | E2: 作成者 | I2: ITSP | M2: テーブル一覧へ
B3: サブシステム名 | C3: 給与 | E3: 作成日 | I3: 2025-11-28
B4: スキーマ名 | E4: RDBMS | I4: MySQL
B5: 論理テーブル名 | C5: v社員二以上事業所勤務情報 | E5: ENGINE | I5: InnoDB
B6: 物理テーブル名 | C6: v_syain_multi_office_kinmu_info | E6: CHARSET | I6: utf8mb4
B7: 備考
B8: 論理テーブル
A12: カラム情報 | L12: 外部キー情報
A13: No | B13: 論理名 | C13: 物理名 | D13: データ型 | E13: Size | F13: Not Null | G13: PK | H13: UK | I13: デフォルト | J13: 備考 | L13: 親テーブル | M13: 参照カラム
A14: 1 | B14: 社員連番 | C14: syainseq | D14: bigint | F14: not null | G14: 〇
A15: 2 | B15: 他社報酬合計 | C15: other_kaisya_reward_total | D15: bigint
A16: 3 | B16: 標準報酬月額 | C16: standard_reward_month_amount | D16: bigint
A17: 4 | B17: 改定年 | C17: revision_year | D17: smallint
A18: 5 | B18: 改定月 | C18: revision_month | D18: smallint
A19: 6 | B19: 作成者 | C19: created_by | D19: bigint | F19: not null
A20: 7 | B20: 作成日時 | C20: created_at | D20: datetime | E20: 6 | F20: not null
A21: 8 | B21: 更新者 | C21: updated_by | D21: bigint | F21: not null
A22: 9 | B22: 更新日時 | C22: updated_at | D22: datetime | E22: 6 | F22: not null

Sheet v社員介護保険
A1: テーブル情報
B2: システム名 | C2: SOCIA | E2: 作成者 | I2: ITSP | M2: テーブル一覧へ
B3: サブシステム名 | C3: 給与 | E3: 作成日 | I3: 2025-11-28
B4: スキーマ名 | E4: RDBMS | I4: MySQL
B5: 論理テーブル名 | C5: v社員介護保険 | E5: ENGINE | I5: InnoDB
B6: 物理テーブル名 | C6: v_syain_care_insurance | E6: CHARSET | I6: utf8mb4
B7: 備考
B8: 論理テーブル
A12: カラム情報 | L12: 外部キー情報
A13: No | B13: 論理名 | C13: 物理名 | D13: データ型 | E13: Size | F13: Not Null | G13: PK | H13: UK | I13: デフォルト | J13: 備考 | L13: 親テーブル | M13: 参照カラム
A14: 1 | B14: 社員連番 | C14: syainseq | D14: bigint | F14: not null | G14: 〇
A15: 2 | B15: 介護保険区分 | C15: care_insurance_type | D15: tinyint
A16: 3 | B16: 作成者 | C16: created_by | D16: bigint | F16: not null
A17: 4 | B17: 作成日時 | C17: created_at | D17: datetime | E17: 6 | F17: not null
A18: 5 | B18: 更新者 | C18: updated_by | D18: bigint | F18: not null
A19: 6 | B19: 更新日時 | C19: updated_at | D19: datetime | E19: 6 | F19: not null

Sheet v社員住民税納付先住所
A1: テーブル情報
B2: システム名 | C2: SOCIA | E2: 作成者 | I2: ITSP | M2: テーブル一覧へ
B3: サブシステム名 | C3: 給与 | E3: 作成日 | I3: 2025-11-28
B4: スキーマ名 | E4: RDBMS | I4: MySQL
B5: 論理テーブル名 | C5: v社員住民税納付先住所 | E5: ENGINE | I5: InnoDB
B6: 物理テーブル名 | C6: v_syain_family_resident_tax_address | E6: CHARSET | I6: utf8mb4
B7: 備考
B8: 論理テーブル
A12: カラム情報 | L12: 外部キー情報
A13: No | B13: 論理名 | C13: 物理名 | D13: データ型 | E13: Size | F13: Not Null | G13: PK | H13: UK | I13: デフォルト | J13: 備考 | L13: 親テーブル | M13: 参照カラム
A14: 1 | B14: 社員連番 | C14: syainseq | D14: bigint | F14: not null | G14: 〇
A15: 2 | B15: 地方自治体コード | C15: local_municipality_code | D15: varchar | E15: 20
A16: 3 | B16: 個人番号 | C16: my_number | D16: varchar | E16: 10
A17: 4 | B17: 作成者 | C17: created_by | D17: bigint | F17: not null
A18: 5 | B18: 作成日時 | C18: created_at | D18: datetime | E18: 6 | F18: not null
A19: 6 | B19: 更新者 | C19: updated_by | D19: bigint | F19: not null
A20: 7 | B20: 更新日時 | C20: updated_at | D20: datetime | E20: 6 | F20: not null

Sheet v社員体系
A1: テーブル情報
B2: システム名 | C2: SOCIA | E2: 作成者 | I2: ITSP | M2: テーブル一覧へ
B3: サブシステム名 | C3: 給与 | E3: 作成日 | I3: 2025-11-28
B4: スキーマ名 | E4: RDBMS | I4: MySQL
B5: 論理テーブル名 | C5: v社員体系 | E5: ENGINE | I5: InnoDB
B6: 物理テーブル名 | C6: v_syain_taikei | E6: CHARSET | I6: utf8mb4
B7: 備考
B8: 論理テーブル
A12: カラム情報 | L12: 外部キー情報
A13: No | B13: 論理名 | C13: 物理名 | D13: データ型 | E13: Size | F13: Not Null | G13: PK | H13: UK | I13: デフォルト | J13: 備考 | L13: 親テーブル | M13: 参照カラム
A14: 1 | B14: 社員連番 | C14: syainseq | D14: bigint | F14: not null | G14: 〇
A15: 2 | B15: 支給区分 | C15: payment_type | D15: tinyint | F15: not null | G15: 〇
A16: 3 | B16: 体系コード | C16: taikei_code | D16: varchar | E16: 20
A17: 4 | B17: 作成者 | C17: created_by | D17: bigint | F17: not null
A18: 5 | B18: 作成日時 | C18: created_at | D18: datetime | E18: 6 | F18: not null
A19: 6 | B19: 更新者 | C19: updated_by | D19: bigint | F19: not null
A20: 7 | B20: 更新日時 | C20: updated_at | D20: datetime | E20: 6 | F20: not null

Sheet v社員保険資格取得
A1: テーブル情報
B2: システム名 | C2: SOCIA | E2: 作成者 | I2: ITSP | M2: テーブル一覧へ
B3: サブシステム名 | C3: 給与 | E3: 作成日 | I3: 2025-11-28
B4: スキーマ名 | E4: RDBMS | I4: MySQL
B5: 論理テーブル名 | C5: v社員保険資格取得 | E5: ENGINE | I5: InnoDB
B6: 物理テーブル名 | C6: v_syain_insurance_qualification_get | E6: CHARSET | I6: utf8mb4
B7: 備考
B8: 論理テーブル
A12: カラム情報 | L12: 外部キー情報
A13: No | B13: 論理名 | C13: 物理名 | D13: データ型 | E13: Size | F13: Not Null | G13: PK | H13: UK | I13: デフォルト | J13: 備考 | L13: 親テーブル | M13: 参照カラム
A14: 1 | B14: 社員連番 | C14: syainseq | D14: bigint | F14: not null | G14: 〇
A15: 2 | B15: 資格取得年月日 | C15: qualification_get_date | D15: date
A16: 3 | B16: 取得対象 | C16: get_target | D16: tinyint
A17: 4 | B17: 取得区分 | C17: get_type | D17: tinyint
A18: 5 | B18: 金銭 | C18: cash | D18: bigint
A19: 6 | B19: 現物 | C19: in_kind | D19: bigint
A20: 7 | B20: 合計 | C20: total | D20: bigint
A21: 8 | B21: 老齢年金給付区分 | C21: elderly_pension_grant_type | D21: tinyint
A22: 9 | B22: 被扶養者届区分 | C22: dependent_submission_type | D22: tinyint
A23: 10 | B23: 備考 | C23: note | D23: text
A24: 11 | B24: 資格確認書発行要否 | C24: qualification_confirm_report_issue_flag | D24: tinyint
A25: 12 | B25: 作成者 | C25: created_by | D25: bigint | F25: not null
A26: 13 | B26: 作成日時 | C26: created_at | D26: datetime | E26: 6 | F26: not null
A27: 14 | B27: 更新者 | C27: updated_by | D27: bigint | F27: not null
A28: 15 | B28: 更新日時 | C28: updated_at | D28: datetime | E28: 6 | F28: not null

Sheet v社員保険資格喪失
A1: テーブル情報
B2: システム名 | C2: SOCIA | E2: 作成者 | I2: ITSP | M2: テーブル一覧へ
B3: サブシステム名 | C3: 給与 | E3: 作成日 | I3: 2025-11-28
B4: スキーマ名 | E4: RDBMS | I4: MySQL
B5: 論理テーブル名 | C5: v社員保険資格喪失 | E5: ENGINE | I5: InnoDB
B6: 物理テーブル名 | C6: v_syain_insurance_qualification_loss | E6: CHARSET | I6: utf8mb4
B7: 備考
B8: 論理テーブル
A12: カラム情報 | L12: 外部キー情報
A13: No | B13: 論理名 | C13: 物理名 | D13: データ型 | E13: Size | F13: Not Null | G13: PK | H13: UK | I13: デフォルト | J13: 備考 | L13: 親テーブル | M13: 参照カラム
A14: 1 | B14: 社員連番 | C14: syainseq | D14: bigint | F14: not null | G14: 〇
A15: 2 | B15: 資格喪失年月日 | C15: qualification_loss_date | D15: date
A16: 3 | B16: 資格喪失対象 | C16: qualification_loss_target | D16: tinyint
A17: 4 | B17: 喪失区分 | C17: loss_type | D17: tinyint
A18: 5 | B18: 被保険者証回収区分 | C18: insured_person_card_return_type | D18: tinyint
A19: 6 | B19: ５５条届出区分 | C19: article55_submission_type | D19: tinyint
A20: 7 | B20: 備考 | C20: note | D20: text
A21: 8 | B21: 添付枚数 | C21: attachments_count | D21: bigint
A22: 9 | B22: 返不能枚数 | C22: return_non_count | D22: bigint
A23: 10 | B23: 作成者 | C23: created_by | D23: bigint | F23: not null
A24: 11 | B24: 作成日時 | C24: created_at | D24: datetime | E24: 6 | F24: not null
A25: 12 | B25: 更新者 | C25: updated_by | D25: bigint | F25: not null
A26: 13 | B26: 更新日時 | C26: updated_at | D26: datetime | E26: 6 | F26: not null

Sheet v社員健康保険
A1: テーブル情報
B2: システム名 | C2: SOCIA | E2: 作成者 | I2: ITSP | M2: テーブル一覧へ
B3: サブシステム名 | C3: 給与 | E3: 作成日 | I3: 2025-11-28
B4: スキーマ名 | E4: RDBMS | I4: MySQL
B5: 論理テーブル名 | C5: v社員健康保険 | E5: ENGINE | I5: InnoDB
B6: 物理テーブル名 | C6: v_syain_health_insurance | E6: CHARSET | I6: utf8mb4
B7: 備考
B8: 論理テーブル
A12: カラム情報 | L12: 外部キー情報
A13: No | B13: 論理名 | C13: 物理名 | D13: データ型 | E13: Size | F13: Not Null | G13: PK | H13: UK | I13: デフォルト | J13: 備考 | L13: 親テーブル | M13: 参照カラム
A14: 1 | B14: 社員連番 | C14: syainseq | D14: bigint | F14: not null | G14: 〇
A15: 2 | B15: 標準報酬月額 | C15: standard_reward_month_amount | D15: bigint
A16: 3 | B16: 報酬 | C16: reward | D16: bigint
A17: 4 | B17: 改定年 | C17: revision_year | D17: smallint
A18: 5 | B18: 改定月 | C18: revision_month | D18: smallint
A19: 6 | B19: 作成者 | C19: created_by | D19: bigint | F19: not null
A20: 7 | B20: 作成日時 | C20: created_at | D20: datetime | E20: 6 | F20: not null
A21: 8 | B21: 更新者 | C21: updated_by | D21: bigint | F21: not null
A22: 9 | B22: 更新日時 | C22: updated_at | D22: datetime | E22: 6 | F22: not null

Sheet v社員厚生年金
A1: テーブル情報
B2: システム名 | C2: SOCIA | E2: 作成者 | I2: ITSP | M2: テーブル一覧へ
B3: サブシステム名 | C3: 給与 | E3: 作成日 | I3: 2025-11-28
B4: スキーマ名 | E4: RDBMS | I4: MySQL
B5: 論理テーブル名 | C5: v社員厚生年金 | E5: ENGINE | I5: InnoDB
B6: 物理テーブル名 | C6: v_syain_kosei_pension | E6: CHARSET | I6: utf8mb4
B7: 備考
B8: 論理テーブル
A12: カラム情報 | L12: 外部キー情報
A13: No | B13: 論理名 | C13: 物理名 | D13: データ型 | E13: Size | F13: Not Null | G13: PK | H13: UK | I13: デフォルト | J13: 備考 | L13: 親テーブル | M13: 参照カラム
A14: 1 | B14: 社員連番 | C14: syainseq | D14: bigint | F14: not null | G14: 〇
A15: 2 | B15: 標準報酬月額 | C15: standard_reward_month_amount | D15: bigint
A16: 3 | B16: 報酬 | C16: reward | D16: bigint
A17: 4 | B17: 改定年 | C17: revision_year | D17: smallint
A18: 5 | B18: 改定月 | C18: revision_month | D18: smallint
A19: 6 | B19: 作成者 | C19: created_by | D19: bigint | F19: not null
A20: 7 | B20: 作成日時 | C20: created_at | D20: datetime | E20: 6 | F20: not null
A21: 8 | B21: 更新者 | C21: updated_by | D21: bigint | F21: not null
A22: 9 | B22: 更新日時 | C22: updated_at | D22: datetime | E22: 6 | F22: not null

Sheet v社員基本
A1: テーブル情報
B2: システム名 | C2: SOCIA | E2: 作成者 | I2: ITSP | M2: テーブル一覧へ
B3: サブシステム名 | C3: 給与 | E3: 作成日 | I3: 2025-11-28
B4: スキーマ名 | E4: RDBMS | I4: MySQL
B5: 論理テーブル名 | C5: v社員基本 | E5: ENGINE | I5: InnoDB
B6: 物理テーブル名 | C6: v_syain_basic | E6: CHARSET | I6: utf8mb4
B7: 備考
B8: 論理テーブル
A12: カラム情報 | L12: 外部キー情報
A13: No | B13: 論理名 | C13: 物理名 | D13: データ型 | E13: Size | F13: Not Null | G13: PK | H13: UK | I13: デフォルト | J13: 備考 | L13: 親テーブル | M13: 参照カラム
A14: 1 | B14: 社員連番 | C14: syainseq | D14: bigint | F14: not null | G14: 〇
A15: 2 | B15: 会社コード | C15: kaisyacd | D15: varchar | E15: 20
A16: 3 | B16: 社員コード | C16: syaincd | D16: varchar | E16: 20
A17: 4 | B17: 氏名 | C17: name | D17: varchar | E17: 255
A18: 5 | B18: フリガナ | C18: furigana | D18: varchar | E18: 20
A19: 6 | B19: 生年月日 | C19: birth_date | D19: date
A20: 7 | B20: 性別区分 | C20: sex_type | D20: tinyint
A21: 8 | B21: 入社年月日 | C21: entrycompany_date | D21: date
A22: 9 | B22: 休・退職区分 | C22: leave_retirement_type | D22: tinyint
A23: 10 | B23: 地方自治体コード | C23: local_municipality_code | D23: varchar | E23: 20
A24: 11 | B24: 住所 | C24: address | D24: varchar | E24: 100
A25: 12 | B25: 住所カナ | C25: address_kana | D25: varchar | E25: 100
A26: 13 | B26: 退職年月日 | C26: retirement_date | D26: date
A27: 14 | B27: 事業所コード | C27: office_code | D27: varchar | E27: 20
A28: 15 | B28: 所属コード | C28: belong_code | D28: varchar | E28: 20
A29: 16 | B29: 部門コード | C29: department_code | D29: varchar | E29: 20
A30: 17 | B30: 郵便番号 | C30: postal_code | D30: varchar | E30: 10
A31: 18 | B31: みなし入社年月日 | C31: deem_entrycompany_date | D31: date
A32: 19 | B32: 役員区分 | C32: officer_type | D32: tinyint
A33: 20 | B33: 弁護士区分 | C33: lawyer_type | D33: tinyint
A34: 21 | B34: 給与区分 | C34: kyuyo_type | D34: tinyint
A35: 22 | B35: データ連番 | C35: dataseq | D35: int
A36: 23 | B36: 住民税区分 | C36: resident_tax_type | D36: tinyint
A37: 24 | B37: 届出コード | C37: submission_code | D37: varchar | E37: 20
A38: 25 | B38: パート区分 | C38: part_type | D38: tinyint
A39: 26 | B39: 健康保険番号 | C39: health_insurance_number | D39: varchar | E39: 20
A40: 27 | B40: 基礎年金番号 | C40: basic_pension_number | D40: varchar | E40: 20
A41: 28 | B41: 年金整理番号 | C41: pension_arrangement_number | D41: varchar | E41: 20
A42: 29 | B42: 作成者 | C42: created_by | D42: bigint | F42: not null
A43: 30 | B43: 作成日時 | C43: created_at | D43: datetime | E43: 6 | F43: not null
A44: 31 | B44: 更新者 | C44: updated_by | D44: bigint | F44: not null
A45: 32 | B45: 更新日時 | C45: updated_at | D45: datetime | E45: 6 | F45: not null

Sheet v社員家族
A1: テーブル情報
B2: システム名 | C2: SOCIA | E2: 作成者 | I2: ITSP | M2: テーブル一覧へ
B3: サブシステム名 | C3: 給与 | E3: 作成日 | I3: 2025-11-28
B4: スキーマ名 | E4: RDBMS | I4: MySQL
B5: 論理テーブル名 | C5: v社員家族 | E5: ENGINE | I5: InnoDB
B6: 物理テーブル名 | C6: v_syain_family | E6: CHARSET | I6: utf8mb4
B7: 備考
B8: 論理テーブル
A12: カラム情報 | L12: 外部キー情報
A13: No | B13: 論理名 | C13: 物理名 | D13: データ型 | E13: Size | F13: Not Null | G13: PK | H13: UK | I13: デフォルト | J13: 備考 | L13: 親テーブル | M13: 参照カラム
A14: 1 | B14: 社員連番 | C14: syainseq | D14: bigint | F14: not null | G14: 〇
A15: 2 | B15: データ連番 | C15: dataseq | D15: int | F15: not null | G15: 〇
A16: 3 | B16: 表示順序 | C16: dsp_order | D16: bigint
A17: 4 | B17: 氏名 | C17: name | D17: varchar | E17: 255
A18: 5 | B18: フリガナ | C18: furigana | D18: varchar | E18: 20
A19: 6 | B19: 性別区分 | C19: sex_type | D19: tinyint
A20: 7 | B20: 郵便番号 | C20: postal_code | D20: varchar | E20: 10
A21: 8 | B21: 住所 | C21: address | D21: varchar | E21: 100
A22: 9 | B22: 生年月日 | C22: birth_date | D22: date
A23: 10 | B23: 続柄コード | C23: relation_code | D23: varchar | E23: 20
A24: 11 | B24: 職業コード | C24: occupation_code | D24: varchar | E24: 20
A25: 12 | B25: 職業名称 | C25: occupation_name | D25: varchar | E25: 255
A26: 13 | B26: 同居区分 | C26: cohabitation_type | D26: tinyint
A27: 14 | B27: 扶養区分 | C27: dependent_type | D27: tinyint
A28: 15 | B28: 障害者区分 | C28: disability_type | D28: tinyint
A29: 16 | B29: 同一生計区分 | C29: same_household_type | D29: tinyint
A30: 17 | B30: 非居住者区分 | C30: nonresident_type | D30: tinyint
A31: 18 | B31: 非居住理由区分 | C31: nonresident_reason_type | D31: tinyint
A32: 19 | B32: 寡婦区分 | C32: widow_type | D32: tinyint
A33: 20 | B33: 配偶者区分 | C33: spouse_type | D33: tinyint
A34: 21 | B34: 市区町村名称 | C34: municipalities_name | D34: varchar | E34: 255
A35: 22 | B35: 事業所名称 | C35: office_name | D35: varchar | E35: 255
A36: 23 | B36: 所属名称 | C36: belong_name | D36: varchar | E36: 255
A37: 24 | B37: 事業所略称 | C37: office_shortname | D37: varchar | E37: 255
A38: 25 | B38: 所属略称 | C38: belong_shortname | D38: varchar | E38: 255
A39: 26 | B39: 作成者 | C39: created_by | D39: bigint | F39: not null
A40: 27 | B40: 作成日時 | C40: created_at | D40: datetime | E40: 6 | F40: not null
A41: 28 | B41: 更新者 | C41: updated_by | D41: bigint | F41: not null
A42: 29 | B42: 更新日時 | C42: updated_at | D42: datetime | E42: 6 | F42: not null

Sheet v社員届出異動履歴
A1: テーブル情報
B2: システム名 | C2: SOCIA | E2: 作成者 | I2: ITSP | M2: テーブル一覧へ
B3: サブシステム名 | C3: 給与 | E3: 作成日 | I3: 2025-11-28
B4: スキーマ名 | E4: RDBMS | I4: MySQL
B5: 論理テーブル名 | C5: v社員届出異動履歴 | E5: ENGINE | I5: InnoDB
B6: 物理テーブル名 | C6: v_syain_submission_transfer_history | E6: CHARSET | I6: utf8mb4
B7: 備考
B8: 論理テーブル。履歴テーブル
A12: カラム情報 | L12: 外部キー情報
A13: No | B13: 論理名 | C13: 物理名 | D13: データ型 | E13: Size | F13: Not Null | G13: PK | H13: UK | I13: デフォルト | J13: 備考 | L13: 親テーブル | M13: 参照カラム
A14: 1 | B14: 社員連番 | C14: syainseq | D14: bigint | F14: not null | G14: 〇
A15: 2 | B15: 有効開始年月日 | C15: fromymd | D15: date | F15: not null | G15: 〇
A16: 3 | B16: 有効終了年月日 | C16: toymd | D16: date
A17: 4 | B17: 届出コード | C17: submission_code | D17: varchar | E17: 20
A18: 5 | B18: 作成者 | C18: created_by | D18: bigint | F18: not null
A19: 6 | B19: 作成日時 | C19: created_at | D19: datetime | E19: 6 | F19: not null
A20: 7 | B20: 更新者 | C20: updated_by | D20: bigint | F20: not null
A21: 8 | B21: 更新日時 | C21: updated_at | D21: datetime | E21: 6 | F21: not null

Sheet v社員社会保険関連個人情報
A1: テーブル情報
B2: システム名 | C2: SOCIA | E2: 作成者 | I2: ITSP | M2: テーブル一覧へ
B3: サブシステム名 | C3: 給与 | E3: 作成日 | I3: 2025-11-28
B4: スキーマ名 | E4: RDBMS | I4: MySQL
B5: 論理テーブル名 | C5: v社員社会保険関連個人情報 | E5: ENGINE | I5: InnoDB
B6: 物理テーブル名 | C6: v_syain_syaho_personal_info | E6: CHARSET | I6: utf8mb4
B7: 備考
B8: 論理テーブル
A12: カラム情報 | L12: 外部キー情報
A13: No | B13: 論理名 | C13: 物理名 | D13: データ型 | E13: Size | F13: Not Null | G13: PK | H13: UK | I13: デフォルト | J13: 備考 | L13: 親テーブル | M13: 参照カラム
A14: 1 | B14: 社員連番 | C14: syainseq | D14: bigint | F14: not null | G14: 〇
A15: 2 | B15: データ区分 | C15: data_type | D15: bigint
A16: 3 | B16: 種別区分 | C16: class_type | D16: tinyint
A17: 4 | B17: 種別コード | C17: class_code | D17: varchar | E17: 20
A18: 5 | B18: 理由 | C18: reason | D18: varchar | E18: 255
A19: 6 | B19: 作成者 | C19: created_by | D19: bigint | F19: not null
A20: 7 | B20: 作成日時 | C20: created_at | D20: datetime | E20: 6 | F20: not null
A21: 8 | B21: 更新者 | C21: updated_by | D21: bigint | F21: not null
A22: 9 | B22: 更新日時 | C22: updated_at | D22: datetime | E22: 6 | F22: not null

Sheet v社員税法
A1: テーブル情報
B2: システム名 | C2: SOCIA | E2: 作成者 | I2: ITSP | M2: テーブル一覧へ
B3: サブシステム名 | C3: 給与 | E3: 作成日 | I3: 2025-11-28
B4: スキーマ名 | E4: RDBMS | I4: MySQL
B5: 論理テーブル名 | C5: v社員税法 | E5: ENGINE | I5: InnoDB
B6: 物理テーブル名 | C6: v_syain_tax_law | E6: CHARSET | I6: utf8mb4
B7: 備考
B8: 論理テーブル
A12: カラム情報 | L12: 外部キー情報
A13: No | B13: 論理名 | C13: 物理名 | D13: データ型 | E13: Size | F13: Not Null | G13: PK | H13: UK | I13: デフォルト | J13: 備考 | L13: 親テーブル | M13: 参照カラム
A14: 1 | B14: 社員連番 | C14: syainseq | D14: bigint | F14: not null | G14: 〇
A15: 2 | B15: 課税区分 | C15: tax_type | D15: tinyint
A16: 3 | B16: 居住者区分 | C16: resident_type | D16: tinyint
A17: 4 | B17: 障害者区分 | C17: disability_type | D17: tinyint
A18: 5 | B18: 寡婦区分 | C18: widow_type | D18: tinyint
A19: 6 | B19: 学生区分 | C19: student_type | D19: tinyint
A20: 7 | B20: 未成年者区分 | C20: minor_type | D20: tinyint
A21: 8 | B21: 死亡退職区分 | C21: death_retirement_type | D21: tinyint
A22: 9 | B22: 災害者区分 | C22: disaster_type | D22: tinyint
A23: 10 | B23: 外国人区分 | C23: foreigner_type | D23: tinyint
A24: 11 | B24: 配偶者区分 | C24: spouse_type | D24: tinyint
A25: 12 | B25: 親族扶養区分 | C25: relative_dependent_type | D25: tinyint
A26: 13 | B26: 親族一般扶養 | C26: relative_general_dependent | D26: tinyint
... A45: 32 | B45: 厚生年金基金区分 | C45: kosei_pension_fund_type | D45: tinyint
A46: 33 | B46: 作成者 | C46: created_by | D46: bigint | F46: not null
A47: 34 | B47: 作成日時 | C47: created_at | D47: datetime | E47: 6 | F47: not null
A48: 35 | B48: 更新者 | C48: updated_by | D48: bigint | F48: not null
A49: 36 | B49: 更新日時 | C49: updated_at | D49: datetime | E49: 6 | F49: not null

Sheet v社員締日
A1: テーブル情報
B2: システム名 | C2: SOCIA | E2: 作成者 | I2: ITSP | M2: テーブル一覧へ
B3: サブシステム名 | C3: 給与 | E3: 作成日 | I3: 2025-11-28
B4: スキーマ名 | E4: RDBMS | I4: MySQL
B5: 論理テーブル名 | C5: v社員締日 | E5: ENGINE | I5: InnoDB
B6: 物理テーブル名 | C6: v_syain_shime_day | E6: CHARSET | I6: utf8mb4
B7: 備考
B8: 論理テーブル
A12: カラム情報 | L12: 外部キー情報
A13: No | B13: 論理名 | C13: 物理名 | D13: データ型 | E13: Size | F13: Not Null | G13: PK | H13: UK | I13: デフォルト | J13: 備考 | L13: 親テーブル | M13: 参照カラム
A14: 1 | B14: 社員連番 | C14: syainseq | D14: bigint | F14: not null | G14: 〇
A15: 2 | B15: 締日 | C15: shime_day | D15: tinyint | F15: not null | G15: 〇
A16: 3 | B16: 支給月区分 | C16: payment_month_type | D16: tinyint | F16: not null | G16: 〇
A17: 4 | B17: 支給日 | C17: payment_day | D17: tinyint | F17: not null | G17: 〇
A18: 5 | B18: 作成者 | C18: created_by | D18: bigint | F18: not null
A19: 6 | B19: 作成日時 | C19: created_at | D19: datetime | E19: 6 | F19: not null
A20: 7 | B20: 更新者 | C20: updated_by | D20: bigint | F20: not null
A21: 8 | B21: 更新日時 | C21: updated_at | D21: datetime | E21: 6 | F21: not null

Sheet v社員賞与時社保徴収先
A1: テーブル情報
B2: システム名 | C2: SOCIA | E2: 作成者 | I2: ITSP | M2: テーブル一覧へ
B3: サブシステム名 | C3: 給与 | E3: 作成日 | I3: 2025-11-28
B4: スキーマ名 | E4: RDBMS | I4: MySQL
B5: 論理テーブル名 | C5: v社員賞与時社保徴収先 | E5: ENGINE | I5: InnoDB
B6: 物理テーブル名 | C6: v_syain_syoyo_syaho_collateral | E6: CHARSET | I6: utf8mb4
B7: 備考
B8: 論理テーブル
A12: カラム情報 | L12: 外部キー情報
A13: No | B13: 論理名 | C13: 物理名 | D13: データ型 | E13: Size | F13: Not Null | G13: PK | H13: UK | I13: デフォルト | J13: 備考 | L13: 親テーブル | M13: 参照カラム
A14: 1 | B14: 社員連番 | C14: syainseq | D14: bigint | F14: not null | G14: 〇
A15: 2 | B15: 徴収先区分 | C15: collateral_type | D15: tinyint
A16: 3 | B16: 作成者 | C16: created_by | D16: bigint | F16: not null
A17: 4 | B17: 作成日時 | C17: created_at | D17: datetime | E17: 6 | F17: not null
A18: 5 | B18: 更新者 | C18: updated_by | D18: bigint | F18: not null
A19: 6 | B19: 更新日時 | C19: updated_at | D19: datetime | E19: 6 | F19: not null

Sheet v社員銀行
A1: テーブル情報
B2: システム名 | C2: SOCIA | E2: 作成者 | I2: ITSP | M2: テーブル一覧へ
B3: サブシステム名 | C3: 給与 | E3: 作成日 | I3: 2025-11-28
B4: スキーマ名 | E4: RDBMS | I4: MySQL
B5: 論理テーブル名 | C5: v社員銀行 | E5: ENGINE | I5: InnoDB
B6: 物理テーブル名 | C6: v_syain_bank | E6: CHARSET | I6: utf8mb4
B7: 備考
B8: 論理テーブル
A12: カラム情報 | L12: 外部キー情報
A13: No | B13: 論理名 | C13: 物理名 | D13: データ型 | E13: Size | F13: Not Null | G13: PK | H13: UK | I13: デフォルト | J13: 備考 | L13: 親テーブル | M13: 参照カラム
A14: 1 | B14: 社員連番 | C14: syainseq | D14: bigint | F14: not null | G14: 〇
A15: 2 | B15: 支給区分 | C15: payment_type | D15: tinyint | F15: not null | G15: 〇
A16: 3 | B16: 処理順序 | C16: process_order | D16: bigint | F16: not null | G16: 〇
A17: 4 | B17: 振込元銀行連番 | C17: remitter_bank_seq | D17: bigint
A18: 5 | B18: 銀行コード | C18: bank_code | D18: varchar | E18: 20
A19: 6 | B19: 支店コード | C19: branch_code | D19: varchar | E19: 20
A20: 7 | B20: 口座種別区分 | C20: account_class_type | D20: tinyint
A21: 8 | B21: 口座番号 | C21: account_number | D21: bigint
A22: 9 | B22: 別名義振込氏名 | C22: different_name_remitter_name | D22: varchar | E22: 255
A23: 10 | B23: 別名義振込カナ | C23: different_name_remitter_kana | D23: varchar | E23: 255
A24: 11 | B24: 振込区分 | C24: transfer_type | D24: tinyint
A25: 12 | B25: 設定値 | C25: setvalue | D25: varchar | E25: 255
A26: 13 | B26: 項目コード | C26: item_code | D26: varchar | E26: 20
A27: 14 | B27: 作成者 | C27: created_by | D27: bigint | F27: not null
A28: 15 | B28: 作成日時 | C28: created_at | D28: datetime | E28: 6 | F28: not null
A29: 16 | B29: 更新者 | C29: updated_by | D29: bigint | F29: not null
A30: 17 | B30: 更新日時 | C30: updated_at | D30: datetime | E30: 6 | F30: not null

Sheet 事業所整理記号情報
A1: テーブル情報
B2: システム名 | C2: SOCIA | E2: 作成者 | I2: ITSP | M2: テーブル一覧へ
B3: サブシステム名 | C3: 給与 | E3: 作成日 | I3: 2025-11-28
B4: スキーマ名 | E4: RDBMS | I4: MySQL
B5: 論理テーブル名 | C5: 事業所整理記号情報 | E5: ENGINE | I5: InnoDB
B6: 物理テーブル名 | C6: office_arrangement_mark_info | E6: CHARSET | I6: utf8mb4
B7: 備考
A12: カラム情報 | L12: 外部キー情報
A13: No | B13: 論理名 | C13: 物理名 | D13: データ型 | E13: Size | F13: Not Null | G13: PK | H13: UK | I13: デフォルト | J13: 備考 | L13: 親テーブル | M13: 参照カラム
A14: 1 | B14: 会社コード | C14: kaisyacd | D14: varchar | E14: 20 | F14: not null | G14: 〇
A15: 2 | B15: 届出コード | C15: submission_code | D15: varchar | E15: 20 | F15: not null | G15: 〇
A16: 3 | B16: 提出先区分 | C16: submission_type | D16: tinyint | F16: not null | G16: 〇
A17: 4 | B17: ＦＤ通番 | C17: fd_serialnumber | D17: smallint
A18: 5 | B18: 郡市区符号 | C18: city_code | D18: tinyint
A19: 6 | B19: 事業所記号 | C19: office_mark | D19: varchar | E19: 4
A20: 7 | B20: 都道府県コード | C20: state_code | D20: varchar | E20: 2
A21: 8 | B21: 作成者 | C21: created_by | D21: bigint | F21: not null
A22: 9 | B22: 作成日時 | C22: created_at | D22: datetime | E22: 6 | F22: not null
A23: 10 | B23: 更新者 | C23: updated_by | D23: bigint | F23: not null
A24: 11 | B24: 更新日時 | C24: updated_at | D24: datetime | E24: 6 | F24: not null

Sheet 介護保険会社情報
A1: テーブル情報
B2: システム名 | C2: SOCIA | E2: 作成者 | I2: ITSP | M2: テーブル一覧へ
B3: サブシステム名 | C3: 給与 | E3: 作成日 | I3: 2025-11-28
B4: スキーマ名 | E4: RDBMS | I4: MySQL
B5: 論理テーブル名 | C5: 介護保険会社情報 | E5: ENGINE | I5: InnoDB
B6: 物理テーブル名 | C6: care_insurance_kaisya_info | E6: CHARSET | I6: utf8mb4
B7: 備考
B8: #238673より、保険会社の事業部/届出 毎の必要がなくなる
A12: カラム情報 | L12: 外部キー情報
A13: No | B13: 論理名 | C13: 物理名 | D13: データ型 | E13: Size | F13: Not Null | G13: PK | H13: UK | I13: デフォルト | J13: 備考 | L13: 親テーブル | M13: 参照カラム
A14: 1 | B14: 会社コード | C14: kaisyacd | D14: varchar | E14: 20 | F14: not null | G14: 〇
A15: 2 | B15: 有効開始年月日 | C15: fromymd | D15: date | F15: not null | G15: 〇
A16: 3 | B16: 有効終了年月日 | C16: toymd | D16: date | F16: not null
A17: 4 | B17: 計算区分 | C17: equation_type | D17: tinyint | F17: not null | J17: 1:率(初期値)_x000D_ 2:表
A18: 5 | B18: 特定被保険者計算区分 | C18: specific_insured_person_equation_type | D18: tinyint | F18: not null | J18: 1:使用する(初期値)_x000D_ 2:使用しない
A19: 6 | B19: 介護被保険者 | C19: care_insured_person | D19: decimal | E19: 6,3 | F19: not null
A20: 7 | B20: 介護事業主 | C20: care_business_owner | D20: decimal | E20: 6,3 | F20: not null
A21: 8 | B21: 特別介護被保険者 | C21: special_care_insured_person | D21: decimal | E21: 6,3
A22: 9 | B22: 特別介護事業主 | C22: special_care_business_owner | D22: decimal | E22: 6,3
A23: 10 | B23: 作成者 | C23: created_by | D23: bigint | F23: not null
A24: 11 | B24: 作成日時 | C24: created_at | D24: datetime | E24: 6 | F24: not null
A25: 12 | B25: 更新者 | C25: updated_by | D25: bigint | F25: not null
A26: 13 | B26: 更新日時 | C26: updated_at | D26: datetime | E26: 6 | F26: not null

Sheet 介護保険料額
A1: テーブル情報
B2: システム名 | C2: SOCIA | E2: 作成者 | I2: ITSP | M2: テーブル一覧へ
B3: サブシステム名 | C3: 給与 | E3: 作成日 | I3: 2025-11-28
B4: スキーマ名 | E4: RDBMS | I4: MySQL
B5: 論理テーブル名 | C5: 介護保険料額 | E5: ENGINE | I5: InnoDB
B6: 物理テーブル名 | C6: care_insurance_amount | E6: CHARSET | I6: utf8mb4
B7: 備考
A12: カラム情報 | L12: 外部キー情報
A13: No | B13: 論理名 | C13: 物理名 | D13: データ型 | E13: Size | F13: Not Null | G13: PK | H13: UK | I13: デフォルト | J13: 備考 | L13: 親テーブル | M13: 参照カラム
A14: 1 | B14: 会社コード | C14: kaisyacd | D14: varchar | E14: 20 | F14: not null | G14: 〇
A15: 2 | B15: 届出コード | C15: submission_code | D15: varchar | E15: 20 | F15: not null | G15: 〇
A16: 3 | B16: 等級 | C16: grade | D16: smallint | F16: not null | G16: 〇
A17: 4 | B17: 有効開始年月日 | C17: fromymd | D17: date | F17: not null | G17: 〇
A18: 5 | B18: 有効終了年月日 | C18: toymd | D18: date | F18: not null
A19: 6 | B19: 標準報酬月額 | C19: standard_reward_month_amount | D19: bigint | F19: not null
A20: 7 | B20: 報酬月額 | C20: reward_monthly | D20: bigint
A21: 8 | B21: 被保険者 | C21: insured_person | D21: int | F21: not null
A22: 9 | B22: 事業主 | C22: business_owner | D22: int | F22: not null
A23: 10 | B23: 作成者 | C23: created_by | D23: bigint | F23: not null
A24: 11 | B24: 作成日時 | C24: created_at | D24: datetime | E24: 6 | F24: not null
A25: 12 | B25: 更新者 | C25: updated_by | D25: bigint | F25: not null
A26: 13 | B26: 更新日時 | C26: updated_at | D26: datetime | E26: 6 | F26: not null

Sheet 会社保険率
A1: テーブル情報
B2: システム名 | C2: SOCIA | E2: 作成者 | I2: ITSP | M2: テーブル一覧へ
B3: サブシステム名 | C3: 給与 | E3: 作成日 | I3: 2025-11-28
B4: スキーマ名 | E4: RDBMS | I4: MySQL
B5: 論理テーブル名 | C5: 会社保険率 | E5: ENGINE | I5: InnoDB
B6: 物理テーブル名 | C6: kaisya_insurance_rate | E6: CHARSET | I6: utf8mb4
B7: 備考
A12: カラム情報 | L12: 外部キー情報
A13: No | B13: 論理名 | C13: 物理名 | D13: データ型 | E13: Size | F13: Not Null | G13: PK | H13: UK | I13: デフォルト | J13: 備考 | L13: 親テーブル | M13: 参照カラム
A14: 1 | B14: 会社コード | C14: kaisyacd | D14: varchar | E14: 20 | F14: not null | G14: 〇
A15: 2 | B15: 届出コード | C15: submission_code | D15: varchar | E15: 20 | F15: not null | G15: 〇
A16: 3 | B16: 有効開始年月日 | C16: fromymd | D16: date | F16: not null | G16: 〇
A17: 4 | B17: 有効終了年月日 | C17: toymd | D17: date | F17: not null
A18: 5 | B18: 給与健康率被保険者(基本) | C18: kyuyo_health_rate_insured_person_basic | D18: decimal | E18: 6,3 | F18: not null
A19: 6 | B19: 給与健康率被保険者(特定) | C19: kyuyo_health_rate_insured_person_specific | D19: decimal | E19: 6,3 | F19: not null
A20: 7 | B20: 給与健康率事業主(基本) | C20: kyuyo_health_rate_business_owner_basic | D20: decimal | E20: 6,3 | F20: not null
A21: 8 | B21: 給与健康率事業主(特定) | C21: kyuyo_health_rate_business_owner_specific | D21: decimal | E21: 6,3 | F21: not null
A22: 9 | B22: 賞与健康率被保険者(基本) | C22: syoyo_health_rate_insured_person_basic | D22: decimal | E22: 6,3 | F22: not null
A23: 10 | B23: 賞与健康率被保険者(特定) | C23: syoyo_health_rate_insured_person_specific | D23: decimal | E23: 6,3 | F23: not null
A24: 11 | B24: 賞与健康率事業主(基本) | C24: syoyo_health_rate_business_owner_basic | D24: decimal | E24: 6,3 | F24: not null
A25: 12 | B25: 賞与健康率事業主(特定) | C25: syoyo_health_rate_business_owner_specific | D25: decimal | E25: 6,3 | F25: not null
A26: 13 | B26: 一般拠出金率 | C26: general_contribution_rate | D26: decimal | E26: 6,3
A27: 14 | B27: 作成者 | C27: created_by | D27: bigint | F27: not null
A28: 15 | B28: 作成日時 | C28: created_at | D28: datetime | E28: 6 | F28: not null
A29: 16 | B29: 更新者 | C29: updated_by | D29: bigint | F29: not null
A30: 17 | B30: 更新日時 | C30: updated_at | D30: datetime | E30: 6 | F30: not null

Sheet 会社地方自治体
A1: テーブル情報
B2: システム名 | C2: SOCIA | E2: 作成者 | I2: ITSP | M2: テーブル一覧へ
B3: サブシステム名 | C3: 給与 | E3: 作成日 | I3: 2025-11-28
B4: スキーマ名 | E4: RDBMS | I4: MySQL
B5: 論理テーブル名 | C5: 会社地方自治体 | E5: ENGINE | I5: InnoDB
B6: 物理テーブル名 | C6: kaisya_local_municipality | E6: CHARSET | I6: utf8mb4
B7: 備考
B8: 現行：QTISJITIとQTISKAISYAJITIの合体
A12: カラム情報 | L12: 外部キー情報
A13: No | B13: 論理名 | C13: 物理名 | D13: データ型 | E13: Size | F13: Not Null | G13: PK | H13: UK | I13: デフォルト | J13: 備考 | L13: 親テーブル | M13: 参照カラム
A14: 1 | B14: 会社コード | C14: kaisyacd | D14: varchar | E14: 20 | F14: not null | G14: 〇
A15: 2 | B15: 届出コード | C15: submission_code | D15: varchar | E15: 20 | F15: not null | G15: 〇
A16: 3 | B16: 市区町村コード | C16: municipalities_code | D16: varchar | E16: 20 | F16: not null | G16: 〇
A17: 4 | B17: 有効開始年月日 | C17: fromymd | D17: date | F17: not null | G17: 〇
A18: 5 | B18: 有効終了年月日 | C18: toymd | D18: date | F18: not null
A19: 6 | B19: 指定番号 | C19: specify_number | D19: varchar | E19: 12
A20: 7 | B20: 地方税納付先銀行コード | C20: local_tax_payee_bank_code | D20: varchar | E20: 20
A21: 8 | B21: 地方税納付先支店コード | C21: local_tax_payee_branch_code | D21: varchar | E21: 20
A22: 9 | B22: 依頼人番号 | C22: applicant_number | D22: bigint
A23: 10 | B23: 所在地（カナ） | C23: location_kana | D23: varchar | E23: 100
A24: 11 | B24: 作成者 | C24: created_by | D24: bigint | F24: not null
A25: 12 | B25: 作成日時 | C25: created_at | D25: datetime | E25: 6 | F25: not null
A26: 13 | B26: 更新者 | C26: updated_by | D26: bigint | F26: not null
A27: 14 | B27: 更新日時 | C27: updated_at | D27: datetime | E27: 6 | F27: not null

Sheet 会社端数処理情報
A1: テーブル情報
B2: システム名 | C2: SOCIA | E2: 作成者 | I2: ITSP | M2: テーブル一覧へ
B3: サブシステム名 | C3: 給与 | E3: 作成日 | I3: 2025-11-28
B4: スキーマ名 | E4: RDBMS | I4: MySQL
B5: 論理テーブル名 | C5: 会社端数処理情報 | E5: ENGINE | I5: InnoDB
B6: 物理テーブル名 | C6: kaisya_fraction_process_info | E6: CHARSET | I6: utf8mb4
B7: 備考
A12: カラム情報 | L12: 外部キー情報
A13: No | B13: 論理名 | C13: 物理名 | D13: データ型 | E13: Size | F13: Not Null | G13: PK | H13: UK | I13: デフォルト | J13: 備考 | L13: 親テーブル | M13: 参照カラム
A14: 1 | B14: 会社コード | C14: kaisyacd | D14: varchar | E14: 20 | F14: not null | G14: 〇
A15: 2 | B15: 届出コード | C15: submission_code | D15: varchar | E15: 20 | F15: not null | G15: 〇
A16: 3 | B16: 有効開始年月日 | C16: fromymd | D16: date | F16: not null | G16: 〇
A17: 4 | B17: 有効終了年月日 | C17: toymd | D17: date | F17: not null
A18: 5 | B18: 給与健康被保険者 | C18: kyuyo_health_insured_person | D18: tinyint | J18: コードマスタ.SQS0073
A19: 6 | B19: 給与健康事業主 | C19: kyuyo_health_business_owner | D19: tinyint | J19: コードマスタ.SQS0073
A20: 7 | B20: 給与介護被保険者 | C20: kyuyo_care_insured_person | D20: tinyint | J20: コードマスタ.SQS0073
A21: 8 | B21: 給与介護事業主 | C21: kyuyo_care_business_owner | D21: tinyint | J21: コードマスタ.SQS0073
A22: 9 | B22: 給与厚生年金被保険者 | C22: kyuyo_kosei_pension_insured_person | D22: tinyint | J22: コードマスタ.SQS0073
A23: 10 | B23: 給与厚生年金事業主 | C23: kyuyo_kosei_pension_business_owner | D23: tinyint | J23: コードマスタ.SQS0073
A24: 11 | B24: 給与厚生年金基金被保険者 | C24: kyuyo_kosei_pension_fund_insured_person | D24: tinyint | J24: コードマスタ.SQS0073
A25: 12 | B25: 給与厚生年金基金事業主 | C25: kyuyo_kosei_pension_fund_business_owner | D25: tinyint | J25: コードマスタ.SQS0073
A26: 13 | B26: 賞与健康被保険者 | C26: syoyo_health_insured_person | D26: tinyint | J26: コードマスタ.SQS0073
A27: 14 | B27: 賞与健康事業主 | C27: syoyo_health_business_owner | D27: tinyint | J27: コードマスタ.SQS0073
A28: 15 | B28: 賞与介護被保険者 | C28: syoyo_care_insured_person | D28: tinyint | J28: コードマスタ.SQS0073
A29: 16 | B29: 賞与介護事業主 | C29: syoyo_care_business_owner | D29: tinyint | J29: コードマスタ.SQS0073
... A41: 28 | B41: 賞与健康事業主(特定) | C41: syoyo_health_business_owner_specific | D41: tinyint | J41: コードマスタ.SQS0073
A42: 29 | B42: 作成者 | C42: created_by | D42: bigint | F42: not null
A43: 30 | B43: 作成日時 | C43: created_at | D43: datetime | E43: 6 | F43: not null
A44: 31 | B44: 更新者 | C44: updated_by | D44: bigint | F44: not null
A45: 32 | B45: 更新日時 | C45: updated_at | D45: datetime | E45: 6 | F45: not null

Sheet 会社銀行
A1: テーブル情報
B2: システム名 | C2: SOCIA | E2: 作成者 | I2: ITSP | M2: テーブル一覧へ
B3: サブシステム名 | C3: 給与 | E3: 作成日 | I3: 2025-11-28
B4: スキーマ名 | E4: RDBMS | I4: MySQL
B5: 論理テーブル名 | C5: 会社銀行 | E5: ENGINE | I5: InnoDB
B6: 物理テーブル名 | C6: kaisya_bank | E6: CHARSET | I6: utf8mb4
B7: 備考
A12: カラム情報 | L12: 外部キー情報
A13: No | B13: 論理名 | C13: 物理名 | D13: データ型 | E13: Size | F13: Not Null | G13: PK | H13: UK | I13: デフォルト | J13: 備考 | L13: 親テーブル | M13: 参照カラム
A14: 1 | B14: 会社コード | C14: kaisyacd | D14: varchar | E14: 20 | F14: not null | G14: 〇
A15: 2 | B15: 届出コード | C15: submission_code | D15: varchar | E15: 20 | F15: not null | G15: 〇
A16: 3 | B16: 振込元銀行連番 | C16: remitter_bank_seq | D16: bigint | F16: not null | G16: 〇
A17: 4 | B17: 有効開始年月日 | C17: fromymd | D17: date | F17: not null | G17: 〇
A18: 5 | B18: 有効終了年月日 | C18: toymd | D18: date | F18: not null
A19: 6 | B19: 銀行コード | C19: bank_code | D19: varchar | E19: 20
A20: 7 | B20: 支店コード | C20: branch_code | D20: varchar | E20: 20
A21: 8 | B21: 口座種別区分 | C21: account_class_type | D21: tinyint | J21: コードマスタ.SQS0068
A22: 9 | B22: 口座番号 | C22: account_number | D22: bigint
A23: 10 | B23: 委託者コード | C23: client_code | D23: bigint
A24: 11 | B24: 作成者 | C24: created_by | D24: bigint | F24: not null
A25: 12 | B25: 作成日時 | C25: created_at | D25: datetime | E25: 6 | F25: not null
A26: 13 | B26: 更新者 | C26: updated_by | D26: bigint | F26: not null
A27: 14 | B27: 更新日時 | C27: updated_at | D27: datetime | E27: 6 | F27: not null

Sheet 会社雇用保険端数処理情報
A1: テーブル情報
B2: システム名 | C2: SOCIA | E2: 作成者 | I2: ITSP | M2: テーブル一覧へ
B3: サブシステム名 | C3: 給与 | E3: 作成日 | I3: 2025-11-28
B4: スキーマ名 | E4: RDBMS | I4: MySQL
B5: 論理テーブル名 | C5: 会社雇用保険端数処理情報 | E5: ENGINE | I5: InnoDB
B6: 物理テーブル名 | C6: kaisya_employment_insurance_fraction_process | E6: CHARSET | I6: utf8mb4
B7: 備考
A12: カラム情報 | L12: 外部キー情報
A13: No | B13: 論理名 | C13: 物理名 | D13: データ型 | E13: Size | F13: Not Null | G13: PK | H13: UK | I13: デフォルト | J13: 備考 | L13: 親テーブル | M13: 参照カラム
A14: 1 | B14: 会社コード | C14: kaisyacd | D14: varchar | E14: 20 | F14: not null | G14: 〇
A15: 2 | B15: 届出コード | C15: submission_code | D15: varchar | E15: 20 | F15: not null | G15: 〇
A16: 3 | B16: 有効開始年月日 | C16: fromymd | D16: date | F16: not null | G16: 〇
A17: 4 | B17: 有効終了年月日 | C17: toymd | D17: date | F17: not null
A18: 5 | B18: 雇用保険被保険者端数区分 | C18: employment_insurance_insured_person_fraction_type | D18: tinyint | J18: コードマスタ.SQS0074
A19: 6 | B19: 作成者 | C19: created_by | D19: bigint | F19: not null
A20: 7 | B20: 作成日時 | C20: created_at | D20: datetime | E20: 6 | F20: not null
A21: 8 | B21: 更新者 | C21: updated_by | D21: bigint | F21: not null
A22: 9 | B22: 更新日時 | C22: updated_at | D22: datetime | E22: 6 | F22: not null

Sheet 体系
A1: テーブル情報
B2: システム名 | C2: SOCIA | E2: 作成者 | I2: ITSP | M2: テーブル一覧へ
B3: サブシステム名 | C3: 給与 | E3: 作成日 | I3: 2025-11-28
B4: スキーマ名 | E4: RDBMS | I4: MySQL
B5: 論理テーブル名 | C5: 体系 | E5: ENGINE | I5: InnoDB
B6: 物理テーブル名 | C6: taikei | E6: CHARSET | I6: utf8mb4
B7: 備考
A12: カラム情報 | L12: 外部キー情報
A13: No | B13: 論理名 | C13: 物理名 | D13: データ型 | E13: Size | F13: Not Null | G13: PK | H13: UK | I13: デフォルト | J13: 備考 | L13: 親テーブル | M13: 参照カラム
A14: 1 | B14: 会社コード | C14: kaisyacd | D14: varchar | E14: 20 | F14: not null | G14: 〇
A15: 2 | B15: 支給区分 | C15: payment_type | D15: tinyint | F15: not null | G15: 〇 | J15: コードマスタ.SQS0013
A16: 3 | B16: 体系コード | C16: taikei_code | D16: varchar | E16: 20 | F16: not null | G16: 〇
A17: 4 | B17: 有効開始年月日 | C17: fromymd | D17: date | F17: not null | G17: 〇
A18: 5 | B18: 有効終了年月日 | C18: toymd | D18: date | F18: not null
A19: 6 | B19: 体系名称 | C19: taikei_name | D19: varchar | E19: 255 | F19: not null
A20: 7 | B20: 明細書出力月 | C20: statement_output_month | D20: tinyint
A21: 8 | B21: 税率区分 | C21: tax_rate_type | D21: tinyint | F21: not null | J21: コードマスタ.SQS0050
A22: 9 | B22: 年末調整項目 | C22: nencho_item | D22: varchar | E22: 20
A23: 10 | B23: 非表示フラグ | C23: hidden | D23: boolean | F23: not null
A24: 11 | B24: 備考 | C24: note | D24: text
A25: 12 | B25: 作成者 | C25: created_by | D25: bigint | F25: not null
A26: 13 | B26: 作成日時 | C26: created_at | D26: datetime | E26: 6 | F26: not null
A27: 14 | B27: 更新者 | C27: updated_by | D27: bigint | F27: not null
A28: 15 | B28: 更新日時 | C28: updated_at | D28: datetime | E28: 6 | F28: not null

Sheet 体系保険
A1: テーブル情報
B2: システム名 | C2: SOCIA | E2: 作成者 | I2: ITSP | M2: テーブル一覧へ
B3: サブシステム名 | C3: 給与 | E3: 作成日 | I3: 2025-11-28
B4: スキーマ名 | E4: RDBMS | I4: MySQL
B5: 論理テーブル名 | C5: 体系保険 | E5: ENGINE | I5: InnoDB
B6: 物理テーブル名 | C6: taikei_insurance | E6: CHARSET | I6: utf8mb4
B7: 備考
B8: 現行：QTISHOKENKOMOKU
A12: カラム情報 | L12: 外部キー情報
A13: No | B13: 論理名 | C13: 物理名 | D13: データ型 | E13: Size | F13: Not Null | G13: PK | H13: UK | I13: デフォルト | J13: 備考 | L13: 親テーブル | M13: 参照カラム
A14: 1 | B14: 会社コード | C14: kaisyacd | D14: varchar | E14: 20 | F14: not null | G14: 〇
A15: 2 | B15: 支給区分 | C15: payment_type | D15: tinyint | F15: not null | G15: 〇 | J15: コードマスタ.SQS0013
A16: 3 | B16: 体系コード | C16: taikei_code | D16: varchar | E16: 20 | F16: not null | G16: 〇
A17: 4 | B17: 体系項目コード | C17: taikei_item_code | D17: varchar | E17: 20 | F17: not null | G17: 〇
A18: 5 | B18: 保険区分 | C18: insurance_type | D18: tinyint | F18: not null | G18: 〇 | J18: コードマスタ.SQS0028
A19: 6 | B19: 保険会社コード | C19: insurance_kaisya_code | D19: varchar | E19: 20 | F19: not null | G19: 〇
A20: 7 | B20: 有効開始年月日 | C20: fromymd | D20: date | F20: not null | G20: 〇
A21: 8 | B21: 有効終了年月日 | C21: toymd | D21: date | F21: not null
A22: 9 | B22: 作成者 | C22: created_by | D22: bigint | F22: not null
A23: 10 | B23: 作成日時 | C23: created_at | D23: datetime | E23: 6 | F23: not null
A24: 11 | B24: 更新者 | C24: updated_by | D24: bigint | F24: not null
A25: 12 | B25: 更新日時 | C25: updated_at | D25: datetime | E25: 6 | F25: not null

Sheet 体系控除順
A1: テーブル情報
B2: システム名 | C2: SOCIA | E2: 作成者 | I2: ITSP | M2: テーブル一覧へ
B3: サブシステム名 | C3: 給与 | E3: 作成日 | I3: 2025-11-28
B4: スキーマ名 | E4: RDBMS | I4: MySQL
B5: 論理テーブル名 | C5: 体系控除順 | E5: ENGINE | I5: InnoDB
B6: 物理テーブル名 | C6: taikei_deduction_order | E6: CHARSET | I6: utf8mb4
B7: 備考
A12: カラム情報 | L12: 外部キー情報
A13: No | B13: 論理名 | C13: 物理名 | D13: データ型 | E13: Size | F13: Not Null | G13: PK | H13: UK | I13: デフォルト | J13: 備考 | L13: 親テーブル | M13: 参照カラム
A14: 1 | B14: 会社コード | C14: kaisyacd | D14: varchar | E14: 20 | F14: not null | G14: 〇
A15: 2 | B15: 支給区分 | C15: payment_type | D15: tinyint | F15: not null | G15: 〇 | J15: コードマスタ.SQS0013
A16: 3 | B16: 体系コード | C16: taikei_code | D16: varchar | E16: 20 | F16: not null | G16: 〇
A17: 4 | B17: 控除順 | C17: deduction_order | D17: smallint | F17: not null | G17: 〇
A18: 5 | B18: 有効開始年月日 | C18: fromymd | D18: date | F18: not null | G18: 〇
A19: 6 | B19: 有効終了年月日 | C19: toymd | D19: date | F19: not null
A20: 7 | B20: 控除項目コード | C20: deduction_item_code | D20: varchar | E20: 20 | F20: not null
A21: 8 | B21: 作成者 | C21: created_by | D21: bigint | F21: not null
A22: 9 | B22: 作成日時 | C22: created_at | D22: datetime | E22: 6 | F22: not null
A23: 10 | B23: 更新者 | C23: updated_by | D23: bigint | F23: not null
A24: 11 | B24: 更新日時 | C24: updated_at | D24: datetime | E24: 6 | F24: not null

Sheet 体系明細書
A1: テーブル情報
B2: システム名 | C2: SOCIA | E2: 作成者 | I2: ITSP | M2: テーブル一覧へ
B3: サブシステム名 | C3: 給与 | E3: 作成日 | I3: 2025-11-28
B4: スキーマ名 | E4: RDBMS | I4: MySQL
B5: 論理テーブル名 | C5: 体系明細書 | E5: ENGINE | I5: InnoDB
B6: 物理テーブル名 | C6: taikei_statement | E6: CHARSET | I6: utf8mb4
B7: 備考
A12: カラム情報 | L12: 外部キー情報
A13: No | B13: 論理名 | C13: 物理名 | D13: データ型 | E13: Size | F13: Not Null | G13: PK | H13: UK | I13: デフォルト | J13: 備考 | L13: 親テーブル | M13: 参照カラム
A14: 1 | B14: 会社コード | C14: kaisyacd | D14: varchar | E14: 20 | F14: not null | G14: 〇
A15: 2 | B15: 支給区分 | C15: payment_type | D15: tinyint | F15: not null | G15: 〇 | J15: コードマスタ.SQS0013
A16: 3 | B16: 体系コード | C16: taikei_code | D16: varchar | E16: 20 | F16: not null | G16: 〇
A17: 4 | B17: 明細書コード | C17: statement_code | D17: varchar | E17: 20 | F17: not null | G17: 〇
A18: 5 | B18: 列番号 | C18: columnno | D18: int | F18: not null | G18: 〇
A19: 6 | B19: 行番号 | C19: lineno | D19: int | F19: not null | G19: 〇
A20: 7 | B20: 有効開始年月日 | C20: fromymd | D20: date | F20: not null | G20: 〇
A21: 8 | B21: 有効終了年月日 | C21: toymd | D21: date | F21: not null
A22: 9 | B22: 体系項目コード | C22: taikei_item_code | D22: varchar | E22: 20 | F22: not null
A23: 10 | B23: 作成者 | C23: created_by | D23: bigint | F23: not null
A24: 11 | B24: 作成日時 | C24: created_at | D24: datetime | E24: 6 | F24: not null
A25: 12 | B25: 更新者 | C25: updated_by | D25: bigint | F25: not null
A26: 13 | B26: 更新日時 | C26: updated_at | D26: datetime | E26: 6 | F26: not null

Sheet 体系明細書基本
A1: テーブル情報
B2: システム名 | C2: SOCIA | E2: 作成者 | I2: ITSP | M2: テーブル一覧へ
B3: サブシステム名 | C3: 給与 | E3: 作成日 | I3: 2025-11-28
B4: スキーマ名 | E4: RDBMS | I4: MySQL
B5: 論理テーブル名 | C5: 体系明細書基本 | E5: ENGINE | I5: InnoDB
B6: 物理テーブル名 | C6: taikei_statement_basic | E6: CHARSET | I6: utf8mb4
B7: 備考
A12: カラム情報 | L12: 外部キー情報
A13: No | B13: 論理名 | C13: 物理名 | D13: データ型 | E13: Size | F13: Not Null | G13: PK | H13: UK | I13: デフォルト | J13: 備考 | L13: 親テーブル | M13: 参照カラム
A14: 1 | B14: 会社コード | C14: kaisyacd | D14: varchar | E14: 20 | F14: not null | G14: 〇
A15: 2 | B15: 支給区分 | C15: payment_type | D15: tinyint | F15: not null | G15: 〇 | J15: コードマスタ.SQS0013
A16: 3 | B16: 体系コード | C16: taikei_code | D16: varchar | E16: 20 | F16: not null | G16: 〇
A17: 4 | B17: 明細書コード | C17: statement_code | D17: varchar | E17: 20 | F17: not null | G17: 〇
A18: 5 | B18: 有効開始年月日 | C18: fromymd | D18: date | F18: not null | G18: 〇
A19: 6 | B19: 有効終了年月日 | C19: toymd | D19: date | F19: not null
A20: 7 | B20: 明細書名称 | C20: statement_name | D20: varchar | E20: 255 | F20: not null
A21: 8 | B21: タイトル | C21: title | D21: varchar | E21: 50
A22: 9 | B22: 項目1ラベル | C22: item1_label | D22: varchar | E22: 255
A23: 10 | B23: 項目1表示項目ID | C23: item1_dsp_itemid | D23: varchar | E23: 20
A24: 11 | B24: 項目1表示タイプ | C24: item1_dsp_type | D24: json | J24: {"code":true|false,"name":true|false,"shorname":true|false}
A25: 12 | B25: 項目2ラベル | C25: item2_label | D25: varchar | E25: 255
A26: 13 | B26: 項目2表示項目ID | C26: item2_dsp_itemid | D26: varchar | E26: 20
A27: 14 | B27: 項目2表示タイプ | C27: item2_dsp_type | D27: json | J27: {"code":true|false,"name":true|false,"shorname":true|false}
A28: 15 | B28: 明細レイアウトJSON | C28: detail_layout_json | D28: json | J28: {"laborNo": 7, "paymentNo" 8, "deductionNo":9, "totalNo":6}
A29: 16 | B29: 作成者 | C29: created_by | D29: bigint | F29: not null
A30: 17 | B30: 作成日時 | C30: created_at | D30: datetime | E30: 6 | F30: not null
A31: 18 | B31: 更新者 | C31: updated_by | D31: bigint | F31: not null
A32: 19 | B32: 更新日時 | C32: updated_at | D32: datetime | E32: 6 | F32: not null

Sheet 体系明細書条件
A1: テーブル情報
B2: システム名 | C2: SOCIA | E2: 作成者 | I2: ITSP | M2: テーブル一覧へ
B3: サブシステム名 | C3: 給与 | E3: 作成日 | I3: 2025-11-28
B4: スキーマ名 | E4: RDBMS | I4: MySQL
B5: 論理テーブル名 | C5: 体系明細書条件 | E5: ENGINE | I5: InnoDB
B6: 物理テーブル名 | C6: taikei_statement_condition | E6: CHARSET | I6: utf8mb4
B7: 備考
B8: ・就業の計算プロセス条件式と合わせる_x000D_ ・抽出条件だけ利用(計算条件不要)
A12: カラム情報 | L12: 外部キー情報
A13: No | B13: 論理名 | C13: 物理名 | D13: データ型 | E13: Size | F13: Not Null | G13: PK | H13: UK | I13: デフォルト | J13: 備考 | L13: 親テーブル | M13: 参照カラム
A14: 1 | B14: 会社コード | C14: kaisyacd | D14: varchar | E14: 20 | F14: not null | G14: 〇
A15: 2 | B15: 支給区分 | C15: payment_type | D15: tinyint | F15: not null | G15: 〇 | J15: コードマスタ.SQS0013
A16: 3 | B16: 体系コード | C16: taikei_code | D16: varchar | E16: 20 | F16: not null | G16: 〇
A17: 4 | B17: 明細書コード | C17: statement_code | D17: varchar | E17: 20 | F17: not null | G17: 〇
A18: 5 | B18: 有効開始年月日 | C18: fromymd | D18: date | F18: not null | G18: 〇
A19: 6 | B19: 有効終了年月日 | C19: toymd | D19: date | F19: not null
A20: 7 | B20: 表示用条件式 | C20: dsp_condition | D20: text
A21: 8 | B21: 実行用条件式 | C21: execute_condition | D21: text
A22: 9 | B22: 作成者 | C22: created_by | D22: bigint | F22: not null
A23: 10 | B23: 作成日時 | C23: created_at | D23: datetime | E23: 6 | F23: not null
A24: 11 | B24: 更新者 | C24: updated_by | D24: bigint | F24: not null
A25: 12 | B25: 更新日時 | C25: updated_at | D25: datetime | E25: 6 | F25: not null

Sheet 体系条件
A1: テーブル情報
B2: システム名 | C2: SOCIA | E2: 作成者 | I2: ITSP | M2: テーブル一覧へ
B3: サブシステム名 | C3: 給与 | E3: 作成日 | I3: 2025-11-28
B4: スキーマ名 | E4: RDBMS | I4: MySQL
B5: 論理テーブル名 | C5: 体系条件 | E5: ENGINE | I5: InnoDB
B6: 物理テーブル名 | C6: taikei_condition | E6: CHARSET | I6: utf8mb4
B7: 備考
B8: ・就業の計算プロセス条件式と合わせる_x000D_ ・抽出条件だけ利用(計算条件不要)
A12: カラム情報 | L12: 外部キー情報
A13: No | B13: 論理名 | C13: 物理名 | D13: データ型 | E13: Size | F13: Not Null | G13: PK | H13: UK | I13: デフォルト | J13: 備考 | L13: 親テーブル | M13: 参照カラム
A14: 1 | B14: 会社コード | C14: kaisyacd | D14: varchar | E14: 20 | F14: not null | G14: 〇
A15: 2 | B15: 支給区分 | C15: payment_type | D15: tinyint | F15: not null | G15: 〇 | J15: コードマスタ.SQS0013
A16: 3 | B16: 体系コード | C16: taikei_code | D16: varchar | E16: 20 | F16: not null | G16: 〇
A17: 4 | B17: 有効開始年月日 | C17: fromymd | D17: date | F17: not null | G17: 〇
A18: 5 | B18: 有効終了年月日 | C18: toymd | D18: date | F18: not null
A19: 6 | B19: 表示用条件式 | C19: dsp_condition | D19: text
A20: 7 | B20: 実行用条件式 | C20: execute_condition | D20: text
A21: 8 | B21: 作成者 | C21: created_by | D21: bigint | F21: not null
A22: 9 | B22: 作成日時 | C22: created_at | D22: datetime | E22: 6 | F22: not null
A23: 10 | B23: 更新者 | C23: updated_by | D23: bigint | F23: not null
A24: 11 | B24: 更新日時 | C24: updated_at | D24: datetime | E24: 6 | F24: not null

Sheet 体系締日
A1: テーブル情報
B2: システム名 | C2: SOCIA | E2: 作成者 | I2: ITSP | M2: テーブル一覧へ
B3: サブシステム名 | C3: 給与 | E3: 作成日 | I3: 2025-11-28
B4: スキーマ名 | E4: RDBMS | I4: MySQL
B5: 論理テーブル名 | C5: 体系締日 | E5: ENGINE | I5: InnoDB
B6: 物理テーブル名 | C6: taikei_shime_day | E6: CHARSET | I6: utf8mb4
B7: 備考
B8: # 238109 より、同じ締日・支給月区分、支給日で体系が異なるケースはない_x000D_ 会社コード、基準日の条件で、支給区分、締日・支給月区分、支給日のユニック制約が必要
A12: カラム情報 | L12: 外部キー情報
A13: No | B13: 論理名 | C13: 物理名 | D13: データ型 | E13: Size | F13: Not Null | G13: PK | H13: UK | I13: デフォルト | J13: 備考 | L13: 親テーブル | M13: 参照カラム
A14: 1 | B14: 会社コード | C14: kaisyacd | D14: varchar | E14: 20 | F14: not null | G14: 〇
A15: 2 | B15: 支給区分 | C15: payment_type | D15: tinyint | F15: not null | G15: 〇 | J15: コードマスタ.SQS0013
A16: 3 | B16: 体系コード | C16: taikei_code | D16: varchar | E16: 20 | F16: not null | G16: 〇
A17: 4 | B17: 締日コード | C17: shime_day_code | D17: varchar | E17: 20 | F17: not null | G17: 〇
A18: 5 | B18: 有効開始年月日 | C18: fromymd | D18: date | F18: not null | G18: 〇
A19: 6 | B19: 有効終了年月日 | C19: toymd | D19: date | F19: not null
A20: 7 | B20: 締日 | C20: shime_day | D20: tinyint | F20: not null
A21: 8 | B21: 支給月区分 | C21: payment_month_type | D21: tinyint | F21: not null | J21: コードマスタ.SQS0012
A22: 9 | B22: 支給日 | C22: payment_day | D22: tinyint | F22: not null
A23: 10 | B23: 非表示フラグ | C23: hidden | D23: boolean | F23: not null
A24: 11 | B24: 有給更新区分 | C24: paid_update_type | D24: tinyint
A25: 12 | B25: 備考 | C25: note | D25: text
A26: 13 | B26: 作成者 | C26: created_by | D26: bigint | F26: not null
A27: 14 | B27: 作成日時 | C27: created_at | D27: datetime | E27: 6 | F27: not null
A28: 15 | B28: 更新者 | C28: updated_by | D28: bigint | F28: not null
A29: 16 | B29: 更新日時 | C29: updated_at | D29: datetime | E29: 6 | F29: not null

Sheet 体系項目
A1: テーブル情報
B2: システム名 | C2: SOCIA | E2: 作成者 | I2: ITSP | M2: テーブル一覧へ
B3: サブシステム名 | C3: 給与 | E3: 作成日 | I3: 2025-11-28
B4: スキーマ名 | E4: RDBMS | I4: MySQL
B5: 論理テーブル名 | C5: 体系項目 | E5: ENGINE | I5: InnoDB
B6: 物理テーブル名 | C6: taikei_item | E6: CHARSET | I6: utf8mb4
B7: 備考
A12: カラム情報 | L12: 外部キー情報
A13: No | B13: 論理名 | C13: 物理名 | D13: データ型 | E13: Size | F13: Not Null | G13: PK | H13: UK | I13: デフォルト | J13: 備考 | L13: 親テーブル | M13: 参照カラム
A14: 1 | B14: 会社コード | C14: kaisyacd | D14: varchar | E14: 20 | F14: not null | G14: 〇
A15: 2 | B15: 支給区分 | C15: payment_type | D15: tinyint | F15: not null | G15: 〇 | J15: コードマスタ.SQS0013
A16: 3 | B16: 体系コード | C16: taikei_code | D16: varchar | E16: 20 | F16: not null | G16: 〇
A17: 4 | B17: 体系項目コード | C17: taikei_item_code | D17: varchar | E17: 20 | F17: not null | G17: 〇
A18: 5 | B18: 有効開始年月日 | C18: fromymd | D18: date | F18: not null | G18: 〇
A19: 6 | B19: 有効終了年月日 | C19: toymd | D19: date | F19: not null
A20: 7 | B20: 支給控除区分 | C20: payment_deduction_type | D20: tinyint | F20: not null | J20: コードマスタ.SQS0049
A21: 8 | B21: 設定区分 | C21: settype | D21: tinyint | J21: コードマスタ.SQS0076
A22: 9 | B22: 項目名称 | C22: item_name | D22: varchar | E22: 255 | F22: not null
A23: 10 | B23: 項目略称 | C23: item_shortname | D23: varchar | E23: 255 | J23: #209802 データ型固定
A24: 11 | B24: 項目区分 | C24: item_category | D24: tinyint | F24: not null | J24: コードマスタ.SQS0027
A25: 12 | B25: 表示区分 | C25: dsp_type | D25: tinyint | F25: not null | J25: コードマスタ.SQS0077
A26: 13 | B26: 項目型区分 | C26: data_type | D26: smallint | F26: not null | J26: コードマスタ.SRS0003
A27: 14 | B27: 選択項目ID | C27: code_itemid | D27: bigint
A28: 15 | B28: 入力必須フラグ | C28: required | D28: boolean | F28: not null
A29: 16 | B29: 項目型設定格納値JSON | C29: data_type_store_json | D29: json | F29: not null
A30: 17 | B30: 非表示フラグ | C30: hidden | D30: boolean | F30: not null
A31: 18 | B31: 備考 | C31: note | D31: text
A32: 19 | B32: 計算式区分 | C32: equation_type | D32: tinyint | F32: not null | J32: コードマスタ.SQS0014
A33: 20 | B33: データ連番 | C33: dataseq | D33: int | F33: not null
A34: 21 | B34: 遡及対象区分 | C34: retroactive_target_type | D34: tinyint | J34: コードマスタ.SQS0061
A35: 22 | B35: 作成者 | C35: created_by | D35: bigint | F35: not null
A36: 23 | B36: 作成日時 | C36: created_at | D36: datetime | E36: 6 | F36: not null
A37: 24 | B37: 更新者 | C37: updated_by | D37: bigint | F37: not null
A38: 25 | B38: 更新日時 | C38: updated_at | D38: datetime | E38: 6 | F38: not null

Sheet 体系項目就業連動
A1: テーブル情報
B2: システム名 | C2: SOCIA | E2: 作成者 | I2: ITSP | M2: テーブル一覧へ
B3: サブシステム名 | C3: 給与 | E3: 作成日 | I3: 2025-11-28
B4: スキーマ名 | E4: RDBMS | I4: MySQL
B5: 論理テーブル名 | C5: 体系項目就業連動 | E5: ENGINE | I5: InnoDB
B6: 物理テーブル名 | C6: taikei_item_syugyo_linked | E6: CHARSET | I6: utf8mb4
B7: 備考
B8: 就業変動項目連動マスタ
A12: カラム情報 | L12: 外部キー情報
A13: No | B13: 論理名 | C13: 物理名 | D13: データ型 | E13: Size | F13: Not Null | G13: PK | H13: UK | I13: デフォルト | J13: 備考 | L13: 親テーブル | M13: 参照カラム
A14: 1 | B14: 会社コード | C14: kaisyacd | D14: varchar | E14: 20 | F14: not null | G14: 〇
A15: 2 | B15: 支給区分 | C15: payment_type | D15: tinyint | F15: not null | G15: 〇 | J15: コードマスタ.SQS0013
A16: 3 | B16: 体系コード | C16: taikei_code | D16: varchar | E16: 20 | F16: not null | G16: 〇
A17: 4 | B17: 体系項目コード | C17: taikei_item_code | D17: varchar | E17: 20 | F17: not null | G17: 〇
A18: 5 | B18: 就業体系コード | C18: syugyo_taikei_code | D18: varchar | E18: 20 | F18: not null | G18: 〇
A19: 6 | B19: 集計単位 | C19: total_unit | D19: smallint | F19: not null | G19: 〇
A20: 7 | B20: 体系集計項目コード | C20: taikei_total_item_code | D20: varchar | E20: 20 | F20: not null | G20: 〇
A21: 8 | B21: 有効開始年月日 | C21: fromymd | D21: date | F21: not null | G21: 〇
A22: 9 | B22: 有効終了年月日 | C22: toymd | D22: date | F22: not null
A23: 10 | B23: 作成者 | C23: created_by | D23: bigint | F23: not null
A24: 11 | B24: 作成日時 | C24: created_at | D24: datetime | E24: 6 | F24: not null
A25: 12 | B25: 更新者 | C25: updated_by | D25: bigint | F25: not null
A26: 13 | B26: 更新日時 | C26: updated_at | D26: datetime | E26: 6 | F26: not null

Sheet 体系項目計算式
A1: テーブル情報
B2: システム名 | C2: SOCIA | E2: 作成者 | I2: ITSP | M2: テーブル一覧へ
B3: サブシステム名 | C3: 給与 | E3: 作成日 | I3: 2025-11-28
B4: スキーマ名 | E4: RDBMS | I4: MySQL
B5: 論理テーブル名 | C5: 体系項目計算式 | E5: ENGINE | I5: InnoDB
B6: 物理テーブル名 | C6: taikei_item_equation | E6: CHARSET | I6: utf8mb4
B7: 備考
B8: ストアド名が唯一制約必要
A12: カラム情報 | L12: 外部キー情報
A13: No | B13: 論理名 | C13: 物理名 | D13: データ型 | E13: Size | F13: Not Null | G13: PK | H13: UK | I13: デフォルト | J13: 備考 | L13: 親テーブル | M13: 参照カラム
A14: 1 | B14: 会社コード | C14: kaisyacd | D14: varchar | E14: 20 | F14: not null | G14: 〇
A15: 2 | B15: 支給区分 | C15: payment_type | D15: tinyint | F15: not null | G15: 〇 | J15: コードマスタ.SQS0013
A16: 3 | B16: 体系コード | C16: taikei_code | D16: varchar | E16: 20 | F16: not null | G16: 〇
A17: 4 | B17: 体系項目コード | C17: taikei_item_code | D17: varchar | E17: 20 | F17: not null | G17: 〇
A18: 5 | B18: 有効開始年月日 | C18: fromymd | D18: date | F18: not null | G18: 〇
A19: 6 | B19: 有効終了年月日 | C19: toymd | D19: date
A20: 7 | B20: ストアド名 | C20: stored_name | D20: varchar | E20: 255 | F20: not null
A21: 8 | B21: 戻り値型区分 | C21: return_type | D21: tinyint
A22: 9 | B22: 表示用計算式 | C22: dsp_equation | D22: text
A23: 10 | B23: 実行用計算式 | C23: execute_equation | D23: json | J23: データ型固定:JSON_x000D_ ・sql：ストアドのSQL文_x000D_ ・計算項目リスト：変換用情報_x000D_ ・変数リスト：変換用情報
A24: 11 | B24: 作成者 | C24: created_by | D24: bigint | F24: not null
A25: 12 | B25: 作成日時 | C25: created_at | D25: datetime | E25: 6 | F25: not null
A26: 13 | B26: 更新者 | C26: updated_by | D26: bigint | F26: not null
A27: 14 | B27: 更新日時 | C27: updated_at | D27: datetime | E27: 6 | F27: not null

Sheet 体系項目関連
A1: テーブル情報
B2: システム名 | C2: SOCIA | E2: 作成者 | I2: ITSP | M2: テーブル一覧へ
B3: サブシステム名 | C3: 給与 | E3: 作成日 | I3: 2025-11-28
B4: スキーマ名 | E4: RDBMS | I4: MySQL
B5: 論理テーブル名 | C5: 体系項目関連 | E5: ENGINE | I5: InnoDB
B6: 物理テーブル名 | C6: taikei_item_relation | E6: CHARSET | I6: utf8mb4
B7: 備考
A12: カラム情報 | L12: 外部キー情報
A13: No | B13: 論理名 | C13: 物理名 | D13: データ型 | E13: Size | F13: Not Null | G13: PK | H13: UK | I13: デフォルト | J13: 備考 | L13: 親テーブル | M13: 参照カラム
A14: 1 | B14: 会社コード | C14: kaisyacd | D14: varchar | E14: 20 | F14: not null | G14: 〇
A15: 2 | B15: 支給区分 | C15: payment_type | D15: tinyint | F15: not null | G15: 〇 | J15: コードマスタ.SQS0013
A16: 3 | B16: 体系コード | C16: taikei_code | D16: varchar | E16: 20 | F16: not null | G16: 〇
A17: 4 | B17: 体系項目コード | C17: taikei_item_code | D17: varchar | E17: 20 | F17: not null | G17: 〇
A18: 5 | B18: 対象区分 | C18: target_type | D18: tinyint | F18: not null | G18: 〇
A19: 6 | B19: 項目コード | C19: item_code | D19: varchar | E19: 20 | F19: not null | G19: 〇
A20: 7 | B20: 有効開始年月日 | C20: fromymd | D20: date | F20: not null | G20: 〇
A21: 8 | B21: 有効終了年月日 | C21: toymd | D21: date | F21: not null
A22: 9 | B22: 関連区分 | C22: relation_type | D22: tinyint | F22: not null | J22: コードマスタ.SQS0032
A23: 10 | B23: 選択区分 | C23: selection_type | D23: tinyint | F23: not null | J23: コードマスタ.SQS0019
A24: 11 | B24: 作成者 | C24: created_by | D24: bigint | F24: not null
A25: 12 | B25: 作成日時 | C25: created_at | D25: datetime | E25: 6 | F25: not null
A26: 13 | B26: 更新者 | C26: updated_by | D26: bigint | F26: not null
A27: 14 | B27: 更新日時 | C27: updated_at | D27: datetime | E27: 6 | F27: not null

Sheet 保険会社
A1: テーブル情報
B2: システム名 | C2: SOCIA | E2: 作成者 | I2: ITSP | M2: テーブル一覧へ
B3: サブシステム名 | C3: 給与 | E3: 作成日 | I3: 2025-11-28
B4: スキーマ名 | E4: RDBMS | I4: MySQL
B5: 論理テーブル名 | C5: 保険会社 | E5: ENGINE | I5: InnoDB
B6: 物理テーブル名 | C6: insurance_kaisya | E6: CHARSET | I6: utf8mb4
B7: 備考
B8: #238673より、保険会社の事業部/届出 毎の必要がなくなる
A12: カラム情報 | L12: 外部キー情報
A13: No | B13: 論理名 | C13: 物理名 | D13: データ型 | E13: Size | F13: Not Null | G13: PK | H13: UK | I13: デフォルト | J13: 備考 | L13: 親テーブル | M13: 参照カラム
A14: 1 | B14: 会社コード | C14: kaisyacd | D14: varchar | E14: 20 | F14: not null | G14: 〇
A15: 2 | B15: 保険区分 | C15: insurance_type | D15: tinyint | F15: not null | G15: 〇
A16: 3 | B16: 保険会社コード | C16: insurance_kaisya_code | D16: varchar | E16: 20 | F16: not null | G16: 〇
A17: 4 | B17: 会社名称 | C17: kaisya_name | D17: varchar | E17: 255
A18: 5 | B18: 会社略称 | C18: kaisya_shortname | D18: varchar | E18: 255
A19: 6 | B19: 会社カナ名 | C19: kaisya_kananame | D19: varchar | E19: 255
A20: 7 | B20: 担当者 | C20: representative | D20: varchar | E20: 255
A21: 8 | B21: 郵便番号 | C21: postal_code | D21: varchar | E21: 10
A22: 9 | B22: 住所 | C22: address | D22: varchar | E22: 100
A23: 10 | B23: 電話番号 | C23: tel | D23: varchar | E23: 20
A24: 11 | B24: 団体コード | C24: group_code | D24: varchar | E24: 20
A25: 12 | B25: 社員番号開始カラム番号 | C25: syainno_from_column_number | D25: tinyint
A26: 13 | B26: 社員番号桁数 | C26: syainno_digit | D26: tinyint
A27: 14 | B27: 反映元区分 | C27: reflection_from_type | D27: tinyint
A28: 15 | B28: 作成者 | C28: created_by | D28: bigint | F28: not null
A29: 16 | B29: 作成日時 | C29: created_at | D29: datetime | E29: 6 | F29: not null
A30: 17 | B30: 更新者 | C30: updated_by | D30: bigint | F30: not null
A31: 18 | B31: 更新日時 | C31: updated_at | D31: datetime | E31: 6 | F31: not null

Sheet 保険料取得ログ
A1: テーブル情報
B2: システム名 | C2: SOCIA | E2: 作成者 | I2: ITSP | M2: テーブル一覧へ
B3: サブシステム名 | C3: 給与 | E3: 作成日 | I3: 2025-11-28
B4: スキーマ名 | E4: RDBMS | I4: MySQL
B5: 論理テーブル名 | C5: 保険料取得ログ | E5: ENGINE | I5: InnoDB
B6: 物理テーブル名 | C6: insurance_get_log | E6: CHARSET | I6: utf8mb4
B7: 備考
A12: カラム情報 | L12: 外部キー情報
A13: No | B13: 論理名 | C13: 物理名 | D13: データ型 | E13: Size | F13: Not Null | G13: PK | H13: UK | I13: デフォルト | J13: 備考 | L13: 親テーブル | M13: 参照カラム
A14: 1 | B14: 会社コード | C14: kaisyacd | D14: varchar | E14: 20 | F14: not null | G14: 〇
A15: 2 | B15: 届出コード | C15: submission_code | D15: varchar | E15: 20 | F15: not null | G15: 〇
A16: 3 | B16: 保険区分 | C16: insurance_type | D16: tinyint | F16: not null | G16: 〇
A17: 4 | B17: 保険会社コード | C17: insurance_kaisya_code | D17: varchar | E17: 20 | F17: not null | G17: 〇
A18: 5 | B18: 処理区分 | C18: process_type | D18: tinyint | F18: not null | G18: 〇
A19: 6 | B19: 支給区分 | C19: payment_type | D19: tinyint | F19: not null | G19: 〇
A20: 7 | B20: 案内年 | C20: guide_year | D20: smallint | F20: not null | G20: 〇
A21: 8 | B21: 案内月 | C21: guide_month | D21: smallint | F21: not null | G21: 〇
A22: 9 | B22: 控除年 | C22: deduction_year | D22: smallint | F22: not null | G22: 〇
A23: 10 | B23: 控除月 | C23: deduction_month | D23: smallint | F23: not null | G23: 〇
A24: 11 | B24: 取込グループ番号 | C24: import_group_number | D24: smallint | F24: not null | G24: 〇
A25: 12 | B25: 取込ＳＥＱ | C25: import_seq | D25: smallint | F25: not null | G25: 〇
A26: 13 | B26: 処理実行日 | C26: process_execute_date | D26: date
A27: 14 | B27: 処理実行時間 | C27: process_execute_time | D27: datetime | E27: 6
A28: 15 | B28: 実行ユーザーＩＤ | C28: execute_userid | D28: varchar | E28: 30
A29: 16 | B29: 取込ファイル名 | C29: import_file_name | D29: varchar | E29: 128
A30: 17 | B30: 出力ファイル名 | C30: output_file_name | D30: varchar | E30: 128
A31: 18 | B31: 反映区分 | C31: reflect_type | D31: tinyint
A32: 19 | B32: 返還区分 | C32: return_type | D32: tinyint
A33: 20 | B33: 作成者 | C33: created_by | D33: bigint | F33: not null
A34: 21 | B34: 作成日時 | C34: created_at | D34: datetime | E34: 6 | F34: not null
A35: 22 | B35: 更新者 | C35: updated_by | D35: bigint | F35: not null
A36: 23 | B36: 更新日時 | C36: updated_at | D36: datetime | E36: 6 | F36: not null

Sheet 健康保険料額
A1: テーブル情報
B2: システム名 | C2: SOCIA | E2: 作成者 | I2: ITSP | M2: テーブル一覧へ
B3: サブシステム名 | C3: 給与 | E3: 作成日 | I3: 2025-11-28
B4: スキーマ名 | E4: RDBMS | I4: MySQL
B5: 論理テーブル名 | C5: 健康保険料額 | E5: ENGINE | I5: InnoDB
B6: 物理テーブル名 | C6: health_insurance_amount | E6: CHARSET | I6: utf8mb4
B7: 備考
A12: カラム情報 | L12: 外部キー情報
A13: No | B13: 論理名 | C13: 物理名 | D13: データ型 | E13: Size | F13: Not Null | G13: PK | H13: UK | I13: デフォルト | J13: 備考 | L13: 親テーブル | M13: 参照カラム
A14: 1 | B14: 会社コード | C14: kaisyacd | D14: varchar | E14: 20 | F14: not null | G14: 〇
A15: 2 | B15: 届出コード | C15: submission_code | D15: varchar | E15: 20 | F15: not null | G15: 〇
A16: 3 | B16: 等級 | C16: grade | D16: smallint | F16: not null | G16: 〇
A17: 4 | B17: 有効開始年月日 | C17: fromymd | D17: date | F17: not null | G17: 〇
A18: 5 | B18: 有効終了年月日 | C18: toymd | D18: date | F18: not null
A19: 6 | B19: 標準報酬月額 | C19: standard_reward_month_amount | D19: bigint | F19: not null
A20: 7 | B20: 報酬月額 | C20: reward_monthly | D20: bigint
A21: 8 | B21: 被保険者 | C21: insured_person | D21: int | F21: not null
A22: 9 | B22: 事業主 | C22: business_owner | D22: int | F22: not null
A23: 10 | B23: 被保険者(基本) | C23: insured_person_basic | D23: int | F23: not null
A24: 11 | B24: 事業主(基本) | C24: business_owner_basic | D24: int | F24: not null
A25: 12 | B25: 被保険者(特定) | C25: insured_person_specific | D25: int | F25: not null
A26: 13 | B26: 事業主(特定) | C26: business_owner_specific | D26: int | F26: not null
A27: 14 | B27: 作成者 | C27: created_by | D27: bigint | F27: not null
A28: 15 | B28: 作成日時 | C28: created_at | D28: datetime | E28: 6 | F28: not null
A29: 16 | B29: 更新者 | C29: updated_by | D29: bigint | F29: not null
A30: 17 | B30: 更新日時 | C30: updated_at | D30: datetime | E30: 6 | F30: not null

Sheet 出勤日数
A1: テーブル情報
B2: システム名 | C2: SOCIA | E2: 作成者 | I2: ITSP | M2: テーブル一覧へ
B3: サブシステム名 | C3: 給与 | E3: 作成日 | I3: 2025-11-28
B4: スキーマ名 | E4: RDBMS | I4: MySQL
B5: 論理テーブル名 | C5: 出勤日数 | E5: ENGINE | I5: InnoDB
B6: 物理テーブル名 | C6: attendance_day | E6: CHARSET | I6: utf8mb4
B7: 備考
A12: カラム情報 | L12: 外部キー情報
A13: No | B13: 論理名 | C13: 物理名 | D13: データ型 | E13: Size | F13: Not Null | G13: PK | H13: UK | I13: デフォルト | J13: 備考 | L13: 親テーブル | M13: 参照カラム
A14: 1 | B14: 会社コード | C14: kaisyacd | D14: varchar | E14: 20 | F14: not null | G14: 〇
A15: 2 | B15: 支給区分 | C15: payment_type | D15: tinyint | F15: not null | G15: 〇 | J15: コードマスタ.SQS0013
A16: 3 | B16: 体系コード | C16: taikei_code | D16: varchar | E16: 20 | F16: not null | G16: 〇
A17: 4 | B17: 出勤日数コード | C17: attendance_day_code | D17: varchar | E17: 20 | F17: not null | G17: 〇
A18: 5 | B18: 有効開始年月日 | C18: fromymd | D18: date | F18: not null | G18: 〇
A19: 6 | B19: 有効終了年月日 | C19: toymd | D19: date | F19: not null
A20: 7 | B20: 出勤日数名称 | C20: attendance_day_name | D20: varchar | E20: 255 | F20: not null
A21: 8 | B21: 項目型区分 | C21: data_type | D21: smallint | J21: コードマスタ.SRS0003
A22: 9 | B22: 選択項目ID | C22: code_itemid | D22: bigint | F22: not null
A23: 10 | B23: 入力必須フラグ | C23: required | D23: boolean | F23: not null
A24: 11 | B24: 項目型設定格納値JSON | C24: data_type_store_json | D24: json | F24: not null
A25: 12 | B25: １月出勤日数 | C25: january_attendance_day | D25: smallint | F25: not null
A26: 13 | B26: ２月出勤日数 | C26: february_attendance_day | D26: smallint | F26: not null
A27: 14 | B27: ３月出勤日数 | C27: march_attendance_day | D27: smallint | F27: not null
A28: 15 | B28: ４月出勤日数 | C28: april_attendance_day | D28: smallint | F28: not null
A29: 16 | B29: ５月出勤日数 | C29: may_attendance_day | D29: smallint | F29: not null
A30: 17 | B30: ６月出勤日数 | C30: june_attendance_day | D30: smallint | F30: not null
A31: 18 | B31: ７月出勤日数 | C31: july_attendance_day | D31: smallint | F31: not null
A32: 19 | B32: ８月出勤日数 | C32: august_attendance_day | D32: smallint | F32: not null
A33: 20 | B33: ９月出勤日数 | C33: september_attendance_day | D33: smallint | F33: not null
... A37: 24 | B37: 作成者 | C37: created_by | D37: bigint | F37: not null
A38: 25 | B38: 作成日時 | C38: created_at | D38: datetime | E38: 6 | F38: not null
A39: 26 | B39: 更新者 | C39: updated_by | D39: bigint | F39: not null
A40: 27 | B40: 更新日時 | C40: updated_at | D40: datetime | E40: 6 | F40: not null

Sheet 割当情報
A1: テーブル情報
B2: システム名 | C2: SOCIA | E2: 作成者 | I2: ITSP | M2: テーブル一覧へ
B3: サブシステム名 | C3: 給与 | E3: 作成日 | I3: 2025-11-28
B4: スキーマ名 | E4: RDBMS | I4: MySQL
B5: 論理テーブル名 | C5: 割当情報 | E5: ENGINE | I5: InnoDB
B6: 物理テーブル名 | C6: allocation_info | E6: CHARSET | I6: utf8mb4
B7: 備考
A12: カラム情報 | L12: 外部キー情報
A13: No | B13: 論理名 | C13: 物理名 | D13: データ型 | E13: Size | F13: Not Null | G13: PK | H13: UK | I13: デフォルト | J13: 備考 | L13: 親テーブル | M13: 参照カラム
A14: 1 | B14: 割当コード | C14: allocation_code | D14: varchar | E14: 20 | F14: not null | G14: 〇
A15: 2 | B15: 割当名称 | C15: allocation_name | D15: varchar | E15: 255 | F15: not null
A16: 3 | B16: 機能区分 | C16: program_type | D16: tinyint | F16: not null | J16: コードマスタ.SQS0062
A17: 4 | B17: 作成者 | C17: created_by | D17: bigint | F17: not null
A18: 5 | B18: 作成日時 | C18: created_at | D18: datetime | E18: 6 | F18: not null
A19: 6 | B19: 更新者 | C19: updated_by | D19: bigint | F19: not null
A20: 7 | B20: 更新日時 | C20: updated_at | D20: datetime | E20: 6 | F20: not null

Sheet 割当情報詳細
A1: テーブル情報
B2: システム名 | C2: SOCIA | E2: 作成者 | I2: ITSP | M2: テーブル一覧へ
B3: サブシステム名 | C3: 給与 | E3: 作成日 | I3: 2025-11-28
B4: スキーマ名 | E4: RDBMS | I4: MySQL
B5: 論理テーブル名 | C5: 割当情報詳細 | E5: ENGINE | I5: InnoDB
B6: 物理テーブル名 | C6: allocation_info_detail | E6: CHARSET | I6: utf8mb4
B7: 備考
A12: カラム情報 | L12: 外部キー情報
A13: No | B13: 論理名 | C13: 物理名 | D13: データ型 | E13: Size | F13: Not Null | G13: PK | H13: UK | I13: デフォルト | J13: 備考 | L13: 親テーブル | M13: 参照カラム
A14: 1 | B14: 割当コード | C14: allocation_code | D14: varchar | E14: 20 | F14: not null | G14: 〇
A15: 2 | B15: 体系コード | C15: taikei_code | D15: varchar | E15: 20 | F15: not null | G15: 〇
A16: 3 | B16: 取込元順番 | C16: import_source_seq | D16: int | F16: not null | G16: 〇
A17: 4 | B17: 取込元項目名 | C17: import_source_item_name | D17: varchar | E17: 255
A18: 5 | B18: 取込先項目コード | C18: import_destination_item_code | D18: varchar | E18: 20
A19: 6 | B19: 作成者 | C19: created_by | D19: bigint | F19: not null
A20: 7 | B20: 作成日時 | C20: created_at | D20: datetime | E20: 6 | F20: not null
A21: 8 | B21: 更新者 | C21: updated_by | D21: bigint | F21: not null
A22: 9 | B22: 更新日時 | C22: updated_at | D22: datetime | E22: 6 | F22: not null

Sheet 労災保険料率
A1: テーブル情報
B2: システム名 | C2: SOCIA | E2: 作成者 | I2: ITSP | M2: テーブル一覧へ
B3: サブシステム名 | C3: 給与 | E3: 作成日 | I3: 2025-11-28
B4: スキーマ名 | E4: RDBMS | I4: MySQL
B5: 論理テーブル名 | C5: 労災保険料率 | E5: ENGINE | I5: InnoDB
B6: 物理テーブル名 | C6: rosai_insurance_rate | E6: CHARSET | I6: utf8mb4
B7: 備考
A12: カラム情報 | L12: 外部キー情報
A13: No | B13: 論理名 | C13: 物理名 | D13: データ型 | E13: Size | F13: Not Null | G13: PK | H13: UK | I13: デフォルト | J13: 備考 | L13: 親テーブル | M13: 参照カラム
A14: 1 | B14: 会社コード | C14: kaisyacd | D14: varchar | E14: 20 | F14: not null | G14: 〇
A15: 2 | B15: 届出コード | C15: submission_code | D15: varchar | E15: 20 | F15: not null | G15: 〇
A16: 3 | B16: 職種 | C16: job_type | D16: varchar | E16: 20 | F16: not null | G16: 〇
A17: 4 | B17: 有効開始年月日 | C17: fromymd | D17: date | F17: not null | G17: 〇
A18: 5 | B18: 有効終了年月日 | C18: toymd | D18: date | F18: not null
A19: 6 | B19: 職種名称 | C19: job_type_name | D19: varchar | E19: 255
A20: 7 | B20: 労災保険料率 | C20: rosai_insurance_rate | D20: decimal | E20: 6,3
A21: 8 | B21: 作成者 | C21: created_by | D21: bigint | F21: not null
A22: 9 | B22: 作成日時 | C22: created_at | D22: datetime | E22: 6 | F22: not null
A23: 10 | B23: 更新者 | C23: updated_by | D23: bigint | F23: not null
A24: 11 | B24: 更新日時 | C24: updated_at | D24: datetime | E24: 6 | F24: not null

Sheet 厚生年金基金会社情報
A1: テーブル情報
B2: システム名 | C2: SOCIA | E2: 作成者 | I2: ITSP | M2: テーブル一覧へ
B3: サブシステム名 | C3: 給与 | E3: 作成日 | I3: 2025-11-28
B4: スキーマ名 | E4: RDBMS | I4: MySQL
B5: 論理テーブル名 | C5: 厚生年金基金会社情報 | E5: ENGINE | I5: InnoDB
B6: 物理テーブル名 | C6: kosei_pension_fund_kaisya_info | E6: CHARSET | I6: utf8mb4
B7: 備考
A12: カラム情報 | L12: 外部キー情報
A13: No | B13: 論理名 | C13: 物理名 | D13: データ型 | E13: Size | F13: Not Null | G13: PK | H13: UK | I13: デフォルト | J13: 備考 | L13: 親テーブル | M13: 参照カラム
A14: 1 | B14: 会社コード | C14: kaisyacd | D14: varchar | E14: 20 | F14: not null | G14: 〇
A15: 2 | B15: 届出コード | C15: submission_code | D15: varchar | E15: 20 | F15: not null | G15: 〇
A16: 3 | B16: 有効開始年月日 | C16: fromymd | D16: date | F16: not null | G16: 〇
A17: 4 | B17: 有効終了年月日 | C17: toymd | D17: date | F17: not null
A18: 5 | B18: 被保険者(一般) | C18: insured_person_general | D18: decimal | E18: 6,3 | F18: not null
A19: 6 | B19: 被保険者(坑内夫) | C19: insured_person_mineworker | D19: decimal | E19: 6,3 | F19: not null
A20: 7 | B20: 事業主(一般) | C20: business_owner_general | D20: decimal | E20: 6,3 | F20: not null
A21: 8 | B21: 事業主(坑内夫) | C21: business_owner_mineworker | D21: decimal | E21: 6,3 | F21: not null
A22: 9 | B22: 被保険者端数区分 | C22: insured_person_fraction_type | D22: tinyint | F22: not null
A23: 10 | B23: 事業主端数区分 | C23: business_owner_fraction_type | D23: tinyint | F23: not null
A24: 11 | B24: 特別基金65歳以上被保険者(一般) | C24: special_fund_insured_person_65_general | D24: decimal | E24: 6,3 | F24: not null
A25: 12 | B25: 特別基金65歳以上被保険者(坑内夫) | C25: special_fund_insured_person_65_mineworker | D25: decimal | E25: 6,3 | F25: not null
A26: 13 | B26: 特別基金65歳以上事業主(一般) | C26: special_fund_business_owner_65_general | D26: decimal | E26: 6,3 | F26: not null
A27: 14 | B27: 特別基金65歳以上事業主(坑内夫) | C27: special_fund_business_owner_65_mineworker | D27: decimal | E27: 6,3
A28: 15 | B28: 作成者 | C28: created_by | D28: bigint | F28: not null
A29: 16 | B29: 作成日時 | C29: created_at | D29: datetime | E29: 6 | F29: not null
A30: 17 | B30: 更新者 | C30: updated_by | D30: bigint | F30: not null
A31: 18 | B31: 更新日時 | C31: updated_at | D31: datetime | E31: 6 | F31: not null

Sheet 厚生年金料額
A1: テーブル情報
B2: システム名 | C2: SOCIA | E2: 作成者 | I2: ITSP | M2: テーブル一覧へ
B3: サブシステム名 | C3: 給与 | E3: 作成日 | I3: 2025-11-28
B4: スキーマ名 | E4: RDBMS | I4: MySQL
B5: 論理テーブル名 | C5: 厚生年金料額 | E5: ENGINE | I5: InnoDB
B6: 物理テーブル名 | C6: kosei_pension_amount | E6: CHARSET | I6: utf8mb4
B7: 備考
A12: カラム情報 | L12: 外部キー情報
A13: No | B13: 論理名 | C13: 物理名 | D13: データ型 | E13: Size | F13: Not Null | G13: PK | H13: UK | I13: デフォルト | J13: 備考 | L13: 親テーブル | M13: 参照カラム
A14: 1 | B14: 会社コード | C14: kaisyacd | D14: varchar | E14: 20 | F14: not null | G14: 〇
A15: 2 | B15: 届出コード | C15: submission_code | D15: varchar | E15: 20 | F15: not null | G15: 〇
A16: 3 | B16: 等級 | C16: grade | D16: smallint | F16: not null | G16: 〇
A17: 4 | B17: 有効開始年月日 | C17: fromymd | D17: date | F17: not null | G17: 〇
A18: 5 | B18: 有効終了年月日 | C18: toymd | D18: date | F18: not null
A19: 6 | B19: 標準報酬月額 | C19: standard_reward_month_amount | D19: bigint | F19: not null
A20: 7 | B20: 報酬月額 | C20: reward_monthly | D20: bigint
A21: 8 | B21: 被保険者 | C21: insured_person | D21: int | F21: not null
A22: 9 | B22: 事業主 | C22: business_owner | D22: int | F22: not null
A23: 10 | B23: 基金被保険者 | C23: insured_person_fund | D23: int | F23: not null
A24: 11 | B24: 基金事業主 | C24: business_owner_fund | D24: int | F24: not null
A25: 12 | B25: 児童手当拠出金 | C25: child_charge_contribution | D25: bigint | F25: not null
A26: 13 | B26: 65歳以上基金被保険者 | C26: insured_person_fund_over_65 | D26: int | F26: not null
A27: 14 | B27: 65歳以上基金事業主 | C27: business_owner_fund_over_65 | D27: int | F27: not null
A28: 15 | B28: 作成者 | C28: created_by | D28: bigint | F28: not null
A29: 16 | B29: 作成日時 | C29: created_at | D29: datetime | E29: 6 | F29: not null
A30: 17 | B30: 更新者 | C30: updated_by | D30: bigint | F30: not null
A31: 18 | B31: 更新日時 | C31: updated_at | D31: datetime | E31: 6 | F31: not null

Sheet 合計項目
A1: テーブル情報
B2: システム名 | C2: SOCIA | E2: 作成者 | I2: ITSP | M2: テーブル一覧へ
B3: サブシステム名 | C3: 給与 | E3: 作成日 | I3: 2025-11-28
B4: スキーマ名 | E4: RDBMS | I4: MySQL
B5: 論理テーブル名 | C5: 合計項目 | E5: ENGINE | I5: InnoDB
B6: 物理テーブル名 | C6: total_item | E6: CHARSET | I6: utf8mb4
B7: 備考
A12: カラム情報 | L12: 外部キー情報
A13: No | B13: 論理名 | C13: 物理名 | D13: データ型 | E13: Size | F13: Not Null | G13: PK | H13: UK | I13: デフォルト | J13: 備考 | L13: 親テーブル | M13: 参照カラム
A14: 1 | B14: 会社コード | C14: kaisyacd | D14: varchar | E14: 20 | F14: not null | G14: 〇
A15: 2 | B15: 体系項目コード | C15: taikei_item_code | D15: varchar | E15: 20 | F15: not null | G15: 〇
A16: 3 | B16: 支給控除区分 | C16: payment_deduction_type | D16: tinyint | J16: コードマスタ.SQS0049
A17: 4 | B17: 設定区分 | C17: settype | D17: tinyint | J17: コードマスタ.SQS0076
A18: 5 | B18: 項目区分 | C18: item_category | D18: tinyint | J18: コードマスタ.SQS0027
A19: 6 | B19: 項目名称 | C19: item_name | D19: varchar | E19: 255
A20: 7 | B20: 項目略称 | C20: item_shortname | D20: varchar | E20: 255
A21: 8 | B21: 表示区分 | C21: dsp_type | D21: tinyint | J21: コードマスタ.SQS0077
A22: 9 | B22: 項目型区分 | C22: data_type | D22: smallint | F22: not null | J22: コードマスタ.SRS0003
A23: 10 | B23: 選択項目ID | C23: code_itemid | D23: bigint
A24: 11 | B24: 入力必須フラグ | C24: required | D24: boolean | F24: not null
A25: 12 | B25: 項目型設定格納値JSON | C25: data_type_store_json | D25: json | F25: not null
A26: 13 | B26: 非表示フラグ | C26: hidden | D26: boolean | F26: not null
A27: 14 | B27: 備考 | C27: note | D27: text
A28: 15 | B28: 並び順 | C28: sort_order | D28: bigint
A29: 16 | B29: 作成者 | C29: created_by | D29: bigint | F29: not null
A30: 17 | B30: 作成日時 | C30: created_at | D30: datetime | E30: 6 | F30: not null
A31: 18 | B31: 更新者 | C31: updated_by | D31: bigint | F31: not null
A32: 19 | B32: 更新日時 | C32: updated_at | D32: datetime | E32: 6 | F32: not null

Sheet 地方自治体
A1: テーブル情報
B2: システム名 | C2: SOCIA | E2: 作成者 | I2: ITSP | M2: テーブル一覧へ
B3: サブシステム名 | C3: 給与 | E3: 作成日 | I3: 2025-11-28
B4: スキーマ名 | E4: RDBMS | I4: MySQL
B5: 論理テーブル名 | C5: 地方自治体 | E5: ENGINE | I5: InnoDB
B6: 物理テーブル名 | C6: local_municipality | E6: CHARSET | I6: utf8mb4
B7: 備考
B8: 現行のQTCUJITI
A12: カラム情報 | L12: 外部キー情報
A13: No | B13: 論理名 | C13: 物理名 | D13: データ型 | E13: Size | F13: Not Null | G13: PK | H13: UK | I13: デフォルト | J13: 備考 | L13: 親テーブル | M13: 参照カラム
A14: 1 | B14: 市区町村コード | C14: municipalities_code | D14: varchar | E14: 20 | F14: not null | G14: 〇
A15: 2 | B15: 有効開始年月日 | C15: fromymd | D15: date | F15: not null | G15: 〇
A16: 3 | B16: 有効終了年月日 | C16: toymd | D16: date | F16: not null
A17: 4 | B17: 市区町村名称 | C17: municipalities_name | D17: varchar | E17: 255
A18: 5 | B18: 市区町村名称カナ | C18: municipalities_name_kana | D18: varchar | E18: 255
A19: 6 | B19: 口座番号 | C19: account_number | D19: bigint
A20: 7 | B20: 加入者名称 | C20: subscriber_name | D20: varchar | E20: 16
A21: 8 | B21: 郵便番号 | C21: postal_code | D21: varchar | E21: 10
A22: 9 | B22: 住所 | C22: address | D22: varchar | E22: 100
A23: 10 | B23: 役場名 | C23: public_office_name | D23: varchar | E23: 50
A24: 11 | B24: 電話番号 | C24: tel | D24: varchar | E24: 20
A25: 12 | B25: 作成者 | C25: created_by | D25: bigint | F25: not null
A26: 13 | B26: 作成日時 | C26: created_at | D26: datetime | E26: 6 | F26: not null
A27: 14 | B27: 更新者 | C27: updated_by | D27: bigint | F27: not null
A28: 15 | B28: 更新日時 | C28: updated_at | D28: datetime | E28: 6 | F28: not null

Sheet 基礎控除額
A1: テーブル情報
B2: システム名 | C2: SOCIA | E2: 作成者 | I2: ITSP | M2: テーブル一覧へ
B3: サブシステム名 | C3: 給与 | E3: 作成日 | I3: 2025-11-28
B4: スキーマ名 | E4: RDBMS | I4: MySQL
B5: 論理テーブル名 | C5: 基礎控除額 | E5: ENGINE | I5: InnoDB
B6: 物理テーブル名 | C6: basic_deduction_amount | E6: CHARSET | I6: utf8mb4
B7: 備考
A12: カラム情報 | L12: 外部キー情報
A13: No | B13: 論理名 | C13: 物理名 | D13: データ型 | E13: Size | F13: Not Null | G13: PK | H13: UK | I13: デフォルト | J13: 備考 | L13: 親テーブル | M13: 参照カラム
A14: 1 | B14: 等級 | C14: grade | D14: smallint | F14: not null | G14: 〇
A15: 2 | B15: 給与額 | C15: kyuyo_amount | D15: bigint | F15: not null | G15: 〇
A16: 3 | B16: 有効開始年月日 | C16: fromymd | D16: date | F16: not null | G16: 〇
A17: 4 | B17: 有効終了年月日 | C17: toymd | D17: date | F17: not null
A18: 5 | B18: 控除率 | C18: deduction_rate | D18: decimal | E18: 6,2
A19: 6 | B19: 控除額 | C19: deduction_amount | D19: bigint
A20: 7 | B20: 作成者 | C20: created_by | D20: bigint | F20: not null
A21: 8 | B21: 作成日時 | C21: created_at | D21: datetime | E21: 6 | F21: not null
A22: 9 | B22: 更新者 | C22: updated_by | D22: bigint | F22: not null
A23: 10 | B23: 更新日時 | C23: updated_at | D23: datetime | E23: 6 | F23: not null

Sheet 外部変動項目情報
A1: テーブル情報
B2: システム名 | C2: SOCIA | E2: 作成者 | I2: ITSP | M2: テーブル一覧へ
B3: サブシステム名 | C3: 給与 | E3: 作成日 | I3: 2025-11-28
B4: スキーマ名 | E4: RDBMS | I4: MySQL
B5: 論理テーブル名 | C5: 外部変動項目情報 | E5: ENGINE | I5: InnoDB
B6: 物理テーブル名 | C6: external_variable_item_info | E6: CHARSET | I6: utf8mb4
B7: 備考
A12: カラム情報 | L12: 外部キー情報
A13: No | B13: 論理名 | C13: 物理名 | D13: データ型 | E13: Size | F13: Not Null | G13: PK | H13: UK | I13: デフォルト | J13: 備考 | L13: 親テーブル | M13: 参照カラム
A14: 1 | B14: 社員連番 | C14: syainseq | D14: bigint | F14: not null | G14: 〇
A15: 2 | B15: 支給区分 | C15: payment_type | D15: tinyint | F15: not null | G15: 〇 | J15: コードマスタ.SQS0013
A16: 3 | B16: 年度 | C16: year | D16: smallint | F16: not null | G16: 〇
A17: 4 | B17: 月度 | C17: month | D17: smallint | F17: not null | G17: 〇
A18: 5 | B18: 締日 | C18: shime_day | D18: tinyint | F18: not null | G18: 〇
A19: 6 | B19: 支給月区分 | C19: payment_month_type | D19: tinyint | F19: not null | G19: 〇 | J19: コードマスタ.SQS0012
A20: 7 | B20: 支給日 | C20: payment_day | D20: tinyint | F20: not null | G20: 〇
A21: 8 | B21: 体系コード | C21: taikei_code | D21: varchar | E21: 20 | F21: not null | G21: 〇
A22: 9 | B22: 体系項目コード | C22: taikei_item_code | D22: varchar | E22: 20 | F22: not null | G22: 〇
A23: 10 | B23: 設定値 | C23: setvalue | D23: varchar | E23: 255 | F23: not null
A24: 11 | B24: 支給年月日 | C24: payment_date | D24: date | F24: not null
A25: 12 | B25: 締年月日 | C25: shime_date | D25: date | F25: not null
A26: 13 | B26: 作成者 | C26: created_by | D26: bigint | F26: not null
A27: 14 | B27: 作成日時 | C27: created_at | D27: datetime | E27: 6 | F27: not null
A28: 15 | B28: 更新者 | C28: updated_by | D28: bigint | F28: not null
A29: 16 | B29: 更新日時 | C29: updated_at | D29: datetime | E29: 6 | F29: not null

Sheet 定数項目
A1: テーブル情報
B2: システム名 | C2: SOCIA | E2: 作成者 | I2: ITSP | M2: テーブル一覧へ
B3: サブシステム名 | C3: 給与 | E3: 作成日 | I3: 2025-11-28
B4: スキーマ名 | E4: RDBMS | I4: MySQL
B5: 論理テーブル名 | C5: 定数項目 | E5: ENGINE | I5: InnoDB
B6: 物理テーブル名 | C6: const_item | E6: CHARSET | I6: utf8mb4
B7: 備考
A12: カラム情報 | L12: 外部キー情報
A13: No | B13: 論理名 | C13: 物理名 | D13: データ型 | E13: Size | F13: Not Null | G13: PK | H13: UK | I13: デフォルト | J13: 備考 | L13: 親テーブル | M13: 参照カラム
A14: 1 | B14: 定数項目コード | C14: const_item_code | D14: varchar | E14: 20 | F14: not null | G14: 〇
A15: 2 | B15: 有効開始年月日 | C15: fromymd | D15: date | F15: not null | G15: 〇
A16: 3 | B16: 有効終了年月日 | C16: toymd | D16: date | F16: not null
A17: 4 | B17: 項目名称 | C17: item_name | D17: varchar | E17: 255
A18: 5 | B18: 項目略称 | C18: item_shortname | D18: varchar | E18: 255
A19: 6 | B19: 項目型区分 | C19: data_type | D19: smallint | F19: not null | J19: コードマスタ.SRS0003
A20: 7 | B20: 選択項目ID | C20: code_itemid | D20: bigint
A21: 8 | B21: 入力必須フラグ | C21: required | D21: boolean
A22: 9 | B22: 項目型設定格納値JSON | C22: data_type_store_json | D22: json | F22: not null
A23: 10 | B23: 非表示フラグ | C23: hidden | D23: boolean | F23: not null | J23: 表示・非表示
A24: 11 | B24: 備考 | C24: note | D24: text
A25: 12 | B25: 作成者 | C25: created_by | D25: bigint | F25: not null
A26: 13 | B26: 作成日時 | C26: created_at | D26: datetime | E26: 6 | F26: not null
A27: 14 | B27: 更新者 | C27: updated_by | D27: bigint | F27: not null
A28: 15 | B28: 更新日時 | C28: updated_at | D28: datetime | E28: 6 | F28: not null

Sheet 届出基本
A1: テーブル情報
B2: システム名 | C2: SOCIA | E2: 作成者 | I2: ITSP | M2: テーブル一覧へ
B3: サブシステム名 | C3: 給与 | E3: 作成日 | I3: 2025-11-28
B4: スキーマ名 | E4: RDBMS | I4: MySQL
B5: 論理テーブル名 | C5: 届出基本 | E5: ENGINE | I5: InnoDB
B6: 物理テーブル名 | C6: submission_basic | E6: CHARSET | I6: utf8mb4
B7: 備考
A12: カラム情報 | L12: 外部キー情報
A13: No | B13: 論理名 | C13: 物理名 | D13: データ型 | E13: Size | F13: Not Null | G13: PK | H13: UK | I13: デフォルト | J13: 備考 | L13: 親テーブル | M13: 参照カラム
A14: 1 | B14: 会社コード | C14: kaisyacd | D14: varchar | E14: 20 | F14: not null | G14: 〇
A15: 2 | B15: 届出コード | C15: submission_code | D15: varchar | E15: 20 | F15: not null | G15: 〇
A16: 3 | B16: 有効開始年月日 | C16: fromymd | D16: date | F16: not null | G16: 〇
A17: 4 | B17: 有効終了年月日 | C17: toymd | D17: date | F17: not null
A18: 5 | B18: 届出名称 | C18: submission_name | D18: varchar | E18: 255 | F18: not null
A19: 6 | B19: 電話番号 | C19: tel | D19: varchar | E19: 20 | F19: not null
A20: 7 | B20: 住所 | C20: address | D20: varchar | E20: 100 | F20: not null
A21: 8 | B21: 代表職名称 | C21: representative_job_name | D21: varchar | E21: 255
A22: 9 | B22: 代表者氏名 | C22: representative_name | D22: varchar | E22: 255
A23: 10 | B23: 郵便番号 | C23: postal_code | D23: varchar | E23: 10
A24: 11 | B24: 会社海外区分 | C24: kaisya_oversea_type | D24: tinyint | F24: not null
A25: 12 | B25: 出力区分 | C25: output_type | D25: smallint
A26: 13 | B26: 所轄税務署 | C26: belong_tax_office | D26: varchar | E26: 10
A27: 14 | B27: 署番号 | C27: station_number | D27: bigint
A28: 15 | B28: 整理番号 | C28: arrangement_number | D28: bigint
A29: 16 | B29: 作成者 | C29: created_by | D29: bigint | F29: not null
A30: 17 | B30: 作成日時 | C30: created_at | D30: datetime | E30: 6 | F30: not null
A31: 18 | B31: 更新者 | C31: updated_by | D31: bigint | F31: not null
A32: 19 | B32: 更新日時 | C32: updated_at | D32: datetime | E32: 6 | F32: not null

Sheet 帳票用パターン
A1: テーブル情報
B2: システム名 | C2: SOCIA | E2: 作成者 | I2: ITSP | M2: テーブル一覧へ
B3: サブシステム名 | C3: 給与 | E3: 作成日 | I3: 2025-11-28
B4: スキーマ名 | E4: RDBMS | I4: MySQL
B5: 論理テーブル名 | C5: 帳票用パターン | E5: ENGINE | I5: InnoDB
B6: 物理テーブル名 | C6: report_pattern | E6: CHARSET | I6: utf8mb4
B7: 備考
A12: カラム情報 | L12: 外部キー情報
A13: No | B13: 論理名 | C13: 物理名 | D13: データ型 | E13: Size | F13: Not Null | G13: PK | H13: UK | I13: デフォルト | J13: 備考 | L13: 親テーブル | M13: 参照カラム
A14: 1 | B14: 会社コード | C14: kaisyacd | D14: varchar | E14: 20 | F14: not null | G14: 〇
A15: 2 | B15: 帳票パターンコード | C15: report_pattern_code | D15: varchar | E15: 20 | F15: not null | G15: 〇
A16: 3 | B16: 帳票パターン名称 | C16: report_pattern_name | D16: varchar | E16: 255 | F16: not null
A17: 4 | B17: タイトル | C17: title | D17: varchar | E17: 50
A18: 5 | B18: 設定情報JSON | C18: set_info_json | D18: json | J18: 管理集計表：_x000D_ 2段出力：True/False_x000D_ 集計項目のブロック_x000D_ 集計範囲のブロック
A19: 6 | B19: パターン区分 | C19: pattern_type | D19: tinyint | F19: not null | J19: 1:賃金台帳、2:管理集計表
A20: 7 | B20: 並び順 | C20: sort_order | D20: bigint | F20: not null
A21: 8 | B21: 作成者 | C21: created_by | D21: bigint | F21: not null
A22: 9 | B22: 作成日時 | C22: created_at | D22: datetime | E22: 6 | F22: not null
A23: 10 | B23: 更新者 | C23: updated_by | D23: bigint | F23: not null
A24: 11 | B24: 更新日時 | C24: updated_at | D24: datetime | E24: 6 | F24: not null

Sheet 帳票用パターン項目
A1: テーブル情報
B2: システム名 | C2: SOCIA | E2: 作成者 | I2: ITSP | M2: テーブル一覧へ
B3: サブシステム名 | C3: 給与 | E3: 作成日 | I3: 2025-11-28
B4: スキーマ名 | E4: RDBMS | I4: MySQL
B5: 論理テーブル名 | C5: 帳票用パターン項目 | E5: ENGINE | I5: InnoDB
B6: 物理テーブル名 | C6: report_pattern_item | E6: CHARSET | I6: utf8mb4
B7: 備考
A12: カラム情報 | L12: 外部キー情報
A13: No | B13: 論理名 | C13: 物理名 | D13: データ型 | E13: Size | F13: Not Null | G13: PK | H13: UK | I13: デフォルト | J13: 備考 | L13: 親テーブル | M13: 参照カラム
A14: 1 | B14: 会社コード | C14: kaisyacd | D14: varchar | E14: 20 | F14: not null | G14: 〇
A15: 2 | B15: 帳票パターンコード | C15: report_pattern_code | D15: varchar | E15: 20 | F15: not null | G15: 〇
A16: 3 | B16: データ連番 | C16: dataseq | D16: int | F16: not null | G16: 〇
A17: 4 | B17: 帳票項目JSON | C17: report_item_json | D17: json | F17: not null | J17: 帳票項目の配列。合計の場合複数
A18: 5 | B18: 帳票項目名称 | C18: report_item_name | D18: varchar | E18: 255 | F18: not null
A19: 6 | B19: 計算区分 | C19: equation_type | D19: tinyint | J19: コードマスタ.SQS0057
A20: 7 | B20: 配置コード | C20: arrangement_code | D20: varchar | E20: 20 | J20: コードマスタ.SQS0058
A21: 8 | B21: 作成者 | C21: created_by | D21: bigint | F21: not null
A22: 9 | B22: 作成日時 | C22: created_at | D22: datetime | E22: 6 | F22: not null
A23: 10 | B23: 更新者 | C23: updated_by | D23: bigint | F23: not null
A24: 11 | B24: 更新日時 | C24: updated_at | D24: datetime | E24: 6 | F24: not null

Sheet 帳票用項目
A1: テーブル情報
B2: システム名 | C2: SOCIA | E2: 作成者 | I2: ITSP | M2: テーブル一覧へ
B3: サブシステム名 | C3: 給与 | E3: 作成日 | I3: 2025-11-28
B4: スキーマ名 | E4: RDBMS | I4: MySQL
B5: 論理テーブル名 | C5: 帳票用項目 | E5: ENGINE | I5: InnoDB
B6: 物理テーブル名 | C6: report_item | E6: CHARSET | I6: utf8mb4
B7: 備考
A12: カラム情報 | L12: 外部キー情報
A13: No | B13: 論理名 | C13: 物理名 | D13: データ型 | E13: Size | F13: Not Null | G13: PK | H13: UK | I13: デフォルト | J13: 備考 | L13: 親テーブル | M13: 参照カラム
A14: 1 | B14: 会社コード | C14: kaisyacd | D14: varchar | E14: 20 | F14: not null | G14: 〇
A15: 2 | B15: 帳票項目コード | C15: report_item_code | D15: varchar | E15: 20 | F15: not null | G15: 〇
A16: 3 | B16: 有効開始年月日 | C16: fromymd | D16: date | F16: not null | G16: 〇
A17: 4 | B17: 有効終了年月日 | C17: toymd | D17: date | F17: not null
A18: 5 | B18: 帳票項目名称 | C18: report_item_name | D18: varchar | E18: 255 | F18: not null
A19: 6 | B19: 支給区分 | C19: payment_type | D19: tinyint | F19: not null | J19: コードマスタ.SQS0013
A20: 7 | B20: 支給控除区分 | C20: payment_deduction_type | D20: tinyint | F20: not null | J20: コードマスタ.SQS0049
A21: 8 | B21: 項目型区分 | C21: data_type | D21: smallint | F21: not null | J21: コードマスタ.SRS0003
A22: 9 | B22: 選択項目ID | C22: code_itemid | D22: bigint
A23: 10 | B23: 入力必須フラグ | C23: required | D23: boolean | F23: not null
A24: 11 | B24: 項目型設定格納値JSON | C24: data_type_store_json | D24: json | F24: not null
A25: 12 | B25: ゼロ表示 | C25: zero_dsp | D25: tinyint
A26: 13 | B26: 非表示フラグ | C26: hidden | D26: boolean | F26: not null
A27: 14 | B27: 備考 | C27: note | D27: text
A28: 15 | B28: 並び順 | C28: sort_order | D28: bigint | F28: not null
A29: 16 | B29: 作成者 | C29: created_by | D29: bigint | F29: not null
A30: 17 | B30: 作成日時 | C30: created_at | D30: datetime | E30: 6 | F30: not null
A31: 18 | B31: 更新者 | C31: updated_by | D31: bigint | F31: not null
A32: 19 | B32: 更新日時 | C32: updated_at | D32: datetime | E32: 6 | F32: not null

Sheet 帳票用項目詳細
A1: テーブル情報
B2: システム名 | C2: SOCIA | E2: 作成者 | I2: ITSP | M2: テーブル一覧へ
B3: サブシステム名 | C3: 給与 | E3: 作成日 | I3: 2025-11-28
B4: スキーマ名 | E4: RDBMS | I4: MySQL
B5: 論理テーブル名 | C5: 帳票用項目詳細 | E5: ENGINE | I5: InnoDB
B6: 物理テーブル名 | C6: report_item_detail | E6: CHARSET | I6: utf8mb4
B7: 備考
A12: カラム情報 | L12: 外部キー情報
A13: No | B13: 論理名 | C13: 物理名 | D13: データ型 | E13: Size | F13: Not Null | G13: PK | H13: UK | I13: デフォルト | J13: 備考 | L13: 親テーブル | M13: 参照カラム
A14: 1 | B14: 会社コード | C14: kaisyacd | D14: varchar | E14: 20 | F14: not null | G14: 〇
A15: 2 | B15: 帳票項目コード | C15: report_item_code | D15: varchar | E15: 20 | F15: not null | G15: 〇
A16: 3 | B16: 体系コード | C16: taikei_code | D16: varchar | E16: 20 | F16: not null | G16: 〇
A17: 4 | B17: 体系項目コード | C17: taikei_item_code | D17: varchar | E17: 20 | F17: not null | G17: 〇
A18: 5 | B18: 有効開始年月日 | C18: fromymd | D18: date | F18: not null | G18: 〇
A19: 6 | B19: 有効終了年月日 | C19: toymd | D19: date | F19: not null
A20: 7 | B20: 作成者 | C20: created_by | D20: bigint | F20: not null
A21: 8 | B21: 作成日時 | C21: created_at | D21: datetime | E21: 6 | F21: not null
A22: 9 | B22: 更新者 | C22: updated_by | D22: bigint | F22: not null
A23: 10 | B23: 更新日時 | C23: updated_at | D23: datetime | E23: 6 | F23: not null

Sheet 年末調整
A1: テーブル情報
B2: システム名 | C2: SOCIA | E2: 作成者 | I2: ITSP | M2: テーブル一覧へ
B3: サブシステム名 | C3: 給与 | E3: 作成日 | I3: 2025-11-28
B4: スキーマ名 | E4: RDBMS | I4: MySQL
B5: 論理テーブル名 | C5: 年末調整 | E5: ENGINE | I5: InnoDB
B6: 物理テーブル名 | C6: nencho | E6: CHARSET | I6: utf8mb4
B7: 備考
A12: カラム情報 | L12: 外部キー情報
A13: No | B13: 論理名 | C13: 物理名 | D13: データ型 | E13: Size | F13: Not Null | G13: PK | H13: UK | I13: デフォルト | J13: 備考 | L13: 親テーブル | M13: 参照カラム
A14: 1 | B14: 社員連番 | C14: syainseq | D14: bigint | F14: not null | G14: 〇
A15: 2 | B15: 年度 | C15: year | D15: smallint | F15: not null | G15: 〇
A16: 3 | B16: 届出コード | C16: submission_code | D16: varchar | E16: 20 | F16: not null | G16: 〇
A17: 4 | B17: 課税区分 | C17: tax_type | D17: tinyint | F17: not null | G17: 〇 | J17: コードマスタ.SQS0002
A18: 5 | B18: 届出連番 | C18: submissionseq | D18: int | F18: not null | J18: 1から。No.1が年度末時点
A19: 6 | B19: データ連番 | C19: dataseq | D19: int | F19: not null | J19: 1から。No.1が年度末時点
A20: 7 | B20: 支払金額 | C20: payment_amount | D20: bigint | F20: not null
A21: 8 | B21: 所得税額 | C21: income_tax_amount | D21: bigint | F21: not null
A22: 9 | B22: 社会保険料(給与控除分) | C22: syaho_fee_kyuyo_deduction | D22: bigint | F22: not null
A23: 10 | B23: 小規模企業掛金 | C23: small_enterprise_contribution | D23: bigint | F23: not null
A24: 11 | B24: 住民税徴収区分 | C24: resident_tax_collection_type | D24: tinyint | F24: not null | J24: コードマスタ.SQS0022
A25: 12 | B25: 普通徴収理由コード | C25: regular_collection_reason_code | D25: varchar | E25: 20 | J25: コードマスタ.SQS0009
A26: 13 | B26: 年末調整区分 | C26: nencho_type | D26: tinyint | F26: not null | J26: コードマスタ.SQS0005
A27: 14 | B27: 災害者区分 | C27: disaster_type | D27: tinyint | J27: コードマスタ.SQS0038
A28: 15 | B28: 居住者区分 | C28: resident_type | D28: tinyint | J28: コードマスタ.SQS0033
A29: 16 | B29: 年末調整限度区分 | C29: nencho_limit_type | D29: tinyint
A30: 17 | B30: 退職区分 | C30: retirement_type | D30: tinyint | J30: コードマスタ.SQS0048
A31: 18 | B31: 作成者 | C31: created_by | D31: bigint | F31: not null
A32: 19 | B32: 作成日時 | C32: created_at | D32: datetime | E32: 6 | F32: not null
A33: 20 | B33: 更新者 | C33: updated_by | D33: bigint | F33: not null
A34: 21 | B34: 更新日時 | C34: updated_at | D34: datetime | E34: 6 | F34: not null

Sheet 年末調整_控除
A1: テーブル情報
B2: システム名 | C2: SOCIA | E2: 作成者 | I2: ITSP | M2: テーブル一覧へ
B3: サブシステム名 | C3: 給与 | E3: 作成日 | I3: 2025-11-28
B4: スキーマ名 | E4: RDBMS | I4: MySQL
B5: 論理テーブル名 | C5: 年末調整_控除 | E5: ENGINE | I5: InnoDB
B6: 物理テーブル名 | C6: nencho_deduction | E6: CHARSET | I6: utf8mb4
B7: 備考
A12: カラム情報 | L12: 外部キー情報
A13: No | B13: 論理名 | C13: 物理名 | D13: データ型 | E13: Size | F13: Not Null | G13: PK | H13: UK | I13: デフォルト | J13: 備考 | L13: 親テーブル | M13: 参照カラム
A14: 1 | B14: 社員連番 | C14: syainseq | D14: bigint | F14: not null | G14: 〇
A15: 2 | B15: 年度 | C15: year | D15: smallint | F15: not null | G15: 〇
A16: 3 | B16: 確定区分 | C16: confirm_type | D16: tinyint | F16: not null | J16: コードマスタ.SQS0006
A17: 4 | B17: 計算結果フラグ | C17: equation_result_flag | D17: tinyint | F17: not null | J17: コードマスタ.SQS0010
A18: 5 | B18: 給与所得控除後金額 | C18: kyuyo_income_after_deduction_amount | D18: bigint | F18: not null
A19: 6 | B19: 社会保険料控除額 | C19: syaho_fee_deduction_amount | D19: bigint | F19: not null
A20: 7 | B20: 生命保険料控除額 | C20: life_insurance_deduction_amount | D20: bigint | F20: not null
A21: 8 | B21: 損害保険料控除額 | C21: casualty_insurance_deduction_amount | D21: bigint | F21: not null
A22: 9 | B22: 配偶者(特別)控除額 | C22: spouse_deduction_amount | D22: bigint | F22: not null
A23: 10 | B23: その他控除額 | C23: other_deduction_amount | D23: bigint | F23: not null
A24: 11 | B24: 所得控除額 | C24: income_deduction_amount | D24: bigint | F24: not null
A25: 12 | B25: 課税額 | C25: tax_amount | D25: bigint | F25: not null
A26: 13 | B26: 年税額 | C26: yearly_tax_amount | D26: bigint | F26: not null
A27: 14 | B27: 源泉徴収税額 | C27: withholding_tax_amount | D27: bigint | F27: not null
A28: 15 | B28: 過不足税額 | C28: discrepancy_tax_amount | D28: bigint | F28: not null
A29: 16 | B29: 前回過不足税額累計額 | C29: last_discrepancy_tax_sum_amount | D29: bigint | F29: not null
... A37: 24 | B37: 作成者 | C37: created_by | D37: bigint | F37: not null
A38: 25 | B38: 作成日時 | C38: created_at | D38: datetime | E38: 6 | F38: not null
A39: 26 | B39: 更新者 | C39: updated_by | D39: bigint | F39: not null
A40: 27 | B40: 更新日時 | C40: updated_at | D40: datetime | E40: 6 | F40: not null

Sheet 年末調整保険控除額
A1: テーブル情報
B2: システム名 | C2: SOCIA | E2: 作成者 | I2: ITSP | M2: テーブル一覧へ
B3: サブシステム名 | C3: 給与 | E3: 作成日 | I3: 2025-11-28
B4: スキーマ名 | E4: RDBMS | I4: MySQL
B5: 論理テーブル名 | C5: 年末調整保険控除額 | E5: ENGINE | I5: InnoDB
B6: 物理テーブル名 | C6: nencho_insurance_deduction | E6: CHARSET | I6: utf8mb4
B7: 備考
A12: カラム情報 | L12: 外部キー情報
A13: No | B13: 論理名 | C13: 物理名 | D13: データ型 | E13: Size | F13: Not Null | G13: PK | H13: UK | I13: デフォルト | J13: 備考 | L13: 親テーブル | M13: 参照カラム
A14: 1 | B14: 保険区分 | C14: insurance_type | D14: tinyint | F14: not null | G14: 〇 | J14: コードマスタ.SQS0052
A15: 2 | B15: 保険料額 | C15: insurance_amount | D15: bigint | F15: not null | G15: 〇
A16: 3 | B16: 有効開始年月日 | C16: fromymd | D16: date | F16: not null | G16: 〇
A17: 4 | B17: 有効終了年月日 | C17: toymd | D17: date | F17: not null
A18: 5 | B18: データ連番 | C18: dataseq | D18: int
A19: 6 | B19: 比率 | C19: rate | D19: decimal | E19: 8,4 | F19: not null
A20: 7 | B20: 控除額 | C20: deduction_amount | D20: bigint | F20: not null
A21: 8 | B21: 作成者 | C21: created_by | D21: bigint | F21: not null
A22: 9 | B22: 作成日時 | C22: created_at | D22: datetime | E22: 6 | F22: not null
A23: 10 | B23: 更新者 | C23: updated_by | D23: bigint | F23: not null
A24: 11 | B24: 更新日時 | C24: updated_at | D24: datetime | E24: 6 | F24: not null

Sheet 年末調整入力
A1: テーブル情報
B2: システム名 | C2: SOCIA | E2: 作成者 | I2: ITSP | M2: テーブル一覧へ
B3: サブシステム名 | C3: 給与 | E3: 作成日 | I3: 2025-11-28
B4: スキーマ名 | E4: RDBMS | I4: MySQL
B5: 論理テーブル名 | C5: 年末調整入力 | E5: ENGINE | I5: InnoDB
B6: 物理テーブル名 | C6: nencho_input | E6: CHARSET | I6: utf8mb4
B7: 備考
A12: カラム情報 | L12: 外部キー情報
A13: No | B13: 論理名 | C13: 物理名 | D13: データ型 | E13: Size | F13: Not Null | G13: PK | H13: UK | I13: デフォルト | J13: 備考 | L13: 親テーブル | M13: 参照カラム
A14: 1 | B14: 社員連番 | C14: syainseq | D14: bigint | F14: not null | G14: 〇
A15: 2 | B15: 年度 | C15: year | D15: smallint | F15: not null | G15: 〇
A16: 3 | B16: 年末調整区分 | C16: nencho_type | D16: tinyint | J16: コードマスタ.SQS0005
A17: 4 | B17: 海外赴任出国日 | C17: oversea_assign_departure_date | D17: date | F17: not null
A18: 5 | B18: 海外赴任住所 | C18: oversea_assign_address | D18: varchar | E18: 100 | F18: not null
A19: 6 | B19: 住民税徴収区分 | C19: resident_tax_collection_type | D19: tinyint | J19: コードマスタ.SQS0022
A20: 7 | B20: 普通徴収理由コード | C20: regular_collection_reason_code | D20: varchar | E20: 20 | J20: コードマスタ.SQS0009
A21: 8 | B21: 作成者 | C21: created_by | D21: bigint | F21: not null
A22: 9 | B22: 作成日時 | C22: created_at | D22: datetime | E22: 6 | F22: not null
A23: 10 | B23: 更新者 | C23: updated_by | D23: bigint | F23: not null
A24: 11 | B24: 更新日時 | C24: updated_at | D24: datetime | E24: 6 | F24: not null

Sheet 年末調整入力_住宅借入
A1: テーブル情報
B2: システム名 | C2: SOCIA | E2: 作成者 | I2: ITSP | M2: テーブル一覧へ
B3: サブシステム名 | C3: 給与 | E3: 作成日 | I3: 2025-11-28
B4: スキーマ名 | E4: RDBMS | I4: MySQL
B5: 論理テーブル名 | C5: 年末調整入力_住宅借入 | E5: ENGINE | I5: InnoDB
B6: 物理テーブル名 | C6: nencho_input_housing_loan | E6: CHARSET | I6: utf8mb4
B7: 備考
A12: カラム情報 | L12: 外部キー情報
A13: No | B13: 論理名 | C13: 物理名 | D13: データ型 | E13: Size | F13: Not Null | G13: PK | H13: UK | I13: デフォルト | J13: 備考 | L13: 親テーブル | M13: 参照カラム
A14: 1 | B14: 社員連番 | C14: syainseq | D14: bigint | F14: not null | G14: 〇
A15: 2 | B15: 年度 | C15: year | D15: smallint | F15: not null | G15: 〇
A16: 3 | B16: データ連番 | C16: dataseq | D16: int | F16: not null | G16: 〇
A17: 4 | B17: 居住開始年月日 | C17: residence_fromymd | D17: date
A18: 5 | B18: 住宅借入金等特別控除区分 | C18: housing_loan_special_deduction_type | D18: varchar | E18: 2 | F18: not null | J18: コードマスタ.SQS0023
A19: 6 | B19: 住宅借入金等特別控除額 | C19: housing_loan_special_deduction_amount | D19: bigint | F19: not null
A20: 7 | B20: 住宅借入金等年末残高 | C20: housing_loan_year_end_balance | D20: bigint | F20: not null
A21: 8 | B21: 作成者 | C21: created_by | D21: bigint | F21: not null
A22: 9 | B22: 作成日時 | C22: created_at | D22: datetime | E22: 6 | F22: not null
A23: 10 | B23: 更新者 | C23: updated_by | D23: bigint | F23: not null
A24: 11 | B24: 更新日時 | C24: updated_at | D24: datetime | E24: 6 | F24: not null

Sheet 年末調整入力_保険料
A1: テーブル情報
B2: システム名 | C2: SOCIA | E2: 作成者 | I2: ITSP | M2: テーブル一覧へ
B3: サブシステム名 | C3: 給与 | E3: 作成日 | I3: 2025-11-28
B4: スキーマ名 | E4: RDBMS | I4: MySQL
B5: 論理テーブル名 | C5: 年末調整入力_保険料 | E5: ENGINE | I5: InnoDB
B6: 物理テーブル名 | C6: nencho_input_insurance | E6: CHARSET | I6: utf8mb4
B7: 備考
A12: カラム情報 | L12: 外部キー情報
A13: No | B13: 論理名 | C13: 物理名 | D13: データ型 | E13: Size | F13: Not Null | G13: PK | H13: UK | I13: デフォルト | J13: 備考 | L13: 親テーブル | M13: 参照カラム
A14: 1 | B14: 社員連番 | C14: syainseq | D14: bigint | F14: not null | G14: 〇
A15: 2 | B15: 年度 | C15: year | D15: smallint | F15: not null | G15: 〇
A16: 3 | B16: 新一般生命保険料 | C16: new_general_life_insurance | D16: bigint | F16: not null
A17: 4 | B17: 旧一般生命保険料 | C17: old_general_life_insurance | D17: bigint | F17: not null
A18: 5 | B18: 介護医療保険料 | C18: medical_care_insurance | D18: bigint | F18: not null
A19: 6 | B19: 新個人年金保険料 | C19: new_personal_pension_insurance | D19: bigint | F19: not null
A20: 7 | B20: 旧個人年金保険料 | C20: old_personal_pension_insurance | D20: bigint | F20: not null
A21: 8 | B21: 地震保険料 | C21: earthquake_insurance | D21: bigint | F21: not null
A22: 9 | B22: 旧長期損害保険料 | C22: old_long_term_casualty_insurance | D22: bigint | F22: not null
A23: 10 | B23: 社会保険料（申告分） | C23: syaho_fee_declaration | D23: bigint | F23: not null
A24: 11 | B24: 国民年金保険料 | C24: national_pension_insurance | D24: bigint | F24: not null
A25: 12 | B25: 小規模企業掛金（申告分） | C25: small_enterprise_contribution_declaration | D25: bigint | F25: not null
A26: 13 | B26: 作成者 | C26: created_by | D26: bigint | F26: not null
A27: 14 | B27: 作成日時 | C27: created_at | D27: datetime | E27: 6 | F27: not null
A28: 15 | B28: 更新者 | C28: updated_by | D28: bigint | F28: not null
A29: 16 | B29: 更新日時 | C29: updated_at | D29: datetime | E29: 6 | F29: not null

Sheet 年末調整入力_基礎控除
A1: テーブル情報
B2: システム名 | C2: SOCIA | E2: 作成者 | I2: ITSP | M2: テーブル一覧へ
B3: サブシステム名 | C3: 給与 | E3: 作成日 | I3: 2025-11-28
B4: スキーマ名 | E4: RDBMS | I4: MySQL
B5: 論理テーブル名 | C5: 年末調整入力_基礎控除 | E5: ENGINE | I5: InnoDB
B6: 物理テーブル名 | C6: nencho_input_basic_deduction | E6: CHARSET | I6: utf8mb4
B7: 備考
A12: カラム情報 | L12: 外部キー情報
A13: No | B13: 論理名 | C13: 物理名 | D13: データ型 | E13: Size | F13: Not Null | G13: PK | H13: UK | I13: デフォルト | J13: 備考 | L13: 親テーブル | M13: 参照カラム
A14: 1 | B14: 社員連番 | C14: syainseq | D14: bigint | F14: not null | G14: 〇
A15: 2 | B15: 年度 | C15: year | D15: smallint | F15: not null | G15: 〇
A16: 3 | B16: 申告書提出区分 | C16: tax_return_filing_type | D16: tinyint | F16: not null | J16: コードマスタ.SQS0046
A17: 4 | B17: 従たる給与収入 | C17: sub_kyuyo_income | D17: bigint | F17: not null
A18: 5 | B18: 給与所得以外収入 | C18: kyuyo_income_other_income | D18: bigint | F18: not null
A19: 6 | B19: 作成者 | C19: created_by | D19: bigint | F19: not null
A20: 7 | B20: 作成日時 | C20: created_at | D20: datetime | E20: 6 | F20: not null
A21: 8 | B21: 更新者 | C21: updated_by | D21: bigint | F21: not null
A22: 9 | B22: 更新日時 | C22: updated_at | D22: datetime | E22: 6 | F22: not null

Sheet 年末調整入力_定額減税
A1: テーブル情報
B2: システム名 | C2: SOCIA | E2: 作成者 | I2: ITSP | M2: テーブル一覧へ
B3: サブシステム名 | C3: 給与 | E3: 作成日 | I3: 2025-11-28
B4: スキーマ名 | E4: RDBMS | I4: MySQL
B5: 論理テーブル名 | C5: 年末調整入力_定額減税 | E5: ENGINE | I5: InnoDB
B6: 物理テーブル名 | C6: nencho_input_flat_deduction | E6: CHARSET | I6: utf8mb4
B7: 備考
A12: カラム情報 | L12: 外部キー情報
A13: No | B13: 論理名 | C13: 物理名 | D13: データ型 | E13: Size | F13: Not Null | G13: PK | H13: UK | I13: デフォルト | J13: 備考 | L13: 親テーブル | M13: 参照カラム
A14: 1 | B14: 社員連番 | C14: syainseq | D14: bigint | F14: not null | G14: 〇
A15: 2 | B15: 年度 | C15: year | D15: smallint | F15: not null | G15: 〇
A16: 3 | B16: 定額減税額 | C16: flat_deduction_amount | D16: bigint
A17: 4 | B17: 控除外額 | C17: nondeduction_amount | D17: bigint
A18: 5 | B18: 備考1 | C18: note1 | D18: text
A19: 6 | B19: 備考2 | C19: note2 | D19: text
A20: 7 | B20: 作成者 | C20: created_by | D20: bigint | F20: not null
A21: 8 | B21: 作成日時 | C21: created_at | D21: datetime | E21: 6 | F21: not null
A22: 9 | B22: 更新者 | C22: updated_by | D22: bigint | F22: not null
A23: 10 | B23: 更新日時 | C23: updated_at | D23: datetime | E23: 6 | F23: not null

Sheet 年末調整入力_所得調整
A1: テーブル情報
B2: システム名 | C2: SOCIA | E2: 作成者 | I2: ITSP | M2: テーブル一覧へ
B3: サブシステム名 | C3: 給与 | E3: 作成日 | I3: 2025-11-28
B4: スキーマ名 | E4: RDBMS | I4: MySQL
B5: 論理テーブル名 | C5: 年末調整入力_所得調整 | E5: ENGINE | I5: InnoDB
B6: 物理テーブル名 | C6: nencho_input_income_adjustment | E6: CHARSET | I6: utf8mb4
B7: 備考
A12: カラム情報 | L12: 外部キー情報
A13: No | B13: 論理名 | C13: 物理名 | D13: データ型 | E13: Size | F13: Not Null | G13: PK | H13: UK | I13: デフォルト | J13: 備考 | L13: 親テーブル | M13: 参照カラム
A14: 1 | B14: 社員連番 | C14: syainseq | D14: bigint | F14: not null | G14: 〇
A15: 2 | B15: 年度 | C15: year | D15: smallint | F15: not null | G15: 〇
A16: 3 | B16: 申告書提出区分 | C16: tax_return_filing_type | D16: tinyint | F16: not null | J16: コードマスタ.SQS0046
A17: 4 | B17: 扶養親族氏名 | C17: dependent_relative_name | D17: varchar | E17: 255 | F17: not null
A18: 5 | B18: 作成者 | C18: created_by | D18: bigint | F18: not null
A19: 6 | B19: 作成日時 | C19: created_at | D19: datetime | E19: 6 | F19: not null
A20: 7 | B20: 更新者 | C20: updated_by | D20: bigint | F20: not null
A21: 8 | B21: 更新日時 | C21: updated_at | D21: datetime | E21: 6 | F21: not null

Sheet 年末調整入力_扶養親族退職所得
A1: テーブル情報
B2: システム名 | C2: SOCIA | E2: 作成者 | I2: ITSP | M2: テーブル一覧へ
B3: サブシステム名 | C3: 給与 | E3: 作成日 | I3: 2025-11-28
B4: スキーマ名 | E4: RDBMS | I4: MySQL
B5: 論理テーブル名 | C5: 年末調整入力_扶養親族退職所得 | E5: ENGINE | I5: InnoDB
B6: 物理テーブル名 | C6: nencho_input_dependent_relative_retirement_income | E6: CHARSET | I6: utf8mb4
B7: 備考
A12: カラム情報 | L12: 外部キー情報
A13: No | B13: 論理名 | C13: 物理名 | D13: データ型 | E13: Size | F13: Not Null | G13: PK | H13: UK | I13: デフォルト | J13: 備考 | L13: 親テーブル | M13: 参照カラム
A14: 1 | B14: 社員連番 | C14: syainseq | D14: bigint | F14: not null | G14: 〇
A15: 2 | B15: 年度 | C15: year | D15: smallint | F15: not null | G15: 〇
A16: 3 | B16: データ連番 | C16: dataseq | D16: int | F16: not null | G16: 〇
A17: 4 | B17: 氏名 | C17: name | D17: varchar | E17: 255
A18: 5 | B18: フリガナ | C18: furigana | D18: varchar | E18: 20
A19: 6 | B19: 生年月日 | C19: birth_date | D19: date
A20: 7 | B20: 続柄名称 | C20: relation_name | D20: varchar | E20: 255
A21: 8 | B21: 住所 | C21: address | D21: varchar | E21: 100
A22: 9 | B22: 非居住者区分 | C22: nonresident_type | D22: tinyint | J22: 0:非居住者ではない、1:非居住者
A23: 10 | B23: 障害者区分 | C23: disability_type | D23: tinyint | J23: コードマスタ.SQS0004
A24: 11 | B24: 所得見積額 | C24: income_estimate_amount | D24: bigint | F24: not null
A25: 12 | B25: 作成者 | C25: created_by | D25: bigint | F25: not null
A26: 13 | B26: 作成日時 | C26: created_at | D26: datetime | E26: 6 | F26: not null
A27: 14 | B27: 更新者 | C27: updated_by | D27: bigint | F27: not null
A28: 15 | B28: 更新日時 | C28: updated_at | D28: datetime | E28: 6 | F28: not null

Sheet 年末調整入力_摘要
A1: テーブル情報
B2: システム名 | C2: SOCIA | E2: 作成者 | I2: ITSP | M2: テーブル一覧へ
B3: サブシステム名 | C3: 給与 | E3: 作成日 | I3: 2025-11-28
B4: スキーマ名 | E4: RDBMS | I4: MySQL
B5: 論理テーブル名 | C5: 年末調整入力_摘要 | E5: ENGINE | I5: InnoDB
B6: 物理テーブル名 | C6: nencho_input_summary | E6: CHARSET | I6: utf8mb4
B7: 備考
A12: カラム情報 | L12: 外部キー情報
A13: No | B13: 論理名 | C13: 物理名 | D13: データ型 | E13: Size | F13: Not Null | G13: PK | H13: UK | I13: デフォルト | J13: 備考 | L13: 親テーブル | M13: 参照カラム
A14: 1 | B14: 社員連番 | C14: syainseq | D14: bigint | F14: not null | G14: 〇
A15: 2 | B15: 年度 | C15: year | D15: smallint | F15: not null | G15: 〇
A16: 3 | B16: 届出コード | C16: submission_code | D16: varchar | E16: 20 | F16: not null | G16: 〇
A17: 4 | B17: 課税区分 | C17: tax_type | D17: tinyint | F17: not null | G17: 〇
A18: 5 | B18: 内容 | C18: content | D18: varchar | E18: 100 | F18: not null
A19: 6 | B19: 作成者 | C19: created_by | D19: bigint | F19: not null
A20: 7 | B20: 作成日時 | C20: created_at | D20: datetime | E20: 6 | F20: not null
A21: 8 | B21: 更新者 | C21: updated_by | D21: bigint | F21: not null
A22: 9 | B22: 更新日時 | C22: updated_at | D22: datetime | E22: 6 | F22: not null

Sheet 年末調整入力_調整項目
A1: テーブル情報
B2: システム名 | C2: SOCIA | E2: 作成者 | I2: ITSP | M2: テーブル一覧へ
B3: サブシステム名 | C3: 給与 | E3: 作成日 | I3: 2025-11-28
B4: スキーマ名 | E4: RDBMS | I4: MySQL
B5: 論理テーブル名 | C5: 年末調整入力_調整項目 | E5: ENGINE | I5: InnoDB
B6: 物理テーブル名 | C6: nencho_input_adjustment_item | E6: CHARSET | I6: utf8mb4
B7: 備考
A12: カラム情報 | L12: 外部キー情報
A13: No | B13: 論理名 | C13: 物理名 | D13: データ型 | E13: Size | F13: Not Null | G13: PK | H13: UK | I13: デフォルト | J13: 備考 | L13: 親テーブル | M13: 参照カラム
A14: 1 | B14: 社員連番 | C14: syainseq | D14: bigint | F14: not null | G14: 〇
A15: 2 | B15: 年度 | C15: year | D15: smallint | F15: not null | G15: 〇
A16: 3 | B16: 届出コード | C16: submission_code | D16: varchar | E16: 20 | F16: not null | G16: 〇
A17: 4 | B17: 課税区分 | C17: tax_type | D17: tinyint | F17: not null | G17: 〇 | J17: コードマスタ.SQS0002
A18: 5 | B18: 調整加算区分 | C18: add_type | D18: tinyint | F18: not null | J18: 0:未加算、1:加算済
A19: 6 | B19: 支払金額 | C19: payment_amount | D19: bigint | F19: not null
A20: 7 | B20: 所得税額 | C20: income_tax_amount | D20: bigint | F20: not null
A21: 8 | B21: 社会保険料(給与控除分) | C21: syaho_fee_kyuyo_deduction | D21: bigint | F21: not null
A22: 9 | B22: 小規模企業掛金(給与控除分) | C22: small_enterprise_contribution_kyuyo_deduction | D22: bigint | F22: not null | I22: 0
A23: 10 | B23: 前回入力支払金額 | C23: last_input_payment_amount | D23: bigint | F23: not null
A24: 11 | B24: 前回入力所得税額 | C24: last_input_income_tax_amount | D24: bigint | F24: not null
A25: 12 | B25: 前回入力社会保険料(給与控除分) | C25: last_input_syaho_kyuyo_deduction | D25: bigint | F25: not null
A26: 13 | B26: 前回入力小規模企業掛金(給与控除分) | C26: last_input_small_enterprise_contribution_kyuyo_deduction | D26: bigint | F26: not null | I26: 0
A27: 14 | B27: 作成者 | C27: created_by | D27: bigint | F27: not null
A28: 15 | B28: 作成日時 | C28: created_at | D28: datetime | E28: 6 | F28: not null
A29: 16 | B29: 更新者 | C29: updated_by | D29: bigint | F29: not null
A30: 17 | B30: 更新日時 | C30: updated_at | D30: datetime | E30: 6 | F30: not null

Sheet 年末調整入力_配偶者
A1: テーブル情報
B2: システム名 | C2: SOCIA | E2: 作成者 | I2: ITSP | M2: テーブル一覧へ
B3: サブシステム名 | C3: 給与 | E3: 作成日 | I3: 2025-11-28
B4: スキーマ名 | E4: RDBMS | I4: MySQL
B5: 論理テーブル名 | C5: 年末調整入力_配偶者 | E5: ENGINE | I5: InnoDB
B6: 物理テーブル名 | C6: nencho_input_spouse | E6: CHARSET | I6: utf8mb4
B7: 備考
A12: カラム情報 | L12: 外部キー情報
A13: No | B13: 論理名 | C13: 物理名 | D13: データ型 | E13: Size | F13: Not Null | G13: PK | H13: UK | I13: デフォルト | J13: 備考 | L13: 親テーブル | M13: 参照カラム
A14: 1 | B14: 社員連番 | C14: syainseq | D14: bigint | F14: not null | G14: 〇
A15: 2 | B15: 年度 | C15: year | D15: smallint | F15: not null | G15: 〇
A16: 3 | B16: 申告書提出区分 | C16: tax_return_filing_type | D16: tinyint | F16: not null | J16: コードマスタ.SQS0046
A17: 4 | B17: 配偶者合計所得 | C17: spouse_total_income | D17: bigint | F17: not null
A18: 5 | B18: 作成者 | C18: created_by | D18: bigint | F18: not null
A19: 6 | B19: 作成日時 | C19: created_at | D19: datetime | E19: 6 | F19: not null
A20: 7 | B20: 更新者 | C20: updated_by | D20: bigint | F20: not null
A21: 8 | B21: 更新日時 | C21: updated_at | D21: datetime | E21: 6 | F21: not null

Sheet 年末調整前職
A1: テーブル情報
B2: システム名 | C2: SOCIA | E2: 作成者 | I2: ITSP | M2: テーブル一覧へ
B3: サブシステム名 | C3: 給与 | E3: 作成日 | I3: 2025-11-28
B4: スキーマ名 | E4: RDBMS | I4: MySQL
B5: 論理テーブル名 | C5: 年末調整前職 | E5: ENGINE | I5: InnoDB
B6: 物理テーブル名 | C6: nencho_previous_job | E6: CHARSET | I6: utf8mb4
B7: 備考
A12: カラム情報 | L12: 外部キー情報
A13: No | B13: 論理名 | C13: 物理名 | D13: データ型 | E13: Size | F13: Not Null | G13: PK | H13: UK | I13: デフォルト | J13: 備考 | L13: 親テーブル | M13: 参照カラム
A14: 1 | B14: 社員連番 | C14: syainseq | D14: bigint | F14: not null | G14: 〇
A15: 2 | B15: 年度 | C15: year | D15: smallint | F15: not null | G15: 〇
A16: 3 | B16: 支払金額 | C16: payment_amount | D16: bigint | F16: not null
A17: 4 | B17: 税額 | C17: tax_amount | D17: bigint | F17: not null
A18: 5 | B18: 小規模企業掛金 | C18: small_enterprise_contribution | D18: bigint | F18: not null
A19: 6 | B19: 社会保険料 | C19: syaho_fee | D19: bigint | F19: not null
A20: 7 | B20: 退職年月日 | C20: retirement_date | D20: date
A21: 8 | B21: 会社名称 | C21: kaisya_name | D21: varchar | E21: 255
A22: 9 | B22: 所在地 | C22: address | D22: varchar | E22: 120
A23: 10 | B23: 会社海外区分 | C23: kaisya_oversea_type | D23: tinyint | J23: 0:海外でない、1:海外
A24: 11 | B24: 作成者 | C24: created_by | D24: bigint | F24: not null
A25: 12 | B25: 作成日時 | C25: created_at | D25: datetime | E25: 6 | F25: not null
A26: 13 | B26: 更新者 | C26: updated_by | D26: bigint | F26: not null
A27: 14 | B27: 更新日時 | C27: updated_at | D27: datetime | E27: 6 | F27: not null

Sheet 年末調整基礎控除額
A1: テーブル情報
B2: システム名 | C2: SOCIA | E2: 作成者 | I2: ITSP | M2: テーブル一覧へ
B3: サブシステム名 | C3: 給与 | E3: 作成日 | I3: 2025-11-28
B4: スキーマ名 | E4: RDBMS | I4: MySQL
B5: 論理テーブル名 | C5: 年末調整基礎控除額 | E5: ENGINE | I5: InnoDB
B6: 物理テーブル名 | C6: nencho_basic_deduction | E6: CHARSET | I6: utf8mb4
B7: 備考
A12: カラム情報 | L12: 外部キー情報
A13: No | B13: 論理名 | C13: 物理名 | D13: データ型 | E13: Size | F13: Not Null | G13: PK | H13: UK | I13: デフォルト | J13: 備考 | L13: 親テーブル | M13: 参照カラム
A14: 1 | B14: 合計所得金額 | C14: total_income_amount | D14: bigint | F14: not null | G14: 〇
A15: 2 | B15: 有効開始年月日 | C15: fromymd | D15: date | F15: not null | G15: 〇
A16: 3 | B16: 有効終了年月日 | C16: toymd | D16: date | F16: not null
A17: 4 | B17: データ連番 | C17: dataseq | D17: int
A18: 5 | B18: 基礎控除額 | C18: basic_deduction_amount | D18: bigint | F18: not null
A19: 6 | B19: 作成者 | C19: created_by | D19: bigint | F19: not null
A20: 7 | B20: 作成日時 | C20: created_at | D20: datetime | E20: 6 | F20: not null
A21: 8 | B21: 更新者 | C21: updated_by | D21: bigint | F21: not null
A22: 9 | B22: 更新日時 | C22: updated_at | D22: datetime | E22: 6 | F22: not null

Sheet 年末調整家族情報
A1: テーブル情報
B2: システム名 | C2: SOCIA | E2: 作成者 | I2: ITSP | M2: テーブル一覧へ
B3: サブシステム名 | C3: 給与 | E3: 作成日 | I3: 2025-11-28
B4: スキーマ名 | E4: RDBMS | I4: MySQL
B5: 論理テーブル名 | C5: 年末調整家族情報 | E5: ENGINE | I5: InnoDB
B6: 物理テーブル名 | C6: nencho_family_info | E6: CHARSET | I6: utf8mb4
B7: 備考
B8: 扶養親族と配偶者の両方
A12: カラム情報 | L12: 外部キー情報
A13: No | B13: 論理名 | C13: 物理名 | D13: データ型 | E13: Size | F13: Not Null | G13: PK | H13: UK | I13: デフォルト | J13: 備考 | L13: 親テーブル | M13: 参照カラム
A14: 1 | B14: 社員連番 | C14: syainseq | D14: bigint | F14: not null | G14: 〇
A15: 2 | B15: 年度 | C15: year | D15: smallint | F15: not null | G15: 〇
A16: 3 | B16: データ連番 | C16: dataseq | D16: int | F16: not null | G16: 〇
A17: 4 | B17: 表示順序 | C17: dsp_order | D17: bigint | F17: not null
A18: 5 | B18: 氏名 | C18: name | D18: varchar | E18: 255
A19: 6 | B19: フリガナ | C19: furigana | D19: varchar | E19: 20
A20: 7 | B20: 性別区分 | C20: sex_type | D20: tinyint | F20: not null
A21: 8 | B21: 郵便番号 | C21: postal_code | D21: varchar | E21: 10
A22: 9 | B22: 住所 | C22: address | D22: varchar | E22: 100
A23: 10 | B23: 生年月日 | C23: birth_date | D23: date
A24: 11 | B24: 続柄コード | C24: relation_code | D24: varchar | E24: 20
A25: 12 | B25: 扶養区分 | C25: dependent_type | D25: tinyint | F25: not null | J25: コードマスタ.SQS0001
A26: 13 | B26: 障害者区分 | C26: disability_type | D26: tinyint | F26: not null | J26: コードマスタ.SQS0004
A27: 14 | B27: 同一生計区分 | C27: same_household_type | D27: tinyint | F27: not null | J27: コードマスタ.SQS0047
A28: 15 | B28: 非居住者区分 | C28: nonresident_type | D28: tinyint | F28: not null
A29: 16 | B29: 非居住理由区分 | C29: nonresident_reason_type | D29: tinyint | J29: コードマスタ.SQS0011
A30: 17 | B30: 寡婦区分 | C30: widow_type | D30: tinyint | F30: not null | J30: コードマスタ.SQS0034
A31: 18 | B31: 配偶者区分 | C31: spouse_type | D31: tinyint | F31: not null | J31: コードマスタ.SQS0040
A32: 19 | B32: 作成者 | C32: created_by | D32: bigint | F32: not null
A33: 20 | B33: 作成日時 | C33: created_at | D33: datetime | E33: 6 | F33: not null
A34: 21 | B34: 更新者 | C34: updated_by | D34: bigint | F34: not null
A35: 22 | B35: 更新日時 | C35: updated_at | D35: datetime | E35: 6 | F35: not null

Sheet 年末調整所得控除額
A1: テーブル情報
B2: システム名 | C2: SOCIA | E2: 作成者 | I2: ITSP | M2: テーブル一覧へ
B3: サブシステム名 | C3: 給与 | E3: 作成日 | I3: 2025-11-28
B4: スキーマ名 | E4: RDBMS | I4: MySQL
B5: 論理テーブル名 | C5: 年末調整所得控除額 | E5: ENGINE | I5: InnoDB
B6: 物理テーブル名 | C6: nencho_income_deduction | E6: CHARSET | I6: utf8mb4
B7: 備考
A12: カラム情報 | L12: 外部キー情報
A13: No | B13: 論理名 | C13: 物理名 | D13: データ型 | E13: Size | F13: Not Null | G13: PK | H13: UK | I13: デフォルト | J13: 備考 | L13: 親テーブル | M13: 参照カラム
A14: 1 | B14: 控除項目コード | C14: deduction_item_code | D14: varchar | E14: 20 | F14: not null | G14: 〇 | J14: コードマスタ.SQS0051
A15: 2 | B15: 有効開始年月日 | C15: fromymd | D15: date | F15: not null | G15: 〇
A16: 3 | B16: 有効終了年月日 | C16: toymd | D16: date | F16: not null
A17: 4 | B17: 控除項目名 | C17: deduction_item_name | D17: varchar | E17: 255 | F17: not null
A18: 5 | B18: 控除額 | C18: deduction_amount | D18: bigint | F18: not null
A19: 6 | B19: 作成者 | C19: created_by | D19: bigint | F19: not null
A20: 7 | B20: 作成日時 | C20: created_at | D20: datetime | E20: 6 | F20: not null
A21: 8 | B21: 更新者 | C21: updated_by | D21: bigint | F21: not null
A22: 9 | B22: 更新日時 | C22: updated_at | D22: datetime | E22: 6 | F22: not null

Sheet 年末調整所得税階差
A1: テーブル情報
B2: システム名 | C2: SOCIA | E2: 作成者 | I2: ITSP | M2: テーブル一覧へ
B3: サブシステム名 | C3: 給与 | E3: 作成日 | I3: 2025-11-28
B4: スキーマ名 | E4: RDBMS | I4: MySQL
B5: 論理テーブル名 | C5: 年末調整所得税階差 | E5: ENGINE | I5: InnoDB
B6: 物理テーブル名 | C6: nencho_income_tax_difference | E6: CHARSET | I6: utf8mb4
B7: 備考
A12: カラム情報 | L12: 外部キー情報
A13: No | B13: 論理名 | C13: 物理名 | D13: データ型 | E13: Size | F13: Not Null | G13: PK | H13: UK | I13: デフォルト | J13: 備考 | L13: 親テーブル | M13: 参照カラム
A14: 1 | B14: 課税所得額 | C14: tax_income_amount | D14: bigint | F14: not null | G14: 〇
A15: 2 | B15: 有効開始年月日 | C15: fromymd | D15: date | F15: not null | G15: 〇
A16: 3 | B16: 有効終了年月日 | C16: toymd | D16: date | F16: not null
A17: 4 | B17: データ連番 | C17: dataseq | D17: int
A18: 5 | B18: 階差 | C18: difference | D18: int | F18: not null
A19: 6 | B19: 作成者 | C19: created_by | D19: bigint | F19: not null
A20: 7 | B20: 作成日時 | C20: created_at | D20: datetime | E20: 6 | F20: not null
A21: 8 | B21: 更新者 | C21: updated_by | D21: bigint | F21: not null
A22: 9 | B22: 更新日時 | C22: updated_at | D22: datetime | E22: 6 | F22: not null

Sheet 年末調整所得税額
A1: テーブル情報
B2: システム名 | C2: SOCIA | E2: 作成者 | I2: ITSP | M2: テーブル一覧へ
B3: サブシステム名 | C3: 給与 | E3: 作成日 | I3: 2025-11-28
B4: スキーマ名 | E4: RDBMS | I4: MySQL
B5: 論理テーブル名 | C5: 年末調整所得税額 | E5: ENGINE | I5: InnoDB
B6: 物理テーブル名 | C6: nencho_income_tax | E6: CHARSET | I6: utf8mb4
B7: 備考
A12: カラム情報 | L12: 外部キー情報
A13: No | B13: 論理名 | C13: 物理名 | D13: データ型 | E13: Size | F13: Not Null | G13: PK | H13: UK | I13: デフォルト | J13: 備考 | L13: 親テーブル | M13: 参照カラム
A14: 1 | B14: 課税所得額 | C14: tax_income_amount | D14: bigint | F14: not null | G14: 〇
A15: 2 | B15: 有効開始年月日 | C15: fromymd | D15: date | F15: not null | G15: 〇
A16: 3 | B16: 有効終了年月日 | C16: toymd | D16: date | F16: not null
A17: 4 | B17: データ連番 | C17: dataseq | D17: int
A18: 5 | B18: 税率 | C18: tax_rate | D18: decimal | E18: 8,4 | F18: not null
A19: 6 | B19: 控除額 | C19: deduction_amount | D19: bigint | F19: not null
A20: 7 | B20: 作成者 | C20: created_by | D20: bigint | F20: not null
A21: 8 | B21: 作成日時 | C21: created_at | D21: datetime | E21: 6 | F21: not null
A22: 9 | B22: 更新者 | C22: updated_by | D22: bigint | F22: not null
A23: 10 | B23: 更新日時 | C23: updated_at | D23: datetime | E23: 6 | F23: not null

Sheet 年末調整税法
A1: テーブル情報
B2: システム名 | C2: SOCIA | E2: 作成者 | I2: ITSP | M2: テーブル一覧へ
B3: サブシステム名 | C3: 給与 | E3: 作成日 | I3: 2025-11-28
B4: スキーマ名 | E4: RDBMS | I4: MySQL
B5: 論理テーブル名 | C5: 年末調整税法 | E5: ENGINE | I5: InnoDB
B6: 物理テーブル名 | C6: nencho_tax_law | E6: CHARSET | I6: utf8mb4
B7: 備考
A12: カラム情報 | L12: 外部キー情報
A13: No | B13: 論理名 | C13: 物理名 | D13: データ型 | E13: Size | F13: Not Null | G13: PK | H13: UK | I13: デフォルト | J13: 備考 | L13: 親テーブル | M13: 参照カラム
A14: 1 | B14: 社員連番 | C14: syainseq | D14: bigint | F14: not null | G14: 〇
A15: 2 | B15: 年度 | C15: year | D15: smallint | F15: not null | G15: 〇
A16: 3 | B16: 居住者区分 | C16: resident_type | D16: tinyint | F16: not null | J16: コードマスタ.SQS0033
A17: 4 | B17: 障害者区分 | C17: disability_type | D17: tinyint | F17: not null | J17: コードマスタ.SQS0004
A18: 5 | B18: 寡婦区分 | C18: widow_type | D18: tinyint | F18: not null | J18: コードマスタ.SQS0034
A19: 6 | B19: 学生区分 | C19: student_type | D19: tinyint | F19: not null | J19: コードマスタ.SQS0035
A20: 7 | B20: 未成年者区分 | C20: minor_type | D20: tinyint | F20: not null | J20: コードマスタ.SQS0036
A21: 8 | B21: 死亡退職区分 | C21: death_retirement_type | D21: tinyint | F21: not null | J21: コードマスタ.SQS0037
A22: 9 | B22: 災害者区分 | C22: disaster_type | D22: tinyint | F22: not null | J22: コードマスタ.SQS0038
A23: 10 | B23: 外国人区分 | C23: foreigner_type | D23: tinyint | F23: not null | J23: コードマスタ.SQS0039
A24: 11 | B24: 配偶者区分 | C24: spouse_type | D24: tinyint | F24: not null | J24: コードマスタ.SQS0040
A25: 12 | B25: 配偶者控除区分 | C25: spouse_deduction_type | D25: tinyint | F25: not null | J25: コードマスタ.SQS0041
A26: 13 | B26: 配偶者特別控除区分 | C26: spouse_special_deduction_type | D26: tinyint | F26: not null | J26: コードマスタ.SQS0042
A27: 14 | B27: 配偶者源泉控除区分 | C27: spouse_withholding_deduction_type | D27: tinyint | F27: not null | J27: コードマスタ.SQS0043
... A29: 16 | B29: 親族扶養区分 | C29: relative_dependent_type | D29: tinyint | F29: not null | J29: コードマスタ.SQS0056
A30: 17 | B30: 親族一般扶養 | C30: relative_general_dependent | D30: tinyint | F30: not null
A31: 18 | B31: 親族特定扶養 | C31: relative_specific_dependent | D31: tinyint | F31: not null
A32: 19 | B32: 親族年少扶養 | C32: relative_young_dependent | D32: tinyint | F32: not null
A33: 20 | B33: 親族同居老親扶養 | C33: relative_cohabitation_elderly_relative | D33: tinyint | F33: not null
A34: 21 | B34: 親族老人扶養 | C34: relative_elderly_dependent | D34: tinyint | F34: not null
A35: 22 | B35: 親族一般障害 | C35: relative_general_disability | D35: tinyint | F35: not null
A36: 23 | B36: 親族特別障害 | C36: relative_special_disability | D36: tinyint | F36: not null
A37: 24 | B37: 親族同居特別障害一般扶養 | C37: relative_cohabitation_special_disability_general_dependent | D37: tinyint | F37: not null
A38: 25 | B38: 親族同居特別障害特定扶養 | C38: relative_cohabitation_special_disability_specific_dependent | D38: tinyint | F38: not null
A39: 26 | B39: 親族同居特別障害年少扶養 | C39: relative_cohabitation_special_disability_young_dependent | D39: tinyint | F39: not null
A40: 27 | B40: 親族同居特別障害老親扶養 | C40: relative_cohabitation_special_disability_elderly_relative | D40: tinyint | F40: not null
A41: 28 | B41: 親族同居特別障害老人扶養 | C41: relative_cohabitation_special_disability_elderly_dependent | D41: tinyint | F41: not null
A42: 29 | B42: 作成者 | C42: created_by | D42: bigint | F42: not null
A43: 30 | B43: 作成日時 | C43: created_at | D43: datetime | E43: 6 | F43: not null
A44: 31 | B44: 更新者 | C44: updated_by | D44: bigint | F44: not null
A45: 32 | B45: 更新日時 | C45: updated_at | D45: datetime | E45: 6 | F45: not null

Sheet 年末調整給与所得控除額
A1: テーブル情報
B2: システム名 | C2: SOCIA | E2: 作成者 | I2: ITSP | M2: テーブル一覧へ
B3: サブシステム名 | C3: 給与 | E3: 作成日 | I3: 2025-11-28
B4: スキーマ名 | E4: RDBMS | I4: MySQL
B5: 論理テーブル名 | C5: 年末調整給与所得控除額 | E5: ENGINE | I5: InnoDB
B6: 物理テーブル名 | C6: nencho_kyuyo_income_deduction | E6: CHARSET | I6: utf8mb4
B7: 備考
A12: カラム情報 | L12: 外部キー情報
A13: No | B13: 論理名 | C13: 物理名 | D13: データ型 | E13: Size | F13: Not Null | G13: PK | H13: UK | I13: デフォルト | J13: 備考 | L13: 親テーブル | M13: 参照カラム
A14: 1 | B14: 給与額 | C14: kyuyo_amount | D14: bigint | F14: not null | G14: 〇
A15: 2 | B15: 有効開始年月日 | C15: fromymd | D15: date | F15: not null | G15: 〇
A16: 3 | B16: 有効終了年月日 | C16: toymd | D16: date | F16: not null
A17: 4 | B17: データ連番 | C17: dataseq | D17: int
A18: 5 | B18: 階差 | C18: difference | D18: int
A19: 6 | B19: 控除率 | C19: deduction_rate | D19: decimal | E19: 6,2 | F19: not null
A20: 7 | B20: 控除額 | C20: deduction_amount | D20: bigint | F20: not null
A21: 8 | B21: 作成者 | C21: created_by | D21: bigint | F21: not null
A22: 9 | B22: 作成日時 | C22: created_at | D22: datetime | E22: 6 | F22: not null
A23: 10 | B23: 更新者 | C23: updated_by | D23: bigint | F23: not null
A24: 11 | B24: 更新日時 | C24: updated_at | D24: datetime | E24: 6 | F24: not null

Sheet 年末調整還付
A1: テーブル情報
B2: システム名 | C2: SOCIA | E2: 作成者 | I2: ITSP | M2: テーブル一覧へ
B3: サブシステム名 | C3: 給与 | E3: 作成日 | I3: 2025-11-28
B4: スキーマ名 | E4: RDBMS | I4: MySQL
B5: 論理テーブル名 | C5: 年末調整還付 | E5: ENGINE | I5: InnoDB
B6: 物理テーブル名 | C6: nencho_refund | E6: CHARSET | I6: utf8mb4
B7: 備考
A12: カラム情報 | L12: 外部キー情報
A13: No | B13: 論理名 | C13: 物理名 | D13: データ型 | E13: Size | F13: Not Null | G13: PK | H13: UK | I13: デフォルト | J13: 備考 | L13: 親テーブル | M13: 参照カラム
A14: 1 | B14: 社員連番 | C14: syainseq | D14: bigint | F14: not null | G14: 〇
A15: 2 | B15: 年度 | C15: year | D15: smallint | F15: not null | G15: 〇
A16: 3 | B16: 締年月日 | C16: shime_date | D16: date | F16: not null | G16: 〇 | J16: 賞与の場合、支給年月日と同じ値
A17: 4 | B17: 支給年月日 | C17: payment_date | D17: date | F17: not null | G17: 〇
A18: 5 | B18: 還付区分 | C18: refund_type | D18: tinyint | F18: not null | G18: 〇 | J18: コードマスタ.SQS0029
A19: 6 | B19: 還付額 | C19: refund_amount | D19: bigint | F19: not null
A20: 7 | B20: 作成者 | C20: created_by | D20: bigint | F20: not null
A21: 8 | B21: 作成日時 | C21: created_at | D21: datetime | E21: 6 | F21: not null
A22: 9 | B22: 更新者 | C22: updated_by | D22: bigint | F22: not null
A23: 10 | B23: 更新日時 | C23: updated_at | D23: datetime | E23: 6 | F23: not null

Sheet 年末調整配偶者(特別)控除額
A1: テーブル情報
B2: システム名 | C2: SOCIA | E2: 作成者 | I2: ITSP | M2: テーブル一覧へ
B3: サブシステム名 | C3: 給与 | E3: 作成日 | I3: 2025-11-28
B4: スキーマ名 | E4: RDBMS | I4: MySQL
B5: 論理テーブル名 | C5: 年末調整配偶者(特別)控除額 | E5: ENGINE | I5: InnoDB
B6: 物理テーブル名 | C6: nencho_spouse_deduction | E6: CHARSET | I6: utf8mb4
B7: 備考
A12: カラム情報 | L12: 外部キー情報
A13: No | B13: 論理名 | C13: 物理名 | D13: データ型 | E13: Size | F13: Not Null | G13: PK | H13: UK | I13: デフォルト | J13: 備考 | L13: 親テーブル | M13: 参照カラム
A14: 1 | B14: 控除区分 | C14: deduction_type | D14: tinyint | F14: not null | G14: 〇 | J14: コードマスタ.SQS0007
A15: 2 | B15: 課税所得額 | C15: tax_income_amount | D15: bigint | F15: not null | G15: 〇
A16: 3 | B16: 有効開始年月日 | C16: fromymd | D16: date | F16: not null | G16: 〇
A17: 4 | B17: 有効終了年月日 | C17: toymd | D17: date | F17: not null
A18: 5 | B18: データ連番 | C18: dataseq | D18: int
A19: 6 | B19: 控除額（900万円以下） | C19: deduction_amount | D19: bigint | F19: not null
A20: 7 | B20: 控除額（950万円以下） | C20: deduction_amount2 | D20: bigint | F20: not null
A21: 8 | B21: 控除額（1000万円以下） | C21: deduction_amount3 | D21: bigint | F21: not null
A22: 9 | B22: 作成者 | C22: created_by | D22: bigint | F22: not null
A23: 10 | B23: 作成日時 | C23: created_at | D23: datetime | E23: 6 | F23: not null
A24: 11 | B24: 更新者 | C24: updated_by | D24: bigint | F24: not null
A25: 12 | B25: 更新日時 | C25: updated_at | D25: datetime | E25: 6 | F25: not null

Sheet 手当連動ストアドワーク
A1: テーブル情報
B2: システム名 | C2: SOCIA | E2: 作成者 | I2: ITSP | M2: テーブル一覧へ
B3: サブシステム名 | C3: 給与 | E3: 作成日 | I3: 2025-11-28
B4: スキーマ名 | E4: RDBMS | I4: MySQL
B5: 論理テーブル名 | C5: 手当連動ストアドワーク | E5: ENGINE | I5: InnoDB
B6: 物理テーブル名 | C6: charge_linked_stored_work | E6: CHARSET | I6: utf8mb4
B7: 備考
A12: カラム情報 | L12: 外部キー情報
A13: No | B13: 論理名 | C13: 物理名 | D13: データ型 | E13: Size | F13: Not Null | G13: PK | H13: UK | I13: デフォルト | J13: 備考 | L13: 親テーブル | M13: 参照カラム
A14: 1 | B14: 会社コード | C14: kaisyacd | D14: varchar | E14: 20 | F14: not null | G14: 〇
A15: 2 | B15: 社員連番 | C15: syainseq | D15: bigint | F15: not null | G15: 〇
A16: 3 | B16: 設定コード | C16: set_code | D16: varchar | E16: 20 | F16: not null | G16: 〇
A17: 4 | B17: X軸詳細SEQ | C17: x_axis_detail_seq | D17: smallint | F17: not null | G17: 〇
A18: 5 | B18: Y軸詳細SEQ | C18: y_axis_detail_seq | D18: smallint | F18: not null | G18: 〇

Sheet 手当連動値設定
A1: テーブル情報
B2: システム名 | C2: SOCIA | E2: 作成者 | I2: ITSP | M2: テーブル一覧へ
B3: サブシステム名 | C3: 給与 | E3: 作成日 | I3: 2025-11-28
B4: スキーマ名 | E4: RDBMS | I4: MySQL
B5: 論理テーブル名 | C5: 手当連動値設定 | E5: ENGINE | I5: InnoDB
B6: 物理テーブル名 | C6: charge_linked_setvalue_set | E6: CHARSET | I6: utf8mb4
B7: 備考
A12: カラム情報 | L12: 外部キー情報
A13: No | B13: 論理名 | C13: 物理名 | D13: データ型 | E13: Size | F13: Not Null | G13: PK | H13: UK | I13: デフォルト | J13: 備考 | L13: 親テーブル | M13: 参照カラム
A14: 1 | B14: 設定コード | C14: set_code | D14: varchar | E14: 20 | F14: not null | G14: 〇
A15: 2 | B15: 会社コード | C15: kaisyacd | D15: varchar | E15: 20 | F15: not null | G15: 〇
A16: 3 | B16: 有効開始年月日 | C16: fromymd | D16: date | F16: not null | G16: 〇
A17: 4 | B17: 有効終了年月日 | C17: toymd | D17: date | F17: not null
A18: 5 | B18: X軸詳細SEQ | C18: x_axis_detail_seq | D18: smallint | F18: not null | G18: 〇
A19: 6 | B19: Y軸詳細SEQ | C19: y_axis_detail_seq | D19: smallint | F19: not null | G19: 〇
A20: 7 | B20: 値 | C20: setvalue | D20: varchar | E20: 255
A21: 8 | B21: 作成者 | C21: created_by | D21: bigint | F21: not null
A22: 9 | B22: 作成日時 | C22: created_at | D22: datetime | E22: 6 | F22: not null
A23: 10 | B23: 更新者 | C23: updated_by | D23: bigint | F23: not null
A24: 11 | B24: 更新日時 | C24: updated_at | D24: datetime | E24: 6 | F24: not null

Sheet 手当連動表設定
A1: テーブル情報
B2: システム名 | C2: SOCIA | E2: 作成者 | I2: ITSP | M2: テーブル一覧へ
B3: サブシステム名 | C3: 給与 | E3: 作成日 | I3: 2025-11-28
B4: スキーマ名 | E4: RDBMS | I4: MySQL
B5: 論理テーブル名 | C5: 手当連動表設定 | E5: ENGINE | I5: InnoDB
B6: 物理テーブル名 | C6: charge_linked_table_set | E6: CHARSET | I6: utf8mb4
B7: 備考
A12: カラム情報 | L12: 外部キー情報
A13: No | B13: 論理名 | C13: 物理名 | D13: データ型 | E13: Size | F13: Not Null | G13: PK | H13: UK | I13: デフォルト | J13: 備考 | L13: 親テーブル | M13: 参照カラム
A14: 1 | B14: 設定コード | C14: set_code | D14: varchar | E14: 20 | F14: not null | G14: 〇
A15: 2 | B15: 会社コード | C15: kaisyacd | D15: varchar | E15: 20 | F15: not null | G15: 〇
A16: 3 | B16: 有効開始年月日 | C16: fromymd | D16: date | F16: not null | G16: 〇
A17: 4 | B17: 有効終了年月日 | C17: toymd | D17: date | F17: not null
A18: 5 | B18: XY区分 | C18: xy_type | D18: tinyint | F18: not null | G18: 〇 | J18: コードマスタ.SQS0017
A19: 6 | B19: 条件No | C19: condition_no | D19: smallint | F19: not null | G19: 〇
A20: 7 | B20: 条件名称 | C20: condition_name | D20: varchar | E20: 40 | F20: not null
A21: 8 | B21: 情報名称 | C21: info_name | D21: varchar | E21: 40 | F21: not null
A22: 9 | B22: 詳細名称 | C22: detail_name | D22: varchar | E22: 40 | F22: not null
A23: 10 | B23: 期間計算 | C23: period_equation | D23: tinyint | I23: 0 | J23: コードマスタ.SQS0018
A24: 11 | B24: 作成者 | C24: created_by | D24: bigint | F24: not null
A25: 12 | B25: 作成日時 | C25: created_at | D25: datetime | E25: 6 | F25: not null
A26: 13 | B26: 更新者 | C26: updated_by | D26: bigint | F26: not null
A27: 14 | B27: 更新日時 | C27: updated_at | D27: datetime | E27: 6 | F27: not null

Sheet 手当連動表詳細要素
A1: テーブル情報
B2: システム名 | C2: SOCIA | E2: 作成者 | I2: ITSP | M2: テーブル一覧へ
B3: サブシステム名 | C3: 給与 | E3: 作成日 | I3: 2025-11-28
B4: スキーマ名 | E4: RDBMS | I4: MySQL
B5: 論理テーブル名 | C5: 手当連動表詳細要素 | E5: ENGINE | I5: InnoDB
B6: 物理テーブル名 | C6: charge_linked_table_detail_factor | E6: CHARSET | I6: utf8mb4
B7: 備考
A12: カラム情報 | L12: 外部キー情報
A13: No | B13: 論理名 | C13: 物理名 | D13: データ型 | E13: Size | F13: Not Null | G13: PK | H13: UK | I13: デフォルト | J13: 備考 | L13: 親テーブル | M13: 参照カラム
A14: 1 | B14: 設定コード | C14: set_code | D14: varchar | E14: 20 | F14: not null | G14: 〇
A15: 2 | B15: 会社コード | C15: kaisyacd | D15: varchar | E15: 20 | F15: not null | G15: 〇
A16: 3 | B16: 有効開始年月日 | C16: fromymd | D16: date | F16: not null | G16: 〇
A17: 4 | B17: 有効終了年月日 | C17: toymd | D17: date | F17: not null
A18: 5 | B18: XY区分 | C18: xy_type | D18: tinyint | F18: not null | G18: 〇 | J18: コードマスタ.SQS0017
A19: 6 | B19: 条件No | C19: condition_no | D19: smallint | F19: not null | G19: 〇
A20: 7 | B20: 詳細SEQ | C20: detail_seq | D20: smallint | F20: not null | G20: 〇
A21: 8 | B21: 要素NO | C21: factor_no | D21: smallint | F21: not null | G21: 〇
A22: 9 | B22: 選択項目ID | C22: code_itemid | D22: bigint | J22: 選択された選択項目値のIDを設定する
A23: 10 | B23: 値指定値1 | C23: inputed_value1 | D23: varchar | E23: 50 | J23: 値入力時、入力した単一値、範囲指定の開始値、複数指定の場合のすべて入力値を格納する
A24: 11 | B24: 値指定値2 | C24: inputed_value2 | D24: varchar | E24: 50 | J24: 値入力時、範囲指定の終了値を格納する
A25: 12 | B25: 作成者 | C25: created_by | D25: bigint | F25: not null
A26: 13 | B26: 作成日時 | C26: created_at | D26: datetime | E26: 6 | F26: not null
A27: 14 | B27: 更新者 | C27: updated_by | D27: bigint | F27: not null
A28: 15 | B28: 更新日時 | C28: updated_at | D28: datetime | E28: 6 | F28: not null

Sheet 手当連動表詳細設定
A1: テーブル情報
B2: システム名 | C2: SOCIA | E2: 作成者 | I2: ITSP | M2: テーブル一覧へ
B3: サブシステム名 | C3: 給与 | E3: 作成日 | I3: 2025-11-28
B4: スキーマ名 | E4: RDBMS | I4: MySQL
B5: 論理テーブル名 | C5: 手当連動表詳細設定 | E5: ENGINE | I5: InnoDB
B6: 物理テーブル名 | C6: charge_linked_table_detail_set | E6: CHARSET | I6: utf8mb4
B7: 備考
A12: カラム情報 | L12: 外部キー情報
A13: No | B13: 論理名 | C13: 物理名 | D13: データ型 | E13: Size | F13: Not Null | G13: PK | H13: UK | I13: デフォルト | J13: 備考 | L13: 親テーブル | M13: 参照カラム
A14: 1 | B14: 設定コード | C14: set_code | D14: varchar | E14: 20 | F14: not null | G14: 〇
A15: 2 | B15: 会社コード | C15: kaisyacd | D15: varchar | E15: 20 | F15: not null | G15: 〇
A16: 3 | B16: 有効開始年月日 | C16: fromymd | D16: date | F16: not null | G16: 〇
A17: 4 | B17: 有効終了年月日 | C17: toymd | D17: date | F17: not null
A18: 5 | B18: XY区分 | C18: xy_type | D18: tinyint | F18: not null | G18: 〇 | J18: コードマスタ.SQS0017
A19: 6 | B19: 条件No | C19: condition_no | D19: smallint | F19: not null | G19: 〇
A20: 7 | B20: 詳細SEQ | C20: detail_seq | D20: smallint | F20: not null | G20: 〇
A21: 8 | B21: 詳細名称 | C21: detail_name | D21: varchar | E21: 40
A22: 9 | B22: 選択区分 | C22: selection_type | D22: tinyint | J22: コードマスタ.SQS0019
A23: 10 | B23: 選択内容 | C23: selection_content | D23: tinyint | J23: コードマスタ.SQS0020
A24: 11 | B24: 参照区分 | C24: ref_type | D24: tinyint | J24: コードマスタ.SQS0021
A25: 12 | B25: 作成者 | C25: created_by | D25: bigint | F25: not null
A26: 13 | B26: 作成日時 | C26: created_at | D26: datetime | E26: 6 | F26: not null
A27: 14 | B27: 更新者 | C27: updated_by | D27: bigint | F27: not null
A28: 15 | B28: 更新日時 | C28: updated_at | D28: datetime | E28: 6 | F28: not null

Sheet 手当連動設定
A1: テーブル情報
B2: システム名 | C2: SOCIA | E2: 作成者 | I2: ITSP | M2: テーブル一覧へ
B3: サブシステム名 | C3: 給与 | E3: 作成日 | I3: 2025-11-28
B4: スキーマ名 | E4: RDBMS | I4: MySQL
B5: 論理テーブル名 | C5: 手当連動設定 | E5: ENGINE | I5: InnoDB
B6: 物理テーブル名 | C6: charge_linked_set | E6: CHARSET | I6: utf8mb4
B7: 備考
A12: カラム情報 | L12: 外部キー情報
A13: No | B13: 論理名 | C13: 物理名 | D13: データ型 | E13: Size | F13: Not Null | G13: PK | H13: UK | I13: デフォルト | J13: 備考 | L13: 親テーブル | M13: 参照カラム
A14: 1 | B14: 設定コード | C14: set_code | D14: varchar | E14: 20 | F14: not null | G14: 〇
A15: 2 | B15: 会社コード | C15: kaisyacd | D15: varchar | E15: 20 | F15: not null | G15: 〇
A16: 3 | B16: 有効開始年月日 | C16: fromymd | D16: date | F16: not null | G16: 〇
A17: 4 | B17: 有効終了年月日 | C17: toymd | D17: date | F17: not null
A18: 5 | B18: 実行順 | C18: sort_order | D18: bigint | F18: not null
A19: 6 | B19: 手当項目名称 | C19: charge_item_name | D19: varchar | E19: 20 | F19: not null
A20: 7 | B20: ストアド名 | C20: stored_name | D20: varchar | E20: 255 | F20: not null
A21: 8 | B21: 実行用計算式 | C21: execute_equation | D21: mediumtext
A22: 9 | B22: 非表示フラグ | C22: hidden | D22: boolean | F22: not null | J22: 1:非表示、0:表示
A23: 10 | B23: 連動先区分 | C23: linked_destination_type | D23: tinyint | F23: not null | J23: コードマスタ.SQS0015
A24: 11 | B24: 支控区分 | C24: payment_deduction_type | D24: tinyint | J24: コードマスタ.SQS0049
A25: 12 | B25: 連動先項目コード | C25: linked_destination_item_code | D25: varchar | E25: 20
A26: 13 | B26: 減額時設定 | C26: upon_reduction_set | D26: tinyint | I26: 0 | J26: コードマスタ.SQS0059
A27: 14 | B27: 表名称 | C27: table_name | D27: varchar | E27: 30
A28: 15 | B28: 表示用条件式 | C28: dsp_condition | D28: text | J28: 対象者条件設定条件を格納する
A29: 16 | B29: 実行用条件式 | C29: execute_condition | D29: text
A30: 17 | B30: ストアドID | C30: stored_id | D30: varchar | E30: 64
A31: 18 | B31: 作成者 | C31: created_by | D31: bigint | F31: not null
A32: 19 | B32: 作成日時 | C32: created_at | D32: datetime | E32: 6 | F32: not null
A33: 20 | B33: 更新者 | C33: updated_by | D33: bigint | F33: not null
A34: 21 | B34: 更新日時 | C34: updated_at | D34: datetime | E34: 6 | F34: not null

Sheet 控除不能金額
A1: テーブル情報
B2: システム名 | C2: SOCIA | E2: 作成者 | I2: ITSP | M2: テーブル一覧へ
B3: サブシステム名 | C3: 給与 | E3: 作成日 | I3: 2025-11-28
B4: スキーマ名 | E4: RDBMS | I4: MySQL
B5: 論理テーブル名 | C5: 控除不能金額 | E5: ENGINE | I5: InnoDB
B6: 物理テーブル名 | C6: deduction_non_amount | E6: CHARSET | I6: utf8mb4
B7: 備考
A12: カラム情報 | L12: 外部キー情報
A13: No | B13: 論理名 | C13: 物理名 | D13: データ型 | E13: Size | F13: Not Null | G13: PK | H13: UK | I13: デフォルト | J13: 備考 | L13: 親テーブル | M13: 参照カラム
A14: 1 | B14: 社員連番 | C14: syainseq | D14: bigint | F14: not null | G14: 〇
A15: 2 | B15: 支給区分 | C15: payment_type | D15: tinyint | F15: not null | G15: 〇 | J15: コードマスタ.SQS0013
A16: 3 | B16: 締年月日 | C16: shime_date | D16: date | F16: not null | G16: 〇
A17: 4 | B17: 支給年月日 | C17: payment_date | D17: date | F17: not null | G17: 〇
A18: 5 | B18: 体系コード | C18: taikei_code | D18: varchar | E18: 20 | F18: not null | G18: 〇
A19: 6 | B19: 体系項目コード | C19: taikei_item_code | D19: varchar | E19: 20 | F19: not null | G19: 〇
A20: 7 | B20: 設定値 | C20: setvalue | D20: varchar | E20: 255
A21: 8 | B21: 作成者 | C21: created_by | D21: bigint | F21: not null
A22: 9 | B22: 作成日時 | C22: created_at | D22: datetime | E22: 6 | F22: not null
A23: 10 | B23: 更新者 | C23: updated_by | D23: bigint | F23: not null
A24: 11 | B24: 更新日時 | C24: updated_at | D24: datetime | E24: 6 | F24: not null

Sheet 支給作成ログ
A1: テーブル情報
B2: システム名 | C2: SOCIA | E2: 作成者 | I2: ITSP | M2: テーブル一覧へ
B3: サブシステム名 | C3: 給与 | E3: 作成日 | I3: 2025-11-28
B4: スキーマ名 | E4: RDBMS | I4: MySQL
B5: 論理テーブル名 | C5: 支給作成ログ | E5: ENGINE | I5: InnoDB
B6: 物理テーブル名 | C6: payment_create_log | E6: CHARSET | I6: utf8mb4
B7: 備考
A12: カラム情報 | L12: 外部キー情報
A13: No | B13: 論理名 | C13: 物理名 | D13: データ型 | E13: Size | F13: Not Null | G13: PK | H13: UK | I13: デフォルト | J13: 備考 | L13: 親テーブル | M13: 参照カラム
A14: 1 | B14: ログシーケンス | C14: logseq | D14: bigint | F14: not null | G14: 〇 | J14: データ型固定：bigint unsigned auto_increment
A15: 2 | B15: 社員連番 | C15: syainseq | D15: bigint | F15: not null
A16: 3 | B16: 締年月日 | C16: shime_date | D16: date
A17: 4 | B17: 支給年月日 | C17: payment_date | D17: date | F17: not null
A18: 5 | B18: 支給区分 | C18: payment_type | D18: tinyint | F18: not null | J18: コードマスタ.SQS0013
A19: 6 | B19: 体系コード | C19: taikei_code | D19: varchar | E19: 20 | F19: not null
A20: 7 | B20: 作成者 | C20: created_by | D20: bigint | F20: not null
A21: 8 | B21: 作成日時 | C21: created_at | D21: datetime | E21: 6 | F21: not null
A22: 9 | B22: 更新者 | C22: updated_by | D22: bigint | F22: not null
A23: 10 | B23: 更新日時 | C23: updated_at | D23: datetime | E23: 6 | F23: not null

Sheet 支給作成詳細ログ
A1: テーブル情報
B2: システム名 | C2: SOCIA | E2: 作成者 | I2: ITSP | M2: テーブル一覧へ
B3: サブシステム名 | C3: 給与 | E3: 作成日 | I3: 2025-11-28
B4: スキーマ名 | E4: RDBMS | I4: MySQL
B5: 論理テーブル名 | C5: 支給作成詳細ログ | E5: ENGINE | I5: InnoDB
B6: 物理テーブル名 | C6: payment_create_detail_log | E6: CHARSET | I6: utf8mb4
B7: 備考
A12: カラム情報 | L12: 外部キー情報
A13: No | B13: 論理名 | C13: 物理名 | D13: データ型 | E13: Size | F13: Not Null | G13: PK | H13: UK | I13: デフォルト | J13: 備考 | L13: 親テーブル | M13: 参照カラム
A14: 1 | B14: ログ詳細シーケンス | C14: logdetailseq | D14: bigint | F14: not null | G14: 〇 | J14: データ型固定：bigint unsigned auto_increment
A15: 2 | B15: ログシーケンス | C15: logseq | D15: bigint | F15: not null
A16: 3 | B16: 体系項目コード | C16: taikei_item_code | D16: varchar | E16: 20 | F16: not null
A17: 4 | B17: 項目値 | C17: item_setvalue | D17: varchar | E17: 255
A18: 5 | B18: 作成者 | C18: created_by | D18: bigint | F18: not null
A19: 6 | B19: 作成日時 | C19: created_at | D19: datetime | E19: 6 | F19: not null
A20: 7 | B20: 更新者 | C20: updated_by | D20: bigint | F20: not null
A21: 8 | B21: 更新日時 | C21: updated_at | D21: datetime | E21: 6 | F21: not null

Sheet 支給実績明細タイトル
A1: テーブル情報
B2: システム名 | C2: SOCIA | E2: 作成者 | I2: ITSP | M2: テーブル一覧へ
B3: サブシステム名 | C3: 給与 | E3: 作成日 | I3: 2025-11-28
B4: スキーマ名 | E4: RDBMS | I4: MySQL
B5: 論理テーブル名 | C5: 支給実績明細タイトル | E5: ENGINE | I5: InnoDB
B6: 物理テーブル名 | C6: payment_results_detail_title | E6: CHARSET | I6: utf8mb4
B7: 備考
A12: カラム情報 | L12: 外部キー情報
A13: No | B13: 論理名 | C13: 物理名 | D13: データ型 | E13: Size | F13: Not Null | G13: PK | H13: UK | I13: デフォルト | J13: 備考 | L13: 親テーブル | M13: 参照カラム
A14: 1 | B14: 支給区分 | C14: payment_type | D14: tinyint | F14: not null | J14: コードマスタ.SQS0013
A15: 2 | B15: 年度 | C15: year | D15: smallint | F15: not null
A16: 3 | B16: 月度 | C16: month | D16: smallint | F16: not null
A17: 4 | B17: 締日 | C17: shime_day | D17: tinyint | J17: 99:末日
A18: 5 | B18: 支給月区分 | C18: payment_month_type | D18: tinyint | J18: コードマスタ.SQS0012
A19: 6 | B19: 支給日 | C19: payment_day | D19: tinyint | F19: not null | J19: 99:末日
A20: 7 | B20: 支給年月日 | C20: payment_date | D20: date | F20: not null
A21: 8 | B21: 締年月日 | C21: shime_date | D21: date
A22: 9 | B22: タイトル | C22: title | D22: varchar | E22: 50
A23: 10 | B23: 作成者 | C23: created_by | D23: bigint | F23: not null
A24: 11 | B24: 作成日時 | C24: created_at | D24: datetime | E24: 6 | F24: not null
A25: 12 | B25: 更新者 | C25: updated_by | D25: bigint | F25: not null
A26: 13 | B26: 更新日時 | C26: updated_at | D26: datetime | E26: 6 | F26: not null

Sheet 支給実績明細備考
A1: テーブル情報
B2: システム名 | C2: SOCIA | E2: 作成者 | I2: ITSP | M2: テーブル一覧へ
B3: サブシステム名 | C3: 給与 | E3: 作成日 | I3: 2025-11-28
B4: スキーマ名 | E4: RDBMS | I4: MySQL
B5: 論理テーブル名 | C5: 支給実績明細備考 | E5: ENGINE | I5: InnoDB
B6: 物理テーブル名 | C6: payment_results_detail_note | E6: CHARSET | I6: utf8mb4
B7: 備考
A12: カラム情報 | L12: 外部キー情報
A13: No | B13: 論理名 | C13: 物理名 | D13: データ型 | E13: Size | F13: Not Null | G13: PK | H13: UK | I13: デフォルト | J13: 備考 | L13: 親テーブル | M13: 参照カラム
A14: 1 | B14: 社員連番 | C14: syainseq | D14: bigint | F14: not null
A15: 2 | B15: 支給区分 | C15: payment_type | D15: tinyint | F15: not null | J15: コードマスタ.SQS0013
A16: 3 | B16: 年度 | C16: year | D16: smallint | F16: not null
A17: 4 | B17: 月度 | C17: month | D17: smallint | F17: not null
A18: 5 | B18: 締日 | C18: shime_day | D18: tinyint | J18: 99:末日
A19: 6 | B19: 支給月区分 | C19: payment_month_type | D19: tinyint | J19: コードマスタ.SQS0012
A20: 7 | B20: 支給日 | C20: payment_day | D20: tinyint | F20: not null | J20: 99:末日
A21: 8 | B21: 支給年月日 | C21: payment_date | D21: date | F21: not null
A22: 9 | B22: 締年月日 | C22: shime_date | D22: date
A23: 10 | B23: 備考 | C23: note | D23: text
A24: 11 | B24: 作成者 | C24: created_by | D24: bigint | F24: not null
A25: 12 | B25: 作成日時 | C25: created_at | D25: datetime | E25: 6 | F25: not null
A26: 13 | B26: 更新者 | C26: updated_by | D26: bigint | F26: not null
A27: 14 | B27: 更新日時 | C27: updated_at | D27: datetime | E27: 6 | F27: not null

Sheet 支給金額データ
A1: テーブル情報
B2: システム名 | C2: SOCIA | E2: 作成者 | I2: ITSP | M2: テーブル一覧へ
B3: サブシステム名 | C3: 給与 | E3: 作成日 | I3: 2025-11-28
B4: スキーマ名 | E4: RDBMS | I4: MySQL
B5: 論理テーブル名 | C5: 支給金額データ | E5: ENGINE | I5: InnoDB
B6: 物理テーブル名 | C6: payment_amount_data | E6: CHARSET | I6: utf8mb4
B7: 備考
A12: カラム情報 | L12: 外部キー情報
A13: No | B13: 論理名 | C13: 物理名 | D13: データ型 | E13: Size | F13: Not Null | G13: PK | H13: UK | I13: デフォルト | J13: 備考 | L13: 親テーブル | M13: 参照カラム
A14: 1 | B14: 社員連番 | C14: syainseq | D14: bigint | F14: not null | G14: 〇
A15: 2 | B15: 支給区分 | C15: payment_type | D15: tinyint | F15: not null | G15: 〇 | J15: コードマスタ.SQS0013
A16: 3 | B16: データ種別 | C16: data_class | D16: tinyint | F16: not null | G16: 〇 | J16: コードマスタ.SQS0070
A17: 4 | B17: 支給年月日 | C17: payment_date | D17: date | F17: not null | G17: 〇
A18: 5 | B18: 締年月日 | C18: shime_date | D18: date | F18: not null | G18: 〇
A19: 6 | B19: 体系コード | C19: taikei_code | D19: varchar | E19: 20 | F19: not null | G19: 〇
A20: 7 | B20: 振込元銀行連番 | C20: remitter_bank_seq | D20: bigint | F20: not null | G20: 〇
A21: 8 | B21: 振込先銀行コード | C21: recipient_bank_code | D21: varchar | E21: 20 | F21: not null
A22: 9 | B22: 振込先支店コード | C22: recipient_branch_code | D22: varchar | E22: 20 | F22: not null
A23: 10 | B23: 振込先口座種別区分 | C23: recipient_account_class_type | D23: tinyint | F23: not null
A24: 11 | B24: 振込先口座番号 | C24: recipient_account_number | D24: bigint
A25: 12 | B25: 振込名義人区分 | C25: remitter_name_type | D25: tinyint | J25: コードマスタ.SQS0071
A26: 13 | B26: 振込先別名義振込氏名 | C26: recipient_different_name_remitter_name | D26: varchar | E26: 255
A27: 14 | B27: 振込先別名義振込カナ | C27: recipient_different_name_remitter_kana | D27: varchar | E27: 255
A28: 15 | B28: 支給額 | C28: payment_amount | D28: bigint
A29: 16 | B29: 振込口座種別 | C29: remitter_account_class | D29: tinyint | F29: not null | G29: 〇
A30: 17 | B30: 住民税納付先コード | C30: resident_tax_payee_code | D30: varchar | E30: 20
A31: 18 | B31: 住民税一括精算額 | C31: resident_tax_bulk_settlement_amount | D31: bigint
A32: 19 | B32: 退職金住民税額 | C32: retirement_pay_resident_tax | D32: bigint
A33: 20 | B33: 退職金市町村民税額 | C33: retirement_pay_city_inhabitant_tax | D33: bigint
A34: 21 | B34: 退職金都道府県民税額 | C34: retirement_pay_state_inhabitant_tax | D34: bigint
A35: 22 | B35: 退職税額 | C35: retirement_tax | D35: bigint
A36: 23 | B36: 作成者 | C36: created_by | D36: bigint | F36: not null
A37: 24 | B37: 作成日時 | C37: created_at | D37: datetime | E37: 6 | F37: not null
A38: 25 | B38: 更新者 | C38: updated_by | D38: bigint | F38: not null
A39: 26 | B39: 更新日時 | C39: updated_at | D39: datetime | E39: 6 | F39: not null

Sheet 月額控除
A1: テーブル情報
B2: システム名 | C2: SOCIA | E2: 作成者 | I2: ITSP | M2: テーブル一覧へ
B3: サブシステム名 | C3: 給与 | E3: 作成日 | I3: 2025-11-28
B4: スキーマ名 | E4: RDBMS | I4: MySQL
B5: 論理テーブル名 | C5: 月額控除 | E5: ENGINE | I5: InnoDB
B6: 物理テーブル名 | C6: month_amount_deduction | E6: CHARSET | I6: utf8mb4
B7: 備考
A12: カラム情報 | L12: 外部キー情報
A13: No | B13: 論理名 | C13: 物理名 | D13: データ型 | E13: Size | F13: Not Null | G13: PK | H13: UK | I13: デフォルト | J13: 備考 | L13: 親テーブル | M13: 参照カラム
A14: 1 | B14: 有効開始年月日 | C14: fromymd | D14: date | F14: not null | G14: 〇
A15: 2 | B15: 有効終了年月日 | C15: toymd | D15: date | F15: not null
A16: 3 | B16: 配偶者控除月額 | C16: spouse_deduction_month_amount | D16: bigint | F16: not null
A17: 4 | B17: 扶養控除月額 | C17: dependent_deduction_month_amount | D17: bigint | F17: not null
A18: 5 | B18: 基礎控除月額 | C18: basic_deduction_month_amount | D18: bigint | F18: not null
A19: 6 | B19: 乙欄扶養控除月額 | C19: otsu_dependent_deduction_monthly | D19: bigint | F19: not null
A20: 7 | B20: 日額表扶養控除月額 | C20: daily_dependent_deduction_monthly | D20: bigint | F20: not null
A21: 8 | B21: 作成者 | C21: created_by | D21: bigint | F21: not null
A22: 9 | B22: 作成日時 | C22: created_at | D22: datetime | E22: 6 | F22: not null
A23: 10 | B23: 更新者 | C23: updated_by | D23: bigint | F23: not null
A24: 11 | B24: 更新日時 | C24: updated_at | D24: datetime | E24: 6 | F24: not null

Sheet 月額算定修正項目
A1: テーブル情報
B2: システム名 | C2: SOCIA | E2: 作成者 | I2: ITSP | M2: テーブル一覧へ
B3: サブシステム名 | C3: 給与 | E3: 作成日 | I3: 2025-11-28
B4: スキーマ名 | E4: RDBMS | I4: MySQL
B5: 論理テーブル名 | C5: 月額算定修正項目 | E5: ENGINE | I5: InnoDB
B6: 物理テーブル名 | C6: monthly_calculate_modify_item | E6: CHARSET | I6: utf8mb4
B7: 備考
B8: 月単位修正項目
A12: カラム情報 | L12: 外部キー情報
A13: No | B13: 論理名 | C13: 物理名 | D13: データ型 | E13: Size | F13: Not Null | G13: PK | H13: UK | I13: デフォルト | J13: 備考 | L13: 親テーブル | M13: 参照カラム
A14: 1 | B14: 社員連番 | C14: syainseq | D14: bigint | F14: not null | G14: 〇
A15: 2 | B15: 年度 | C15: year | D15: smallint | F15: not null | G15: 〇
A16: 3 | B16: 月度 | C16: month | D16: smallint | F16: not null | G16: 〇
A17: 4 | B17: 修正項目区分 | C17: modify_item_type | D17: tinyint | F17: not null | G17: 〇 | J17: コードマスタ.SQS0063
A18: 5 | B18: 修正項目値 | C18: modify_item_setvalue | D18: varchar | E18: 255 | F18: not null
A19: 6 | B19: 作成者 | C19: created_by | D19: bigint | F19: not null
A20: 7 | B20: 作成日時 | C20: created_at | D20: datetime | E20: 6 | F20: not null
A21: 8 | B21: 更新者 | C21: updated_by | D21: bigint | F21: not null
A22: 9 | B22: 更新日時 | C22: updated_at | D22: datetime | E22: 6 | F22: not null

Sheet 月額算定健保
A1: テーブル情報
B2: システム名 | C2: SOCIA | E2: 作成者 | I2: ITSP | M2: テーブル一覧へ
B3: サブシステム名 | C3: 給与 | E3: 作成日 | I3: 2025-11-28
B4: スキーマ名 | E4: RDBMS | I4: MySQL
B5: 論理テーブル名 | C5: 月額算定健保 | E5: ENGINE | I5: InnoDB
B6: 物理テーブル名 | C6: monthly_calculate_healthinsurance | E6: CHARSET | I6: utf8mb4
B7: 備考
A12: カラム情報 | L12: 外部キー情報
A13: No | B13: 論理名 | C13: 物理名 | D13: データ型 | E13: Size | F13: Not Null | G13: PK | H13: UK | I13: デフォルト | J13: 備考 | L13: 親テーブル | M13: 参照カラム
A14: 1 | B14: 社員連番 | C14: syainseq | D14: bigint | F14: not null | G14: 〇
A15: 2 | B15: 算定年度 | C15: calculate_year | D15: smallint | F15: not null | G15: 〇
A16: 3 | B16: 算定月度 | C16: calculate_month | D16: smallint | F16: not null | G16: 〇
A17: 4 | B17: 算定区分 | C17: calculate_type | D17: tinyint | F17: not null | J17: コードマスタ.SQS0026
A18: 5 | B18: 従前報酬月額 | C18: before_reward_month_amount | D18: bigint | J18: 標準報酬月額等級表の上限または下限にわたる等級変更判定時用
A19: 6 | B19: 従前等級 | C19: before_grade | D19: tinyint
A20: 7 | B20: 従前標準報酬月額 | C20: before_standard_reward_month_amount | D20: bigint | J20: 従前利用の場合は必要
A21: 8 | B21: 等級 | C21: grade | D21: smallint | F21: not null
A22: 9 | B22: 標準報酬月額 | C22: standard_reward_month_amount | D22: bigint | F22: not null
A23: 10 | B23: 従前利用区分 | C23: before_use_type | D23: tinyint | I23: 0 | J23: コードマスタ.SQS0065
A24: 11 | B24: 非該当理由 | C24: non_applicability_reason | D24: tinyint | J24: コードマスタ.SQS0066
A25: 12 | B25: 適用年度 | C25: apply_year | D25: smallint | F25: not null
A26: 13 | B26: 適用月度 | C26: apply_month | D26: smallint | F26: not null
A27: 14 | B27: 従前改定年度 | C27: before_revision_year | D27: smallint
A28: 15 | B28: 従前改定月度 | C28: before_revision_month | D28: smallint
A29: 16 | B29: 作成者 | C29: created_by | D29: bigint | F29: not null
A30: 17 | B30: 作成日時 | C30: created_at | D30: datetime | E30: 6 | F30: not null
A31: 18 | B31: 更新者 | C31: updated_by | D31: bigint | F31: not null
A32: 19 | B32: 更新日時 | C32: updated_at | D32: datetime | E32: 6 | F32: not null

Sheet 月額算定厚生年金
A1: テーブル情報
B2: システム名 | C2: SOCIA | E2: 作成者 | I2: ITSP | M2: テーブル一覧へ
B3: サブシステム名 | C3: 給与 | E3: 作成日 | I3: 2025-11-28
B4: スキーマ名 | E4: RDBMS | I4: MySQL
B5: 論理テーブル名 | C5: 月額算定厚生年金 | E5: ENGINE | I5: InnoDB
B6: 物理テーブル名 | C6: monthly_calculate_kosei_pension | E6: CHARSET | I6: utf8mb4
B7: 備考
A12: カラム情報 | L12: 外部キー情報
A13: No | B13: 論理名 | C13: 物理名 | D13: データ型 | E13: Size | F13: Not Null | G13: PK | H13: UK | I13: デフォルト | J13: 備考 | L13: 親テーブル | M13: 参照カラム
A14: 1 | B14: 社員連番 | C14: syainseq | D14: bigint | F14: not null | G14: 〇
A15: 2 | B15: 算定年度 | C15: calculate_year | D15: smallint | F15: not null | G15: 〇
A16: 3 | B16: 算定月度 | C16: calculate_month | D16: smallint | F16: not null | G16: 〇
A17: 4 | B17: 算定区分 | C17: calculate_type | D17: tinyint | F17: not null | J17: 0:非該当 _x000D_ 1:算定者 _x000D_ 2:月変者 _x000D_ 3:変更予定者 _x000D_ 4:戻り算定者 _x000D_ コードマスタ.SQS0026
A18: 5 | B18: 従前報酬月額 | C18: before_reward_month_amount | D18: bigint | J18: 標準報酬月額等級表の上限または下限にわたる等級変更判定時用
A19: 6 | B19: 従前等級 | C19: before_grade | D19: tinyint
A20: 7 | B20: 従前標準報酬月額 | C20: before_standard_reward_month_amount | D20: bigint | J20: 従前利用の場合は必要
A21: 8 | B21: 等級 | C21: grade | D21: smallint | F21: not null
A22: 9 | B22: 標準報酬月額 | C22: standard_reward_month_amount | D22: bigint | F22: not null
A23: 10 | B23: 従前利用区分 | C23: before_use_type | D23: tinyint | I23: 0 | J23: コードマスタ.SQS0065
A24: 11 | B24: 非該当理由 | C24: non_applicability_reason | D24: tinyint | J24: コードマスタ.SQS0066
A25: 12 | B25: 適用年度 | C25: apply_year | D25: smallint | F25: not null
A26: 13 | B26: 適用月度 | C26: apply_month | D26: smallint | F26: not null
A27: 14 | B27: 従前改定年度 | C27: before_revision_year | D27: smallint
A28: 15 | B28: 従前改定月度 | C28: before_revision_month | D28: smallint
A29: 16 | B29: 作成者 | C29: created_by | D29: bigint | F29: not null
A30: 17 | B30: 作成日時 | C30: created_at | D30: datetime | E30: 6 | F30: not null
A31: 18 | B31: 更新者 | C31: updated_by | D31: bigint | F31: not null
A32: 19 | B32: 更新日時 | C32: updated_at | D32: datetime | E32: 6 | F32: not null

Sheet 月額算定用項目
A1: テーブル情報
B2: システム名 | C2: SOCIA | E2: 作成者 | I2: ITSP | M2: テーブル一覧へ
B3: サブシステム名 | C3: 給与 | E3: 作成日 | I3: 2025-11-28
B4: スキーマ名 | E4: RDBMS | I4: MySQL
B5: 論理テーブル名 | C5: 月額算定用項目 | E5: ENGINE | I5: InnoDB
B6: 物理テーブル名 | C6: monthly_calculate_use_item | E6: CHARSET | I6: utf8mb4
B7: 備考
B8: 健保・厚年共通用項目
A12: カラム情報 | L12: 外部キー情報
A13: No | B13: 論理名 | C13: 物理名 | D13: データ型 | E13: Size | F13: Not Null | G13: PK | H13: UK | I13: デフォルト | J13: 備考 | L13: 親テーブル | M13: 参照カラム
A14: 1 | B14: 社員連番 | C14: syainseq | D14: bigint | F14: not null | G14: 〇
A15: 2 | B15: 算定年度 | C15: calculate_year | D15: smallint | F15: not null | G15: 〇
A16: 3 | B16: 算定月度 | C16: calculate_month | D16: smallint | F16: not null | G16: 〇
A17: 4 | B17: パート区分１ | C17: part_type1 | D17: tinyint | F17: not null | J17: コードマスタ.SQS0024
A18: 5 | B18: パート区分２ | C18: part_type2 | D18: tinyint | F18: not null | J18: コードマスタ.SQS0024
A19: 6 | B19: パート区分３ | C19: part_type3 | D19: tinyint | F19: not null | J19: コードマスタ.SQS0024
A20: 7 | B20: 給与区分１ | C20: kyuyo_type1 | D20: tinyint | F20: not null | J20: コードマスタ.SQS0025
A21: 8 | B21: 給与区分２ | C21: kyuyo_type2 | D21: tinyint | F21: not null | J21: コードマスタ.SQS0025
A22: 9 | B22: 給与区分３ | C22: kyuyo_type3 | D22: tinyint | F22: not null | J22: コードマスタ.SQS0025
A23: 10 | B23: 中途入社１ | C23: middle_entrycompany1 | D23: tinyint
A24: 11 | B24: 中途入社２ | C24: middle_entrycompany2 | D24: tinyint
A25: 12 | B25: 中途入社３ | C25: middle_entrycompany3 | D25: tinyint
A26: 13 | B26: 基礎日数１ | C26: basic_day1 | D26: tinyint | F26: not null
A27: 14 | B27: 基礎日数２ | C27: basic_day2 | D27: tinyint | F27: not null
A28: 15 | B28: 基礎日数３ | C28: basic_day3 | D28: tinyint | F28: not null
A29: 16 | B29: 金額1 | C29: amount1 | D29: bigint | F29: not null
A30: 17 | B30: 金額2 | C30: amount2 | D30: bigint | F30: not null
A31: 18 | B31: 金額3 | C31: amount3 | D31: bigint | F31: not null
A32: 19 | B32: 物品１ | C32: goods1 | D32: bigint | F32: not null
A33: 20 | B33: 物品２ | C33: goods2 | D33: bigint | F33: not null
A34: 21 | B34: 物品３ | C34: goods3 | D34: bigint | F34: not null
A35: 22 | B35: 賃金カット月１ | C35: wage_cut_month1 | D35: tinyint
A36: 23 | B36: 賃金カット月２ | C36: wage_cut_month2 | D36: tinyint
A37: 24 | B37: 賃金カット月３ | C37: wage_cut_month3 | D37: tinyint
A38: 25 | B38: 遡及支払額１ | C38: retroactive_payment_amount1 | D38: bigint | F38: not null | J38: 初月の遡及支払額
A39: 26 | B39: 遡及支払額２ | C39: retroactive_payment_amount2 | D39: bigint | F39: not null | J39: 次月の遡及支払額
A40: 27 | B40: 遡及支払額３ | C40: retroactive_payment_amount3 | D40: bigint | F40: not null | J40: 次々月の遡及支払額
A41: 28 | B41: 遡及額１ | C41: retroactive_amount1 | D41: bigint | F41: not null | J41: 初月に対する遡及額
A42: 29 | B42: 遡及額２ | C42: retroactive_amount2 | D42: bigint | F42: not null | J42: 次月に対する遡及額
A43: 30 | B43: 昇降給差額(印字用) | C43: updownsalary_difference | D43: bigint | F43: not null | J43: 基準内賃金(初月‐(初月-1))
A44: 31 | B44: 基準内賃金差額１ | C44: standard_wage_difference1 | D44: bigint | J44: 初月－初月の前月_x000D_ ※どっちか「固定的賃金」の0の場合、「0」とする
A45: 32 | B45: 基準内賃金差額２ | C45: standard_wage_difference2 | D45: bigint | J45: 次月－初月_x000D_ ※どっちか「固定的賃金」の0の場合、「0」とする
A46: 33 | B46: 基準内賃金差額３ | C46: standard_wage_difference3 | D46: bigint | J46: 次々月－次月_x000D_ ※どっちか「固定的賃金」の0の場合、「0」とする
A47: 34 | B47: 単純合計額 | C47: simple_total_amount | D47: bigint | F47: not null
A48: 35 | B48: 単純平均額 | C48: simple_average_amount | D48: bigint | F48: not null
A49: 36 | B49: 修正合計額 | C49: modify_total_amount | D49: bigint | F49: not null
A50: 37 | B50: 修正平均額 | C50: modify_average_amount | D50: bigint | F50: not null
A51: 38 | B51: 変更予定者未使用フラグ | C51: change_predeterminer_unuse_flag | D51: boolean
A52: 39 | B52: 中途入社対象フラグ | C52: middle_entrycompany_target_flag | D52: boolean | F52: not null | J52: 0：対象とする_x000D_ 1：対象としない
A53: 40 | B53: 作成者 | C53: created_by | D53: bigint | F53: not null
A54: 41 | B54: 作成日時 | C54: created_at | D54: datetime | E54: 6 | F54: not null
A55: 42 | B55: 更新者 | C55: updated_by | D55: bigint | F55: not null
A56: 43 | B56: 更新日時 | C56: updated_at | D56: datetime | E56: 6 | F56: not null

Sheet 月額算定結果メンテナンス
A1: テーブル情報
B2: システム名 | C2: SOCIA | E2: 作成者 | I2: ITSP | M2: テーブル一覧へ
B3: サブシステム名 | C3: 給与 | E3: 作成日 | I3: 2025-11-28
B4: スキーマ名 | E4: RDBMS | I4: MySQL
B5: 論理テーブル名 | C5: 月額算定結果メンテナンス | E5: ENGINE | I5: InnoDB
B6: 物理テーブル名 | C6: monthly_calculate_result_maintenance | E6: CHARSET | I6: utf8mb4
B7: 備考
B8: 算定単位修正項目
A12: カラム情報 | L12: 外部キー情報
A13: No | B13: 論理名 | C13: 物理名 | D13: データ型 | E13: Size | F13: Not Null | G13: PK | H13: UK | I13: デフォルト | J13: 備考 | L13: 親テーブル | M13: 参照カラム
A14: 1 | B14: 社員連番 | C14: syainseq | D14: bigint | F14: not null | G14: 〇
A15: 2 | B15: 算定年度 | C15: calculate_year | D15: smallint | F15: not null | G15: 〇
A16: 3 | B16: 算定月度 | C16: calculate_month | D16: smallint | F16: not null | G16: 〇
A17: 4 | B17: 算定結果項目コード | C17: calculate_result_item_code | D17: varchar | E17: 20 | F17: not null | G17: 〇 | J17: コードマスタ.SQS0064
A18: 5 | B18: 算定結果項目値 | C18: calculate_result_item_setvalue | D18: bigint | F18: not null
A19: 6 | B19: 作成者 | C19: created_by | D19: bigint | F19: not null
A20: 7 | B20: 作成日時 | C20: created_at | D20: datetime | E20: 6 | F20: not null
A21: 8 | B21: 更新者 | C21: updated_by | D21: bigint | F21: not null
A22: 9 | B22: 更新日時 | C22: updated_at | D22: datetime | E22: 6 | F22: not null

Sheet 確定労働保険料
A1: テーブル情報
B2: システム名 | C2: SOCIA | E2: 作成者 | I2: ITSP | M2: テーブル一覧へ
B3: サブシステム名 | C3: 給与 | E3: 作成日 | I3: 2025-11-28
B4: スキーマ名 | E4: RDBMS | I4: MySQL
B5: 論理テーブル名 | C5: 確定労働保険料 | E5: ENGINE | I5: InnoDB
B6: 物理テーブル名 | C6: confirm_labor_insurance_fee | E6: CHARSET | I6: utf8mb4
B7: 備考
A12: カラム情報 | L12: 外部キー情報
A13: No | B13: 論理名 | C13: 物理名 | D13: データ型 | E13: Size | F13: Not Null | G13: PK | H13: UK | I13: デフォルト | J13: 備考 | L13: 親テーブル | M13: 参照カラム
A14: 1 | B14: 社員連番 | C14: syainseq | D14: bigint | F14: not null | G14: 〇
A15: 2 | B15: 年度 | C15: year | D15: smallint | F15: not null | J15: （基準年月日の年）
A16: 3 | B16: 月度 | C16: month | D16: smallint | F16: not null | J16: （基準年月日の月）
A17: 4 | B17: 支給区分 | C17: payment_type | D17: tinyint | F17: not null | G17: 〇 | J17: コードマスタ.SQS0013
A18: 5 | B18: 支給年月日 | C18: payment_date | D18: date | F18: not null | G18: 〇 | J18: 支給区分は臨時給与、賞与の場合は必須
A19: 6 | B19: 締年月日 | C19: shime_date | D19: date | F19: not null | G19: 〇 | J19: 支給区分は給与の場合必須
A20: 7 | B20: 会社コード | C20: kaisyacd | D20: varchar | E20: 20 | F20: not null
A21: 8 | B21: 届出コード | C21: submission_code | D21: varchar | E21: 20 | F21: not null
A22: 9 | B22: 所属コード | C22: belong_code | D22: varchar | E22: 20
A23: 10 | B23: 職種 | C23: job_type | D23: varchar | E23: 20 | F23: not null | J23: (労災保険区分)_x000D_ 0:対象外_x000D_ その他:QTISROSAIRITU.SYOKUSYU
A24: 11 | B24: 雇用保険区分 | C24: employment_insurance_type | D24: tinyint | F24: not null | J24: コードマスタ.SQS0067
A25: 12 | B25: 雇用保険対象額 | C25: employment_insurance_target_amount | D25: bigint | J25: 合計項目：213
A26: 13 | B26: 雇用保険個人負担額 | C26: employment_insurance_personal_burden_amount | D26: bigint | J26: 合計項目：217
A27: 14 | B27: 雇用保険合計額 | C27: employment_insurance_total_amount | D27: bigint | J27: 合計項目：217 ＋ 合計項目：284
A28: 15 | B28: 労災保険対象額 | C28: rosai_insurance_target_amount | D28: bigint | J28: 合計項目：212
A29: 16 | B29: 労災保険料額 | C29: rosai_insurance_amount | D29: bigint | J29: 合計項目：285
A30: 17 | B30: 作成者 | C30: created_by | D30: bigint | F30: not null
A31: 18 | B31: 作成日時 | C31: created_at | D31: datetime | E31: 6 | F31: not null
A32: 19 | B32: 更新者 | C32: updated_by | D32: bigint | F32: not null
A33: 20 | B33: 更新日時 | C33: updated_at | D33: datetime | E33: 6 | F33: not null

Sheet 社会保険前職
A1: テーブル情報
B2: システム名 | C2: SOCIA | E2: 作成者 | I2: ITSP | M2: テーブル一覧へ
B3: サブシステム名 | C3: 給与 | E3: 作成日 | I3: 2025-11-28
B4: スキーマ名 | E4: RDBMS | I4: MySQL
B5: 論理テーブル名 | C5: 社会保険前職 | E5: ENGINE | I5: InnoDB
B6: 物理テーブル名 | C6: syaho_previous_job | E6: CHARSET | I6: utf8mb4
B7: 備考
A12: カラム情報 | L12: 外部キー情報
A13: No | B13: 論理名 | C13: 物理名 | D13: データ型 | E13: Size | F13: Not Null | G13: PK | H13: UK | I13: デフォルト | J13: 備考 | L13: 親テーブル | M13: 参照カラム
A14: 1 | B14: 社員連番 | C14: syainseq | D14: bigint | F14: not null | G14: 〇
A15: 2 | B15: データ連番 | C15: dataseq | D15: int | F15: not null | G15: 〇
A16: 3 | B16: 有効開始年月日 | C16: fromymd | D16: date | F16: not null | G16: 〇
A17: 4 | B17: 有効終了年月日 | C17: toymd | D17: date | F17: not null | G17: 〇
A18: 5 | B18: 表示順序 | C18: dsp_order | D18: bigint
A19: 6 | B19: 前職賞与支払年月日 | C19: previous_job_syoyo_payment_date | D19: date
A20: 7 | B20: 前職標準賞与額 | C20: previous_job_standard_syoyo_amount | D20: bigint
A21: 8 | B21: 予備２ | C21: reserve2 | D21: bigint
A22: 9 | B22: 予備３ | C22: reserve3 | D22: bigint
A23: 10 | B23: 予備４ | C23: reserve4 | D23: bigint
A24: 11 | B24: 予備５ | C24: reserve5 | D24: bigint
A25: 12 | B25: 備考 | C25: note | D25: text
A26: 13 | B26: 作成者 | C26: created_by | D26: bigint | F26: not null
A27: 14 | B27: 作成日時 | C27: created_at | D27: datetime | E27: 6 | F27: not null
A28: 15 | B28: 更新者 | C28: updated_by | D28: bigint | F28: not null
A29: 16 | B29: 更新日時 | C29: updated_at | D29: datetime | E29: 6 | F29: not null

Sheet 社会保険徴収情報
A1: テーブル情報
B2: システム名 | C2: SOCIA | E2: 作成者 | I2: ITSP | M2: テーブル一覧へ
B3: サブシステム名 | C3: 給与 | E3: 作成日 | I3: 2025-11-28
B4: スキーマ名 | E4: RDBMS | I4: MySQL
B5: 論理テーブル名 | C5: 社会保険徴収情報 | E5: ENGINE | I5: InnoDB
B6: 物理テーブル名 | C6: syaho_collection_info | E6: CHARSET | I6: utf8mb4
B7: 備考
A12: カラム情報 | L12: 外部キー情報
A13: No | B13: 論理名 | C13: 物理名 | D13: データ型 | E13: Size | F13: Not Null | G13: PK | H13: UK | I13: デフォルト | J13: 備考 | L13: 親テーブル | M13: 参照カラム
A14: 1 | B14: 会社コード | C14: kaisyacd | D14: varchar | E14: 20 | F14: not null | G14: 〇
A15: 2 | B15: 届出コード | C15: submission_code | D15: varchar | E15: 20 | F15: not null | G15: 〇
A16: 3 | B16: 有効開始年月日 | C16: fromymd | D16: date | F16: not null | G16: 〇
A17: 4 | B17: 有効終了年月日 | C17: toymd | D17: date
A18: 5 | B18: 徴収区分 | C18: collection_type | D18: tinyint
A19: 6 | B19: 作成者 | C19: created_by | D19: bigint | F19: not null
A20: 7 | B20: 作成日時 | C20: created_at | D20: datetime | E20: 6 | F20: not null
A21: 8 | B21: 更新者 | C21: updated_by | D21: bigint | F21: not null
A22: 9 | B22: 更新日時 | C22: updated_at | D22: datetime | E22: 6 | F22: not null

Sheet 社員固定項目
A1: テーブル情報
B2: システム名 | C2: SOCIA | E2: 作成者 | I2: ITSP | M2: テーブル一覧へ
B3: サブシステム名 | C3: 給与 | E3: 作成日 | I3: 2025-11-28
B4: スキーマ名 | E4: RDBMS | I4: MySQL
B5: 論理テーブル名 | C5: 社員固定項目 | E5: ENGINE | I5: InnoDB
B6: 物理テーブル名 | C6: syain_fixeditem | E6: CHARSET | I6: utf8mb4
B7: 備考
A12: カラム情報 | L12: 外部キー情報
A13: No | B13: 論理名 | C13: 物理名 | D13: データ型 | E13: Size | F13: Not Null | G13: PK | H13: UK | I13: デフォルト | J13: 備考 | L13: 親テーブル | M13: 参照カラム
A14: 1 | B14: 社員連番 | C14: syainseq | D14: bigint | F14: not null | G14: 〇
A15: 2 | B15: 項目コード | C15: item_code | D15: varchar | E15: 20 | F15: not null | G15: 〇
A16: 3 | B16: 有効開始年月日 | C16: fromymd | D16: date | F16: not null | G16: 〇
A17: 4 | B17: 有効終了年月日 | C17: toymd | D17: date
A18: 5 | B18: 改定年月 | C18: revision_ym | D18: varchar | E18: 6
A19: 6 | B19: 適用年月 | C19: apply_ym | D19: varchar | E19: 6
A20: 7 | B20: 設定値 | C20: setvalue | D20: bigint | J20: varchar(255)にしなく、データ型固定
A21: 8 | B21: 作成者 | C21: created_by | D21: bigint | F21: not null
A22: 9 | B22: 作成日時 | C22: created_at | D22: datetime | E22: 6 | F22: not null
A23: 10 | B23: 更新者 | C23: updated_by | D23: bigint | F23: not null
A24: 11 | B24: 更新日時 | C24: updated_at | D24: datetime | E24: 6 | F24: not null

Sheet 社員損保保険料
A1: テーブル情報
B2: システム名 | C2: SOCIA | E2: 作成者 | I2: ITSP | M2: テーブル一覧へ
B3: サブシステム名 | C3: 給与 | E3: 作成日 | I3: 2025-11-28
B4: スキーマ名 | E4: RDBMS | I4: MySQL
B5: 論理テーブル名 | C5: 社員損保保険料 | E5: ENGINE | I5: InnoDB
B6: 物理テーブル名 | C6: syain_casualty_insurance_fee | E6: CHARSET | I6: utf8mb4
B7: 備考
A12: カラム情報 | L12: 外部キー情報
A13: No | B13: 論理名 | C13: 物理名 | D13: データ型 | E13: Size | F13: Not Null | G13: PK | H13: UK | I13: デフォルト | J13: 備考 | L13: 親テーブル | M13: 参照カラム
A14: 1 | B14: 社員連番 | C14: syainseq | D14: bigint | F14: not null | G14: 〇
A15: 2 | B15: 家族区分 | C15: family_type | D15: tinyint | F15: not null | G15: 〇
A16: 3 | B16: 保険区分 | C16: insurance_type | D16: tinyint | F16: not null | G16: 〇
A17: 4 | B17: 保険会社コード | C17: insurance_kaisya_code | D17: varchar | E17: 20 | F17: not null | G17: 〇
A18: 5 | B18: 支給区分 | C18: payment_type | D18: tinyint | F18: not null | G18: 〇
A19: 6 | B19: 証券記号番号 | C19: securities_mark_number | D19: varchar | E19: 13 | F19: not null | G19: 〇
A20: 7 | B20: 控除年 | C20: deduction_year | D20: smallint | F20: not null | G20: 〇
A21: 8 | B21: 控除月 | C21: deduction_month | D21: smallint | F21: not null | G21: 〇
A22: 9 | B22: 返還区分 | C22: return_type | D22: tinyint | F22: not null | G22: 〇
A23: 10 | B23: データ種類 | C23: data_class | D23: varchar | E23: 1
A24: 11 | B24: 保険種類コード | C24: insurance_class_code | D24: varchar | E24: 20
A25: 12 | B25: 払込回目 | C25: payment_times | D25: varchar | E25: 20
A26: 13 | B26: 始期年月日 | C26: fromymd | D26: date
A27: 14 | B27: 終期年月日 | C27: toymd | D27: date
A28: 15 | B28: 控除開始年月 | C28: deduction_fromym | D28: varchar | E28: 6
A29: 16 | B29: 控除終了年月 | C29: deduction_toym | D29: varchar | E29: 6
A30: 17 | B30: 控除保険料 | C30: deduction_insurance | D30: varchar | E30: 7
A31: 18 | B31: 団体集金事務費 | C31: group_money_office_expenses | D31: varchar | E31: 6
A32: 19 | B32: 正味精算額 | C32: net_settlement_amount | D32: varchar | E32: 7
A33: 20 | B33: 引去金額 | C33: evacuation_amount | D33: varchar | E33: 7
A34: 21 | B34: 契約者氏名 | C34: subscriber_name | D34: varchar | E34: 15
A35: 22 | B35: 控除結果 | C35: deduction_result | D35: varchar | E35: 1
A36: 23 | B36: 内訳コード | C36: breakdown_code | D36: varchar | E36: 20
A37: 24 | B37: 所属コード | C37: belong_code | D37: varchar | E37: 20
A38: 25 | B38: 団体コード | C38: group_code | D38: varchar | E38: 20
A39: 26 | B39: 社員配当金 | C39: syain_dividends | D39: varchar | E39: 7
A40: 27 | B40: 所属コード変更フラグ | C40: belong_code_change_flag | D40: boolean
A41: 28 | B41: 契約者氏名変更フラグ | C41: subscriber_name_change_flag | D41: boolean
A42: 29 | B42: 幹事会社コード | C42: organizer_kaisyacd | D42: varchar | E42: 20
A43: 30 | B43: 任意使用欄 | C43: option_use_ran | D43: varchar | E43: 15
A44: 31 | B44: 損保独自欄 | C44: casualty_insurance_proprietary_ran | D44: varchar | E44: 7
A45: 32 | B45: 従業員番号 | C45: employees_number | D45: varchar | E45: 12
A46: 33 | B46: 取込エラー区分 | C46: import_error_type | D46: tinyint
A47: 34 | B47: ダミーデータ１ | C47: dummy_data1 | D47: varchar | E47: 1
A48: 35 | B48: ダミーデータ２ | C48: dummy_data2 | D48: varchar | E48: 20
A49: 36 | B49: 作成者 | C49: created_by | D49: bigint | F49: not null
A50: 37 | B50: 作成日時 | C50: created_at | D50: datetime | E50: 6 | F50: not null
A51: 38 | B51: 更新者 | C51: updated_by | D51: bigint | F51: not null
A52: 39 | B52: 更新日時 | C52: updated_at | D52: datetime | E52: 6 | F52: not null

Sheet 社員生保保険料
A1: テーブル情報
B2: システム名 | C2: SOCIA | E2: 作成者 | I2: ITSP | M2: テーブル一覧へ
B3: サブシステム名 | C3: 給与 | E3: 作成日 | I3: 2025-11-28
B4: スキーマ名 | E4: RDBMS | I4: MySQL
B5: 論理テーブル名 | C5: 社員生保保険料 | E5: ENGINE | I5: InnoDB
B6: 物理テーブル名 | C6: syain_life_insurance_fee | E6: CHARSET | I6: utf8mb4
B7: 備考
A12: カラム情報 | L12: 外部キー情報
A13: No | B13: 論理名 | C13: 物理名 | D13: データ型 | E13: Size | F13: Not Null | G13: PK | H13: UK | I13: デフォルト | J13: 備考 | L13: 親テーブル | M13: 参照カラム
A14: 1 | B14: 社員連番 | C14: syainseq | D14: bigint | F14: not null | G14: 〇
A15: 2 | B15: 家族区分 | C15: family_type | D15: tinyint | F15: not null | G15: 〇
A16: 3 | B16: 保険区分 | C16: insurance_type | D16: tinyint | F16: not null | G16: 〇
A17: 4 | B17: 保険会社コード | C17: insurance_kaisya_code | D17: varchar | E17: 20 | F17: not null | G17: 〇
A18: 5 | B18: 支給区分 | C18: payment_type | D18: tinyint | F18: not null | G18: 〇
A19: 6 | B19: 証券記号番号 | C19: securities_mark_number | D19: varchar | E19: 13 | F19: not null | G19: 〇
A20: 7 | B20: 案内年 | C20: guide_year | D20: smallint | F20: not null | G20: 〇
A21: 8 | B21: 案内月 | C21: guide_month | D21: smallint | F21: not null | G21: 〇
A22: 9 | B22: 控除年 | C22: deduction_year | D22: smallint | F22: not null | G22: 〇
A23: 10 | B23: 控除月 | C23: deduction_month | D23: smallint | F23: not null | G23: 〇
A24: 11 | B24: 返還区分 | C24: return_type | D24: tinyint | F24: not null | G24: 〇
A25: 12 | B25: 請求金額 | C25: request_amount | D25: varchar | E25: 7
A26: 13 | B26: 引去金額 | C26: evacuation_amount | D26: varchar | E26: 7
A27: 14 | B27: 併徴区分 | C27: summons_type | D27: tinyint
A28: 15 | B28: 新規・変更区分 | C28: new_change_type | D28: tinyint
A29: 16 | B29: 引去結果コード | C29: evacuation_result_code | D29: varchar | E29: 20
A30: 17 | B30: 未入金事由コード | C30: unpaid_reason_code | D30: varchar | E30: 20
A31: 18 | B31: 所属変更マーク | C31: belong_change_mark | D31: varchar | E31: 1
A32: 19 | B32: ボーナス払区分 | C32: bonus_pay_type | D32: tinyint
A33: 20 | B33: 生保任意使用欄 | C33: life_insurance_option_use_ran | D33: varchar | E33: 15
A34: 21 | B34: 所属コード | C34: belong_code | D34: varchar | E34: 20
A35: 22 | B35: 契約者生年月日 | C35: subscriber_birth_date | D35: date
A36: 23 | B36: 契約者名 | C36: subscriber_name | D36: varchar | E36: 12
A37: 24 | B37: 氏名コード | C37: name_code | D37: varchar | E37: 20
A38: 25 | B38: 団体コード | C38: group_code | D38: varchar | E38: 20
A39: 26 | B39: 取込エラー区分 | C39: import_error_type | D39: tinyint
A40: 27 | B40: ダミーデータ１ | C40: dummy_data1 | D40: varchar | E40: 1
A41: 28 | B41: ダミーデータ２ | C41: dummy_data2 | D41: varchar | E41: 20
A42: 29 | B42: 作成者 | C42: created_by | D42: bigint | F42: not null
A43: 30 | B43: 作成日時 | C43: created_at | D43: datetime | E43: 6 | F43: not null
A44: 31 | B44: 更新者 | C44: updated_by | D44: bigint | F44: not null
A45: 32 | B45: 更新日時 | C45: updated_at | D45: datetime | E45: 6 | F45: not null

Sheet 社員税法
A1: テーブル情報
B2: システム名 | C2: SOCIA | E2: 作成者 | I2: ITSP | M2: テーブル一覧へ
B3: サブシステム名 | C3: 給与 | E3: 作成日 | I3: 2025-11-28
B4: スキーマ名 | E4: RDBMS | I4: MySQL
B5: 論理テーブル名 | C5: 社員税法 | E5: ENGINE | I5: InnoDB
B6: 物理テーブル名 | C6: syain_tax_law | E6: CHARSET | I6: utf8mb4
B7: 備考
B8: 「v社員税法」テーブルの給与管理部分。TODO：システム予約項目が完全に決まってから可能限り精査する
A12: カラム情報 | L12: 外部キー情報
A13: No | B13: 論理名 | C13: 物理名 | D13: データ型 | E13: Size | F13: Not Null | G13: PK | H13: UK | I13: デフォルト | J13: 備考 | L13: 親テーブル | M13: 参照カラム
A14: 1 | B14: 社員連番 | C14: syainseq | D14: bigint | F14: not null | G14: 〇
A15: 2 | B15: 基準年月日 | C15: standard_date | D15: date | F15: not null | G15: 〇
A16: 3 | B16: 未成年者区分 | C16: minor_type | D16: tinyint
A17: 4 | B17: 配偶者区分 | C17: spouse_type | D17: tinyint
A18: 5 | B18: 親族扶養区分 | C18: relative_dependent_type | D18: tinyint
A19: 6 | B19: 親族一般扶養 | C19: relative_general_dependent | D19: tinyint
A20: 7 | B20: 親族特定扶養 | C20: relative_specific_dependent | D20: tinyint
A21: 8 | B21: 親族年少扶養 | C21: relative_young_dependent | D21: tinyint
A22: 9 | B22: 親族同居老親扶養 | C22: relative_cohabitation_elderly_relative | D22: tinyint
A23: 10 | B23: 親族老人扶養 | C23: relative_elderly_dependent | D23: tinyint
A24: 11 | B24: 親族一般障害 | C24: relative_general_disability | D24: tinyint
A25: 12 | B25: 親族特別障害 | C25: relative_special_disability | D25: tinyint
A26: 13 | B26: 親族同居特別障害一般扶養 | C26: relative_cohabitation_special_disability_general_dependent | D26: tinyint
A27: 14 | B27: 親族同居特別障害特定扶養 | C27: relative_cohabitation_special_disability_specific_dependent | D27: tinyint
... A30: 17 | B30: 親族同居特別障害老人扶養 | C30: relative_cohabitation_special_disability_elderly_dependent | D30: tinyint
A31: 18 | B31: 作成者 | C31: created_by | D31: bigint | F31: not null
A32: 19 | B32: 作成日時 | C32: created_at | D32: datetime | E32: 6 | F32: not null
A33: 20 | B33: 更新者 | C33: updated_by | D33: bigint | F33: not null
A34: 21 | B34: 更新日時 | C34: updated_at | D34: datetime | E34: 6 | F34: not null

Sheet 社員配当金
A1: テーブル情報
B2: システム名 | C2: SOCIA | E2: 作成者 | I2: ITSP | M2: テーブル一覧へ
B3: サブシステム名 | C3: 給与 | E3: 作成日 | I3: 2025-11-28
B4: スキーマ名 | E4: RDBMS | I4: MySQL
B5: 論理テーブル名 | C5: 社員配当金 | E5: ENGINE | I5: InnoDB
B6: 物理テーブル名 | C6: syain_dividends | E6: CHARSET | I6: utf8mb4
B7: 備考
A12: カラム情報 | L12: 外部キー情報
A13: No | B13: 論理名 | C13: 物理名 | D13: データ型 | E13: Size | F13: Not Null | G13: PK | H13: UK | I13: デフォルト | J13: 備考 | L13: 親テーブル | M13: 参照カラム
A14: 1 | B14: 社員連番 | C14: syainseq | D14: bigint | F14: not null | G14: 〇
A15: 2 | B15: 家族区分 | C15: family_type | D15: tinyint | F15: not null | G15: 〇
A16: 3 | B16: 保険区分 | C16: insurance_type | D16: tinyint | F16: not null | G16: 〇
A17: 4 | B17: 保険会社コード | C17: insurance_kaisya_code | D17: varchar | E17: 20 | F17: not null | G17: 〇
A18: 5 | B18: 支給区分 | C18: payment_type | D18: tinyint | F18: not null | G18: 〇
A19: 6 | B19: 証券記号番号 | C19: securities_mark_number | D19: varchar | E19: 13 | F19: not null | G19: 〇
A20: 7 | B20: 契約年月日 | C20: contract_date | D20: date
A21: 8 | B21: 配当支払方法 | C21: dividend_payment_method | D21: tinyint
A22: 9 | B22: 当年度配当金 | C22: currentyear_dividends | D22: bigint
A23: 10 | B23: 累計配当金 | C23: sum_dividends | D23: bigint
A24: 11 | B24: 年調対象配当金 | C24: nencho_target_dividends | D24: bigint
A25: 12 | B25: 生保任意使用欄 | C25: life_insurance_option_use_ran | D25: varchar | E25: 15
A26: 13 | B26: 所属コード | C26: belong_code | D26: varchar | E26: 20
A27: 14 | B27: ボーナス払区分 | C27: bonus_pay_type | D27: tinyint
A28: 15 | B28: 氏名コード | C28: name_code | D28: varchar | E28: 20
A29: 16 | B29: 団体コード | C29: group_code | D29: varchar | E29: 20
A30: 17 | B30: 取込エラー区分 | C30: import_error_type | D30: tinyint
A31: 18 | B31: ダミーデータ１ | C31: dummy_data1 | D31: varchar | E31: 1
A32: 19 | B32: ダミーデータ２ | C32: dummy_data2 | D32: varchar | E32: 20
A33: 20 | B33: 作成者 | C33: created_by | D33: bigint | F33: not null
A34: 21 | B34: 作成日時 | C34: created_at | D34: datetime | E34: 6 | F34: not null
A35: 22 | B35: 更新者 | C35: updated_by | D35: bigint | F35: not null
A36: 23 | B36: 更新日時 | C36: updated_at | D36: datetime | E36: 6 | F36: not null

Sheet 給与抽出
A1: テーブル情報
B2: システム名 | C2: SOCIA | E2: 作成者 | I2: ITSP | M2: テーブル一覧へ
B3: サブシステム名 | C3: 給与 | E3: 作成日 | I3: 2025-11-28
B4: スキーマ名 | E4: RDBMS | I4: MySQL
B5: 論理テーブル名 | C5: 給与抽出 | E5: ENGINE | I5: InnoDB
B6: 物理テーブル名 | C6: kyuyo_select | E6: CHARSET | I6: utf8mb4
B7: 備考
A12: カラム情報 | L12: 外部キー情報
A13: No | B13: 論理名 | C13: 物理名 | D13: データ型 | E13: Size | F13: Not Null | G13: PK | H13: UK | I13: デフォルト | J13: 備考 | L13: 親テーブル | M13: 参照カラム
A14: 1 | B14: 会社コード | C14: kaisyacd | D14: varchar | E14: 20 | F14: not null | G14: 〇
A15: 2 | B15: 年度 | C15: year | D15: smallint | F15: not null | G15: 〇
A16: 3 | B16: 月度 | C16: month | D16: smallint | F16: not null | G16: 〇
A17: 4 | B17: 締日 | C17: shime_day | D17: tinyint | F17: not null | G17: 〇 | J17: 99:末日
A18: 5 | B18: 支給月区分 | C18: payment_month_type | D18: tinyint | F18: not null | G18: 〇 | J18: コードマスタ.SQS0012
A19: 6 | B19: 支給日 | C19: payment_day | D19: tinyint | F19: not null | G19: 〇 | J19: 99:末日
A20: 7 | B20: 支給年月日 | C20: payment_date | D20: date
A21: 8 | B21: 締年月日 | C21: shime_date | D21: date
A22: 9 | B22: 確定区分 | C22: confirm_type | D22: tinyint | F22: not null | J22: コードマスタ.SQS0030
A23: 10 | B23: 作成者 | C23: created_by | D23: bigint | F23: not null
A24: 11 | B24: 作成日時 | C24: created_at | D24: datetime | E24: 6 | F24: not null
A25: 12 | B25: 更新者 | C25: updated_by | D25: bigint | F25: not null
A26: 13 | B26: 更新日時 | C26: updated_at | D26: datetime | E26: 6 | F26: not null

Sheet 給与支給
A1: テーブル情報
B2: システム名 | C2: SOCIA | E2: 作成者 | I2: ITSP | M2: テーブル一覧へ
B3: サブシステム名 | C3: 給与 | E3: 作成日 | I3: 2025-11-28
B4: スキーマ名 | E4: RDBMS | I4: MySQL
B5: 論理テーブル名 | C5: 給与支給 | E5: ENGINE | I5: InnoDB
B6: 物理テーブル名 | C6: kyuyo_payment | E6: CHARSET | I6: utf8mb4
B7: 備考
A12: カラム情報 | L12: 外部キー情報
A13: No | B13: 論理名 | C13: 物理名 | D13: データ型 | E13: Size | F13: Not Null | G13: PK | H13: UK | I13: デフォルト | J13: 備考 | L13: 親テーブル | M13: 参照カラム
A14: 1 | B14: 社員連番 | C14: syainseq | D14: bigint | F14: not null | G14: 〇
A15: 2 | B15: 締年月日 | C15: shime_date | D15: date | F15: not null | G15: 〇
A16: 3 | B16: 支給年月日 | C16: payment_date | D16: date | F16: not null | G16: 〇
A17: 4 | B17: 体系項目コード | C17: taikei_item_code | D17: varchar | E17: 20 | F17: not null | G17: 〇
A18: 5 | B18: 項目値 | C18: item_setvalue | D18: varchar | E18: 255 | F18: not null
A19: 6 | B19: 作成者 | C19: created_by | D19: bigint | F19: not null
A20: 7 | B20: 作成日時 | C20: created_at | D20: datetime | E20: 6 | F20: not null
A21: 8 | B21: 更新者 | C21: updated_by | D21: bigint | F21: not null
A22: 9 | B22: 更新日時 | C22: updated_at | D22: datetime | E22: 6 | F22: not null

Sheet 給与支給基本
A1: テーブル情報
B2: システム名 | C2: SOCIA | E2: 作成者 | I2: ITSP | M2: テーブル一覧へ
B3: サブシステム名 | C3: 給与 | E3: 作成日 | I3: 2025-11-28
B4: スキーマ名 | E4: RDBMS | I4: MySQL
B5: 論理テーブル名 | C5: 給与支給基本 | E5: ENGINE | I5: InnoDB
B6: 物理テーブル名 | C6: kyuyo_payment_basic | E6: CHARSET | I6: utf8mb4
B7: 備考
A12: カラム情報 | L12: 外部キー情報
A13: No | B13: 論理名 | C13: 物理名 | D13: データ型 | E13: Size | F13: Not Null | G13: PK | H13: UK | I13: デフォルト | J13: 備考 | L13: 親テーブル | M13: 参照カラム
A14: 1 | B14: 社員連番 | C14: syainseq | D14: bigint | F14: not null | G14: 〇
A15: 2 | B15: 締年月日 | C15: shime_date | D15: date | F15: not null | G15: 〇
A16: 3 | B16: 支給年月日 | C16: payment_date | D16: date | F16: not null | G16: 〇
A17: 4 | B17: 体系コード | C17: taikei_code | D17: varchar | E17: 20
A18: 5 | B18: 課税区分 | C18: tax_type | D18: tinyint | F18: not null | J18: コードマスタ.SQS0003
A19: 6 | B19: 作成者 | C19: created_by | D19: bigint | F19: not null
A20: 7 | B20: 作成日時 | C20: created_at | D20: datetime | E20: 6 | F20: not null
A21: 8 | B21: 更新者 | C21: updated_by | D21: bigint | F21: not null
A22: 9 | B22: 更新日時 | C22: updated_at | D22: datetime | E22: 6 | F22: not null

Sheet 給与支給調整
A1: テーブル情報
B2: システム名 | C2: SOCIA | E2: 作成者 | I2: ITSP | M2: テーブル一覧へ
B3: サブシステム名 | C3: 給与 | E3: 作成日 | I3: 2025-11-28
B4: スキーマ名 | E4: RDBMS | I4: MySQL
B5: 論理テーブル名 | C5: 給与支給調整 | E5: ENGINE | I5: InnoDB
B6: 物理テーブル名 | C6: kyuyo_payment_adjustment | E6: CHARSET | I6: utf8mb4
B7: 備考
A12: カラム情報 | L12: 外部キー情報
A13: No | B13: 論理名 | C13: 物理名 | D13: データ型 | E13: Size | F13: Not Null | G13: PK | H13: UK | I13: デフォルト | J13: 備考 | L13: 親テーブル | M13: 参照カラム
A14: 1 | B14: 社員連番 | C14: syainseq | D14: bigint | F14: not null | G14: 〇
A15: 2 | B15: 締年月日 | C15: shime_date | D15: date | F15: not null | G15: 〇
A16: 3 | B16: 支給年月日 | C16: payment_date | D16: date | F16: not null | G16: 〇
A17: 4 | B17: 体系項目コード | C17: taikei_item_code | D17: varchar | E17: 20 | F17: not null | G17: 〇
A18: 5 | B18: 調整値 | C18: adjustment_setvalue | D18: bigint | F18: not null
A19: 6 | B19: 自動計算値 | C19: auto_equation_setvalue | D19: bigint
A20: 7 | B20: 作成者 | C20: created_by | D20: bigint | F20: not null
A21: 8 | B21: 作成日時 | C21: created_at | D21: datetime | E21: 6 | F21: not null
A22: 9 | B22: 更新者 | C22: updated_by | D22: bigint | F22: not null
A23: 10 | B23: 更新日時 | C23: updated_at | D23: datetime | E23: 6 | F23: not null

Sheet 給与明細備考
A1: テーブル情報
B2: システム名 | C2: SOCIA | E2: 作成者 | I2: ITSP | M2: テーブル一覧へ
B3: サブシステム名 | C3: 給与 | E3: 作成日 | I3: 2025-11-28
B4: スキーマ名 | E4: RDBMS | I4: MySQL
B5: 論理テーブル名 | C5: 給与明細備考 | E5: ENGINE | I5: InnoDB
B6: 物理テーブル名 | C6: kyuyo_detail_note | E6: CHARSET | I6: utf8mb4
B7: 備考
A12: カラム情報 | L12: 外部キー情報
A13: No | B13: 論理名 | C13: 物理名 | D13: データ型 | E13: Size | F13: Not Null | G13: PK | H13: UK | I13: デフォルト | J13: 備考 | L13: 親テーブル | M13: 参照カラム
A14: 1 | B14: 社員連番 | C14: syainseq | D14: bigint | F14: not null | G14: 〇
A15: 2 | B15: 支給区分 | C15: payment_type | D15: tinyint | F15: not null | G15: 〇
A16: 3 | B16: 備考 | C16: note | D16: text
A17: 4 | B17: 作成者 | C17: created_by | D17: bigint | F17: not null
A18: 5 | B18: 作成日時 | C18: created_at | D18: datetime | E18: 6 | F18: not null
A19: 6 | B19: 更新者 | C19: updated_by | D19: bigint | F19: not null
A20: 7 | B20: 更新日時 | C20: updated_at | D20: datetime | E20: 6 | F20: not null

Sheet 給与税率乙欄所得税額
A1: テーブル情報
B2: システム名 | C2: SOCIA | E2: 作成者 | I2: ITSP | M2: テーブル一覧へ
B3: サブシステム名 | C3: 給与 | E3: 作成日 | I3: 2025-11-28
B4: スキーマ名 | E4: RDBMS | I4: MySQL
B5: 論理テーブル名 | C5: 給与税率乙欄所得税額 | E5: ENGINE | I5: InnoDB
B6: 物理テーブル名 | C6: kyuyo_tax_otsu_income_tax | E6: CHARSET | I6: utf8mb4
B7: 備考
A12: カラム情報 | L12: 外部キー情報
A13: No | B13: 論理名 | C13: 物理名 | D13: データ型 | E13: Size | F13: Not Null | G13: PK | H13: UK | I13: デフォルト | J13: 備考 | L13: 親テーブル | M13: 参照カラム
A14: 1 | B14: 等級 | C14: grade | D14: smallint | F14: not null | G14: 〇
A15: 2 | B15: 給与額 | C15: kyuyo_amount | D15: bigint | F15: not null | G15: 〇
A16: 3 | B16: 有効開始年月日 | C16: fromymd | D16: date | F16: not null | G16: 〇
A17: 4 | B17: 有効終了年月日 | C17: toymd | D17: date | F17: not null
A18: 5 | B18: 控除額 | C18: deduction_amount | D18: bigint
A19: 6 | B19: 比率 | C19: rate | D19: decimal | E19: 8,4
A20: 7 | B20: 税額 | C20: tax_amount | D20: bigint
A21: 8 | B21: 作成者 | C21: created_by | D21: bigint | F21: not null
A22: 9 | B22: 作成日時 | C22: created_at | D22: datetime | E22: 6 | F22: not null
A23: 10 | B23: 更新者 | C23: updated_by | D23: bigint | F23: not null
A24: 11 | B24: 更新日時 | C24: updated_at | D24: datetime | E24: 6 | F24: not null

Sheet 給与税率日額丙欄
A1: テーブル情報
B2: システム名 | C2: SOCIA | E2: 作成者 | I2: ITSP | M2: テーブル一覧へ
B3: サブシステム名 | C3: 給与 | E3: 作成日 | I3: 2025-11-28
B4: スキーマ名 | E4: RDBMS | I4: MySQL
B5: 論理テーブル名 | C5: 給与税率日額丙欄 | E5: ENGINE | I5: InnoDB
B6: 物理テーブル名 | C6: kyuyo_tax_day_amount_hei | E6: CHARSET | I6: utf8mb4
B7: 備考
A12: カラム情報 | L12: 外部キー情報
A13: No | B13: 論理名 | C13: 物理名 | D13: データ型 | E13: Size | F13: Not Null | G13: PK | H13: UK | I13: デフォルト | J13: 備考 | L13: 親テーブル | M13: 参照カラム
A14: 1 | B14: 等級 | C14: grade | D14: smallint | F14: not null | G14: 〇
A15: 2 | B15: 給与額 | C15: kyuyo_amount | D15: bigint | F15: not null | G15: 〇
A16: 3 | B16: 有効開始年月日 | C16: fromymd | D16: date | F16: not null | G16: 〇
A17: 4 | B17: 有効終了年月日 | C17: toymd | D17: date | F17: not null
A18: 5 | B18: 控除額 | C18: deduction_amount | D18: bigint
A19: 6 | B19: 比率 | C19: rate | D19: decimal | E19: 8,4
A20: 7 | B20: 税額 | C20: tax_amount | D20: bigint
A21: 8 | B21: 作成者 | C21: created_by | D21: bigint | F21: not null
A22: 9 | B22: 作成日時 | C22: created_at | D22: datetime | E22: 6 | F22: not null
A23: 10 | B23: 更新者 | C23: updated_by | D23: bigint | F23: not null
A24: 11 | B24: 更新日時 | C24: updated_at | D24: datetime | E24: 6 | F24: not null

Sheet 給与税率日額乙欄
A1: テーブル情報
B2: システム名 | C2: SOCIA | E2: 作成者 | I2: ITSP | M2: テーブル一覧へ
B3: サブシステム名 | C3: 給与 | E3: 作成日 | I3: 2025-11-28
B4: スキーマ名 | E4: RDBMS | I4: MySQL
B5: 論理テーブル名 | C5: 給与税率日額乙欄 | E5: ENGINE | I5: InnoDB
B6: 物理テーブル名 | C6: kyuyo_tax_day_amount_otsu | E6: CHARSET | I6: utf8mb4
B7: 備考
A12: カラム情報 | L12: 外部キー情報
A13: No | B13: 論理名 | C13: 物理名 | D13: データ型 | E13: Size | F13: Not Null | G13: PK | H13: UK | I13: デフォルト | J13: 備考 | L13: 親テーブル | M13: 参照カラム
A14: 1 | B14: 等級 | C14: grade | D14: smallint | F14: not null | G14: 〇
A15: 2 | B15: 給与額 | C15: kyuyo_amount | D15: bigint | F15: not null | G15: 〇
A16: 3 | B16: 有効開始年月日 | C16: fromymd | D16: date | F16: not null | G16: 〇
A17: 4 | B17: 有効終了年月日 | C17: toymd | D17: date | F17: not null
A18: 5 | B18: 控除額 | C18: deduction_amount | D18: bigint
A19: 6 | B19: 比率 | C19: rate | D19: decimal | E19: 8,4
A20: 7 | B20: 税額 | C20: tax_amount | D20: bigint
A21: 8 | B21: 作成者 | C21: created_by | D21: bigint | F21: not null
A22: 9 | B22: 作成日時 | C22: created_at | D22: datetime | E22: 6 | F22: not null
A23: 10 | B23: 更新者 | C23: updated_by | D23: bigint | F23: not null
A24: 11 | B24: 更新日時 | C24: updated_at | D24: datetime | E24: 6 | F24: not null

Sheet 給与税率日額甲欄
A1: テーブル情報
B2: システム名 | C2: SOCIA | E2: 作成者 | I2: ITSP | M2: テーブル一覧へ
B3: サブシステム名 | C3: 給与 | E3: 作成日 | I3: 2025-11-28
B4: スキーマ名 | E4: RDBMS | I4: MySQL
B5: 論理テーブル名 | C5: 給与税率日額甲欄 | E5: ENGINE | I5: InnoDB
B6: 物理テーブル名 | C6: kyuyo_tax_day_amount_ko | E6: CHARSET | I6: utf8mb4
B7: 備考
A12: カラム情報 | L12: 外部キー情報
A13: No | B13: 論理名 | C13: 物理名 | D13: データ型 | E13: Size | F13: Not Null | G13: PK | H13: UK | I13: デフォルト | J13: 備考 | L13: 親テーブル | M13: 参照カラム
A14: 1 | B14: 等級 | C14: grade | D14: smallint | F14: not null | G14: 〇
A15: 2 | B15: 給与額 | C15: kyuyo_amount | D15: bigint | F15: not null | G15: 〇
A16: 3 | B16: 有効開始年月日 | C16: fromymd | D16: date | F16: not null | G16: 〇
A17: 4 | B17: 有効終了年月日 | C17: toymd | D17: date | F17: not null
A18: 5 | B18: 控除額 | C18: deduction_amount | D18: bigint
A19: 6 | B19: 比率 | C19: rate | D19: decimal | E19: 8,4
A20: 7 | B20: 税額０ | C20: tax_amount0 | D20: bigint
A21: 8 | B21: 税額１ | C21: tax_amount1 | D21: bigint
A22: 9 | B22: 税額２ | C22: tax_amount2 | D22: bigint
A23: 10 | B23: 税額３ | C23: tax_amount3 | D23: bigint
A24: 11 | B24: 税額４ | C24: tax_amount4 | D24: bigint
A25: 12 | B25: 税額５ | C25: tax_amount5 | D25: bigint
A26: 13 | B26: 税額６ | C26: tax_amount6 | D26: bigint
A27: 14 | B27: 税額７ | C27: tax_amount7 | D27: bigint
